Workbook
Name Slicer_smoker: #N/A
Name Slicer_Weight_Status: #N/A

Sheet OG Customer Names
A1: Customer ID | B1: name
A2: Id1 | B2: Hawks, Ms. Kelly
A3: Id2 | B3: Lehner, Mr. Matthew D
A4: Id3 | B4: Lu, Mr. Phil
A5: Id4 | B5: Osborne, Ms. Kelsey
A6: Id5 | B6: Kadala, Ms. Kristyn
A7: Id6 | B7: Baker, Mr. Russell B.
A8: Id7 | B8: Macpherson, Mr. Scott
A9: Id8 | B9: Hallman, Mr. Stephen
A10: Id9 | B10: Moran, Mr. Patrick R.
A11: Id10 | B11: Benner, Ms. Brooke N.
A12: Id11 | B12: Fierro Vargas, Ms. Paola Andrea
... A2336: Id2335 | B2336: German, Mr. Aaron K

Sheet OG Hospitalisation Details
A1: Customer ID | B1: year | C1: month | D1: date | E1: children | F1: charges | G1: Hospital tier | H1: City tier | I1: State ID
A2: Id2335 | B2: 1992 | C2: Jul | D2: 9 | E2: 0 | F2: 563.84 | G2: tier - 2 | H2: tier - 3 | I2: R1013
A3: Id2334 | B3: 1992 | C3: Nov | D3: 30 | E3: 0 | F3: 570.62 | G3: tier - 2 | H3: tier - 1 | I3: R1013
A4: Id2333 | B4: 1993 | C4: Jun | D4: 30 | E4: 0 | F4: 600 | G4: tier - 2 | H4: tier - 1 | I4: R1013
A5: Id2332 | B5: 1992 | C5: Sep | D5: 13 | E5: 0 | F5: 604.54 | G5: tier - 3 | H5: tier - 3 | I5: R1013
A6: Id2331 | B6: 1998 | C6: Jul | D6: 27 | E6: 0 | F6: 637.26 | G6: tier - 3 | H6: tier - 3 | I6: R1013
A7: Id2330 | B7: 2001 | C7: Nov | D7: 20 | E7: 0 | F7: 646.14 | G7: tier - 3 | H7: tier - 3 | I7: R1012
A8: Id2329 | B8: 1993 | C8: Jun | D8: 1 | E8: 0 | F8: 650 | G8: tier - 3 | H8: tier - 3 | I8: R1013
A9: Id2328 | B9: 1995 | C9: Jul | D9: 4 | E9: 0 | F9: 650 | G9: tier - 3 | H9: tier - 3 | I9: R1013
A10: Id2327 | B10: 2002 | C10: Nov | D10: 29 | E10: 0 | F10: 668 | G10: tier - 3 | H10: tier - 2 | I10: R1012
A11: Id2326 | B11: 1997 | C11: Nov | D11: 9 | E11: 0 | F11: 670 | G11: tier - 3 | H11: tier - 3 | I11: R1013
A12: Id2325 | B12: 2001 | C12: Sep | D12: 12 | E12: 0 | F12: 687.54 | G12: tier - 3 | H12: tier - 2 | I12: R1013
A13: Id2324 | B13: 1999 | C13: Dec | D13: 26 | E13: 0 | F13: 700 | G13: ? | H13: tier - 3 | I13: R1013
... A1050: Id1290 | B1050: 1977 | C1050: Jul | D1050: 26 | E1050: 2 | F1050: 8527.53 | G1050: tier - 2 | H1050: tier - 2 | I1050: R1013
A1051: Id1289 | B1051: ? | C1051: Jul | D1051: 24 | E1051: 0 | F1051: 8534.67 | G1051: tier - 2 | H1051: tier - 3 | I1051: R1024
A1052: Id1288 | B1052: 1981 | C1052: Dec | D1052: 27 | E1052: 3 | F1052: 8538.29 | G1052: tier - 2 | H1052: tier - 3 | I1052: R1024
A1053: Id1287 | B1053: 1975 | C1053: Nov | D1053: 6 | E1053: 1 | F1053: 8539.67 | G1053: tier - 2 | H1053: tier - 3 | I1053: R1011
A1054: Id1286 | B1054: ? | C1054: Dec | D1054: 12 | E1054: 1 | F1054: 8547.69 | G1054: tier - 2 | H1054: tier - 1 | I1054: R1013
A1055: Id1285 | B1055: 1975 | C1055: Aug | D1055: 6 | E1055: 1 | F1055: 8551.35 | G1055: tier - 2 | H1055: tier - 2 | I1055: R1011
A1056: Id1284 | B1056: 1975 | C1056: Aug | D1056: 21 | E1056: 1 | F1056: 8556.91 | G1056: tier - 2 | H1056: tier - 1 | I1056: R1011
A1057: Id1283 | B1057: 1988 | C1057: Sep | D1057: 21 | E1057: 3 | F1057: 8567.25 | G1057: tier - 2 | H1057: tier - 1 | I1057: R1012
A1058: Id1282 | B1058: 1975 | C1058: Sep | D1058: 26 | E1058: 1 | F1058: 8569.86 | G1058: tier - 2 | H1058: tier - 3 | I1058: R1013
A1059: Id1281 | B1059: 1982 | C1059: Dec | D1059: 6 | E1059: 3 | F1059: 8572.04 | G1059: tier - 2 | H1059: tier - 2 | I1059: R1021
A1060: Id1280 | B1060: 1987 | C1060: Nov | D1060: 11 | E1060: 3 | F1060: 8573.3 | G1060: tier - 2 | H1060: tier - 2 | I1060: R1021
A1061: Id1279 | B1061: 1983 | C1061: Dec | D1061: 30 | E1061: 5 | F1061: 8582.3 | G1061: tier - 2 | H1061: tier - 1 | I1061: R1013
A1062: Id1278 | B1062: 1983 | C1062: Jul | D1062: 25 | E1062: 5 | F1062: 8596.83 | G1062: tier - 2 | H1062: tier - 3 | I1062: R1013
A1063: Id1277 | B1063: 1973 | C1063: Jul | D1063: 11 | E1063: 0 | F1063: 8601.33 | G1063: tier - 2 | H1063: tier - 1 | I1063: R1013
A1064: Id1276 | B1064: 1977 | C1064: Sep | D1064: 24 | E1064: 2 | F1064: 8603.82 | G1064: tier - 2 | H1064: tier - 1 | I1064: R1019
A1065: Id1275 | B1065: 1977 | C1065: Nov | D1065: 12 | E1065: 2 | F1065: 8604.48 | G1065: tier - 3 | H1065: tier - 2 | I1065: R1016
A1066: Id1274 | B1066: 1977 | C1066: Oct | D1066: 15 | E1066: 3 | F1066: 8605.36 | G1066: tier - 2 | H1066: tier - 2 | I1066: R1013
... A2344: Id1 | B2344: 1968 | C2344: Oct | D2344: 12 | E2344: 0 | F2344: 63770.43 | G2344: tier - 1 | H2344: tier - 3 | I2344: R1013

Sheet OG Medical Examinations
A1: Customer ID | B1: BMI | C1: HBA1C | D1: Heart Issues | E1: Any Transplants | F1: Cancer history | G1: NumberOfMajorSurgeries | H1: smoker
A2: Id1 | B2: 47.41 | C2: 7.47 | D2: No | E2: No | F2: No | G2: No major surgery | H2: yes
A3: Id2 | B3: 30.36 | C3: 5.77 | D3: No | E3: No | F3: No | G3: No major surgery | H3: yes
A4: Id3 | B4: 34.485 | C4: 11.87 | D4: yes | E4: No | F4: No | G4: 2 | H4: yes
A5: Id4 | B5: 38.095 | C5: 6.05 | D5: No | E5: No | F5: No | G5: No major surgery | H5: yes
A6: Id5 | B6: 35.53 | C6: 5.45 | D6: No | E6: No | F6: No | G6: No major surgery | H6: yes
A7: Id6 | B7: 32.8 | C7: 6.59 | D7: No | E7: No | F7: No | G7: No major surgery | H7: yes
A8: Id7 | B8: 36.4 | C8: 6.07 | D8: No | E8: No | F8: No | G8: No major surgery | H8: yes
A9: Id8 | B9: 36.96 | C9: 7.93 | D9: No | E9: No | F9: No | G9: 3 | H9: yes
A10: Id9 | B10: 41.14 | C10: 9.58 | D10: yes | E10: No | F10: Yes | G10: 1 | H10: yes
A11: Id10 | B11: 38.06 | C11: 10.79 | D11: No | E11: No | F11: No | G11: No major surgery | H11: yes
A12: Id11 | B12: 37.7 | C12: 5.96 | D12: yes | E12: No | F12: No | G12: 2 | H12: yes
A13: Id12 | B13: 42.13 | C13: 11.9 | D13: No | E13: No | F13: No | G13: No major surgery | H13: yes
A14: Id13 | B14: 40.92 | C14: 8.41 | D14: No | E14: No | F14: No | G14: No major surgery | H14: yes
A15: Id14 | B15: 40.565 | C15: 7.02 | D15: No | E15: No | F15: No | G15: No major surgery | H15: yes
A16: Id15 | B16: 36.385 | C16: 7.59 | D16: yes | E16: No | F16: No | G16: 2 | H16: yes
A17: Id16 | B17: 39.9 | C17: 11.32 | D17: No | E17: No | F17: No | G17: No major surgery | H17: yes
A18: Id17 | B18: 33.8 | C18: 7.67 | D18: No | E18: No | F18: No | G18: 3 | H18: yes
A19: Id18 | B19: 36.765 | C19: 7.29 | D19: yes | E19: No | F19: Yes | G19: 1 | H19: yes
A20: Id19 | B20: 36.955 | C20: 4.72 | D20: yes | E20: No | F20: No | G20: 1 | H20: yes
A21: Id20 | B21: 42.9 | C21: 11.41 | D21: No | E21: No | F21: No | G21: No major surgery | H21: yes
A22: Id21 | B22: 36.3 | C22: 11.5 | D22: yes | E22: No | F22: No | G22: 2 | H22: yes
A23: Id22 | B23: 32.2 | C23: 6.22 | D23: yes | E23: No | F23: No | G23: 2 | H23: yes
A24: Id23 | B24: 31.3 | C24: 11.38 | D24: No | E24: No | F24: No | G24: 3 | H24: yes
A25: Id24 | B25: 41.8 | C25: 7.89 | D25: yes | E25: No | F25: No | G25: 2 | H25: yes
A26: Id25 | B26: 35.09 | C26: 4.38 | D26: yes | E26: No | F26: No | G26: 2 | H26: yes
A27: Id26 | B27: 33.88 | C27: 7.01 | D27: No | E27: No | F27: No | G27: 3 | H27: yes
A28: Id27 | B28: 30.875 | C28: 11.88 | D28: No | E28: No | F28: No | G28: No major surgery | H28: yes
A29: Id28 | B29: 36.86 | C29: 5.19 | D29: yes | E29: No | F29: Yes | G29: 1 | H29: yes
A30: Id29 | B30: 35.86 | C30: 6.74 | D30: yes | E30: No | F30: No | G30: 2 | H30: yes
A31: Id30 | B31: 37.05 | C31: 8.44 | D31: No | E31: No | F31: No | G31: No major surgery | H31: yes
A32: Id31 | B32: 43.89 | C32: 8.71 | D32: No | E32: No | F32: No | G32: No major surgery | H32: yes
A33: Id32 | B33: 42.35 | C33: 5.08 | D33: yes | E33: No | F33: No | G33: No major surgery | H33: yes
A34: Id33 | B34: 31.35 | C34: 6.86 | D34: No | E34: No | F34: No | G34: No major surgery | H34: yes
A35: Id34 | B35: 47.6 | C35: 5.95 | D35: yes | E35: No | F35: No | G35: No major surgery | H35: yes
A36: Id35 | B36: 46.2 | C36: 6.09 | D36: No | E36: No | F36: Yes | G36: 1 | H36: yes
A37: Id36 | B37: 32.015 | C37: 11.75 | D37: No | E37: No | F37: No | G37: No major surgery | H37: yes
A38: Id37 | B38: 40.565 | C38: 7.37 | D38: No | E38: No | F38: No | G38: No major surgery | H38: yes
A39: Id38 | B39: 32.45 | C39: 11.91 | D39: No | E39: No | F39: No | G39: No major surgery | H39: yes
A40: Id39 | B40: 34.96 | C40: 6.52 | D40: No | E40: No | F40: No | G40: No major surgery | H40: yes
A41: Id40 | B41: 35.5 | C41: 5.14 | D41: No | E41: No | F41: Yes | G41: 1 | H41: yes
A42: Id41 | B42: 52.58 | C42: 4.19 | D42: No | E42: yes | F42: No | G42: 1 | H42: yes
A43: Id42 | B43: 35.2 | C43: 11.68 | D43: yes | E43: No | F43: No | G43: No major surgery | H43: yes
A44: Id43 | B44: 38.06 | C44: 6.98 | D44: No | E44: No | F44: No | G44: No major surgery | H44: yes
A45: Id44 | B45: 34.21 | C45: 8.34 | D45: No | E45: No | F45: No | G45: No major surgery | H45: yes
A46: Id45 | B46: 38.94 | C46: 8.49 | D46: yes | E46: No | F46: No | G46: 1 | H46: yes
A47: Id46 | B47: 30.21 | C47: 5.34 | D47: yes | E47: No | F47: No | G47: 1 | H47: yes
A48: Id47 | B48: 33.63 | C48: 4.43 | D48: yes | E48: No | F48: No | G48: 2 | H48: yes
A49: Id48 | B49: 40.37 | C49: 4.47 | D49: No | E49: No | F49: No | G49: No major surgery | H49: yes
A50: Id49 | B50: 53.09 | C50: 4.82 | D50: yes | E50: No | F50: No | G50: 2 | H50: yes
A51: Id50 | B51: 31.79 | C51: 5.51 | D51: yes | E51: No | F51: No | G51: 2 | H51: yes
A52: Id51 | B52: 41.895 | C52: 10.87 | D52: yes | E52: No | F52: No | G52: 1 | H52: yes
A53: Id52 | B53: 31.16 | C53: 9.34 | D53: No | E53: No | F53: No | G53: No major surgery | H53: yes
A54: Id53 | B54: 34.105 | C54: 5.03 | D54: yes | E54: No | F54: Yes | G54: 1 | H54: yes
A55: Id54 | B55: 51.93 | C55: 11.05 | D55: No | E55: No | F55: No | G55: No major surgery | H55: yes
A56: Id55 | B56: 38.95 | C56: 11.95 | D56: No | E56: No | F56: No | G56: No major surgery | H56: yes
A57: Id56 | B57: 36.63 | C57: 7.72 | D57: yes | E57: No | F57: No | G57: 1 | H57: yes
A58: Id57 | B58: 34.2 | C58: 5.75 | D58: No | E58: No | F58: No | G58: 2 | H58: yes
A59: Id58 | B59: 50.63 | C59: 11.89 | D59: No | E59: No | F59: No | G59: No major surgery | H59: yes
A60: Id59 | B60: 36.48 | C60: 6.2 | D60: No | E60: No | F60: No | G60: No major surgery | H60: yes
A61: Id60 | B61: 54.82 | C61: 10.61 | D61: No | E61: No | F61: No | G61: No major surgery | H61: yes
A62: Id61 | B62: 38.06 | C62: 6.04 | D62: No | E62: No | F62: Yes | G62: 1 | H62: yes
A63: Id62 | B63: 51.48 | C63: 9.33 | D63: yes | E63: No | F63: No | G63: No major surgery | H63: yes
A64: Id63 | B64: 52.06 | C64: 11.47 | D64: No | E64: No | F64: No | G64: No major surgery | H64: yes
A65: Id64 | B65: 30.685 | C65: 7.02 | D65: yes | E65: No | F65: No | G65: No major surgery | H65: yes
A66: Id65 | B66: 36.08 | C66: 8.8 | D66: yes | E66: No | F66: No | G66: 1 | H66: yes
A67: Id66 | B67: 54.99 | C67: 8.68 | D67: No | E67: No | F67: No | G67: 2 | H67: yes
A68: Id67 | B68: 35.97 | C68: 6.12 | D68: No | E68: No | F68: Yes | G68: 1 | H68: yes
A69: Id68 | B69: 45.54 | C69: 5.4 | D69: yes | E69: No | F69: Yes | G69: 1 | H69: yes
A70: Id69 | B70: 35.53 | C70: 4.36 | D70: yes | E70: No | F70: No | G70: No major surgery | H70: yes
A71: Id70 | B71: 30.8 | C71: 9.77 | D71: No | E71: No | F71: No | G71: No major surgery | H71: yes
A72: Id71 | B72: 38.39 | C72: 4.25 | D72: No | E72: No | F72: No | G72: 1 | H72: yes
A73: Id72 | B73: 32.3 | C73: 4.76 | D73: No | E73: No | F73: No | G73: 2 | H73: yes
A74: Id73 | B74: 48.8 | C74: 6.22 | D74: yes | E74: No | F74: No | G74: 2 | H74: yes
A75: Id74 | B75: 45.5 | C75: 7.96 | D75: No | E75: No | F75: No | G75: No major surgery | H75: yes
A76: Id75 | B76: 53.61 | C76: 10.92 | D76: yes | E76: No | F76: No | G76: 1 | H76: yes
A77: Id76 | B77: 36.19 | C77: 11.51 | D77: yes | E77: No | F77: No | G77: 1 | H77: yes
A78: Id77 | B78: 34.6 | C78: 5.99 | D78: yes | E78: No | F78: No | G78: No major surgery | H78: yes
A79: Id78 | B79: 54.12 | C79: 11.57 | D79: No | E79: No | F79: No | G79: No major surgery | H79: yes
A80: Id79 | B80: 48.82 | C80: 6.67 | D80: yes | E80: No | F80: No | G80: No major surgery | H80: yes
A81: Id80 | B81: 51.01 | C81: 9.2 | D81: No | E81: No | F81: No | G81: No major surgery | H81: yes
A82: Id81 | B82: 45.65 | C82: 5.11 | D82: yes | E82: No | F82: No | G82: 1 | H82: yes
A83: Id82 | B83: 52.9 | C83: 5.34 | D83: No | E83: No | F83: No | G83: No major surgery | H83: yes
A84: Id83 | B84: 45.41 | C84: 4.03 | D84: yes | E84: No | F84: No | G84: 1 | H84: yes
A85: Id84 | B85: 49.41 | C85: 4.23 | D85: yes | E85: No | F85: Yes | G85: 1 | H85: yes
A86: Id85 | B86: 31.825 | C86: 4.06 | D86: No | E86: No | F86: No | G86: 2 | H86: yes
A87: Id86 | B87: 51.28 | C87: 4.68 | D87: No | E87: No | F87: No | G87: 2 | H87: yes
A88: Id87 | B88: 34.96 | C88: 4.34 | D88: No | E88: No | F88: Yes | G88: 1 | H88: yes
A89: Id88 | B89: 33.11 | C89: 10.51 | D89: No | E89: No | F89: No | G89: No major surgery | H89: yes
A90: Id89 | B90: 54.74 | C90: 5.84 | D90: yes | E90: No | F90: Yes | G90: 1 | H90: yes
A91: Id90 | B91: 32.56 | C91: 5.41 | D91: No | E91: No | F91: Yes | G91: 1 | H91: yes
A92: Id91 | B92: 39.05 | C92: 6.06 | D92: No | E92: No | F92: No | G92: 1 | H92: yes
A93: Id92 | B93: 42.75 | C93: 4.22 | D93: No | E93: No | F93: No | G93: No major surgery | H93: yes
A94: Id93 | B94: 50.58 | C94: 5.12 | D94: No | E94: No | F94: No | G94: 2 | H94: yes
A95: Id94 | B95: 30.495 | C95: 4.57 | D95: yes | E95: No | F95: No | G95: No major surgery | H95: yes
A96: Id95 | B96: 48.31 | C96: 9.58 | D96: yes | E96: No | F96: No | G96: 2 | H96: yes
A97: Id96 | B97: 48.99 | C97: 9.78 | D97: yes | E97: No | F97: No | G97: 1 | H97: yes
A98: Id97 | B98: 38.39 | C98: 4.11 | D98: yes | E98: No | F98: No | G98: No major surgery | H98: yes
A99: Id98 | B99: 44.34 | C99: 4.02 | D99: yes | E99: No | F99: No | G99: 2 | H99: yes
A100: Id99 | B100: 41.51 | C100: 6.92 | D100: No | E100: No | F100: No | G100: No major surgery | H100: yes
...

Sheet Dashboard
A1: Healthcare Dashboard – AI Analysis | M1: Healthcare Statistics
M2: Total customers count | N2: =COUNTA(Table1[[#Data],[#Totals],[Customer ID]]) -> 2336
M3: Total Healthcare Costs | N3: =SUM(Table1[charges]) -> 31592359
M4: Average Charges | N4: =AVERAGE(Table1[[#Data],[#Totals],[charges]]) -> 13529.918
M5: Average BMI | N5: =AVERAGE(Table1[BMI]) -> 30.972649
M6: Average HBA1C | N6: =AVERAGE(Table1[HBA1C]) -> 6.5789979
M7: Average Age | N7: =AVERAGE(Table1[Age]) -> 39.228694
M8: Total hospitalisation count | N8: =COUNTA(Table1[[#Data],[#Totals],[Customer ID]]) -> 2336

Sheet Cancer History
A3: Count of Customer ID | B3: Column Labels
A4: Row Labels | B4: No | C4: Yes | D4: Grand Total
A5: No | B5: 1539 | C5: 307 | D5: 1846
A6: Yes | B6: 405 | C6: 84 | D6: 489
A7: Grand Total | B7: 1944 | C7: 391 | D7: 2335

Sheet Weight Status
A3: Row Labels | B3: Sum of charges
A4: Normal Weight | B4: 4305290.1
A5: Obesity | B5: 20343647
A6: Overweight | B6: 5729141.8
A7: Underweight | B7: 1214279.9
A8: Grand Total | B8: 31592359

Sheet Healthcare
A1: Customer ID | B1: First Name | C1: BMI | D1: HBA1C | E1: Heart Issues | F1: Any Transplants | G1: Cancer history | H1: NumberOfMajorSurgeries | I1: smoker | J1: Weight Status | K1: Date of Birth | L1: charges | M1: Hospital tier | N1: City tier | O1: State ID | P1: Age | R1: Healthcare Statistics
A2: Id1 | B2: =_xlfn.XLOOKUP(A2,'Customer Names'!A:A,'Customer Names'!C:C,"Not Found") -> Hawks | C2: =_xlfn.XLOOKUP($A$2,'Medical Examinations'!$A:$A,'Medical Examinations'!B:B,"not found") -> 47.41 | D2: =_xlfn.XLOOKUP(A2,'Medical Examinations'!A:A,'Medical Examinations'!C:C,"not found") -> 7.47 | E2: =_xlfn.XLOOKUP(A2,'Medical Examinations'!A:A,'Medical Examinations'!D:D,"not found") -> No | F2: =_xlfn.XLOOKUP(A2,'Medical Examinations'!A:A,'Medical Examinations'!E:E,"not found") -> No | G2: =_xlfn.XLOOKUP(A2,'Medical Examinations'!A:A,'Medical Examinations'!F:F,"not found") -> No | H2: =_xlfn.XLOOKUP(A2,'Medical Examinations'!A:A,'Medical Examinations'!G:G,"not found") -> 0 | I2: =_xlfn.XLOOKUP(A2,'Medical Examinations'!A:A,'Medical Examinations'!H:H,"not found") -> Yes | J2: =_xlfn.XLOOKUP(A2,'Medical Examinations'!A:A,'Medical Examinations'!I:I,"not found") -> Obesity | K2: =_xlfn.XLOOKUP($A$2,'Hospitalisation Details'!$A:$A,'Hospitalisation Details'!F:F,"Not Found") -> 25123 | L2: =_xlfn.XLOOKUP(A2,'Hospitalisation Details'!A:A,'Hospitalisation Details'!H:H,"Not Found") -> 63770.43 | M2: =_xlfn.XLOOKUP(A2,'Hospitalisation Details'!A:A,'Hospitalisation Details'!I:I,"Not Found") -> tier - 1 | N2: =_xlfn.XLOOKUP(A2,'Hospitalisation Details'!A:A,'Hospitalisation Details'!J:J,"Not Found") -> tier - 3 | O2: =_xlfn.XLOOKUP(A2,'Hospitalisation Details'!A:A,'Hospitalisation Details'!K:K,"Not Found") -> R1013 | P2: =_xlfn.XLOOKUP(A2,'Hospitalisation Details'!A:A,'Hospitalisation Details'!L:L,"Not Found") -> 54 | R2: Total customers count | S2: =COUNTA(Table1[[#Data],[#Totals],[Customer ID]]) -> 2336
A3: Id2 | B3: =_xlfn.XLOOKUP(A3,'Customer Names'!A:A,'Customer Names'!C:C,"Not Found") -> Lehner | C3: =_xlfn.XLOOKUP(A3,'Medical Examinations'!A:A,'Medical Examinations'!B:B,"not found") -> 30.36 | D3: =_xlfn.XLOOKUP(A3,'Medical Examinations'!A:A,'Medical Examinations'!C:C,"not found") -> 5.77 | E3: =_xlfn.XLOOKUP(A3,'Medical Examinations'!A:A,'Medical Examinations'!D:D,"not found") -> No | F3: =_xlfn.XLOOKUP(A3,'Medical Examinations'!A:A,'Medical Examinations'!E:E,"not found") -> No | G3: =_xlfn.XLOOKUP(A3,'Medical Examinations'!A:A,'Medical Examinations'!F:F,"not found") -> No | H3: =_xlfn.XLOOKUP(A3,'Medical Examinations'!A:A,'Medical Examinations'!G:G,"not found") -> 0 | I3: =_xlfn.XLOOKUP(A3,'Medical Examinations'!A:A,'Medical Examinations'!H:H,"not found") -> Yes | J3: =_xlfn.XLOOKUP(A3,'Medical Examinations'!A:A,'Medical Examinations'!I:I,"not found") -> Obesity | K3: =_xlfn.XLOOKUP(A3,'Hospitalisation Details'!A:A,'Hospitalisation Details'!F:F,"Not Found") -> 28284 | L3: =_xlfn.XLOOKUP(A3,'Hospitalisation Details'!A:A,'Hospitalisation Details'!H:H,"Not Found") -> 62592.87 | M3: =_xlfn.XLOOKUP(A3,'Hospitalisation Details'!A:A,'Hospitalisation Details'!I:I,"Not Found") -> tier - 1 | N3: =_xlfn.XLOOKUP(A3,'Hospitalisation Details'!A:A,'Hospitalisation Details'!J:J,"Not Found") -> tier - 3 | O3: =_xlfn.XLOOKUP(A3,'Hospitalisation Details'!A:A,'Hospitalisation Details'!K:K,"Not Found") -> R1013 | P3: =_xlfn.XLOOKUP(A3,'Hospitalisation Details'!A:A,'Hospitalisation Details'!L:L,"Not Found") -> 46 | R3: Total Healthcare Costs | S3: =SUM(Table1[charges]) -> 31592359
A4: Id3 | B4: =_xlfn.XLOOKUP(A4,'Customer Names'!A:A,'Customer Names'!C:C,"Not Found") -> Lu | C4: =_xlfn.XLOOKUP(A4,'Medical Examinations'!A:A,'Medical Examinations'!B:B,"not found") -> 34.485 | D4: =_xlfn.XLOOKUP(A4,'Medical Examinations'!A:A,'Medical Examinations'!C:C,"not found") -> 11.87 | E4: =_xlfn.XLOOKUP(A4,'Medical Examinations'!A:A,'Medical Examinations'!D:D,"not found") -> Yes | F4: =_xlfn.XLOOKUP(A4,'Medical Examinations'!A:A,'Medical Examinations'!E:E,"not found") -> No | G4: =_xlfn.XLOOKUP(A4,'Medical Examinations'!A:A,'Medical Examinations'!F:F,"not found") -> No | H4: =_xlfn.XLOOKUP(A4,'Medical Examinations'!A:A,'Medical Examinations'!G:G,"not found") -> 2 | I4: =_xlfn.XLOOKUP(A4,'Medical Examinations'!A:A,'Medical Examinations'!H:H,"not found") -> Yes | J4: =_xlfn.XLOOKUP(A4,'Medical Examinations'!A:A,'Medical Examinations'!I:I,"not found") -> Obesity | K4: =_xlfn.XLOOKUP(A4,'Hospitalisation Details'!A:A,'Hospitalisation Details'!F:F,"Not Found") -> 25822 | L4: =_xlfn.XLOOKUP(A4,'Hospitalisation Details'!A:A,'Hospitalisation Details'!H:H,"Not Found") -> 60021.4 | M4: =_xlfn.XLOOKUP(A4,'Hospitalisation Details'!A:A,'Hospitalisation Details'!I:I,"Not Found") -> tier - 1 | N4: =_xlfn.XLOOKUP(A4,'Hospitalisation Details'!A:A,'Hospitalisation Details'!J:J,"Not Found") -> tier - 3 | O4: =_xlfn.XLOOKUP(A4,'Hospitalisation Details'!A:A,'Hospitalisation Details'!K:K,"Not Found") -> R1012 | P4: =_xlfn.XLOOKUP(A4,'Hospitalisation Details'!A:A,'Hospitalisation Details'!L:L,"Not Found") -> 52 | R4: Average Charges | S4: =AVERAGE(Table1[[#Data],[#Totals],[charges]]) -> 13529.918
A5: Id4 | B5: =_xlfn.XLOOKUP(A5,'Customer Names'!A:A,'Customer Names'!C:C,"Not Found") -> Osborne | C5: =_xlfn.XLOOKUP(A5,'Medical Examinations'!A:A,'Medical Examinations'!B:B,"not found") -> 38.095 | D5: =_xlfn.XLOOKUP(A5,'Medical Examinations'!A:A,'Medical Examinations'!C:C,"not found") -> 6.05 | E5: =_xlfn.XLOOKUP(A5,'Medical Examinations'!A:A,'Medical Examinations'!D:D,"not found") -> No | F5: =_xlfn.XLOOKUP(A5,'Medical Examinations'!A:A,'Medical Examinations'!E:E,"not found") -> No | G5: =_xlfn.XLOOKUP(A5,'Medical Examinations'!A:A,'Medical Examinations'!F:F,"not found") -> No | H5: =_xlfn.XLOOKUP(A5,'Medical Examinations'!A:A,'Medical Examinations'!G:G,"not found") -> 0 | I5: =_xlfn.XLOOKUP(A5,'Medical Examinations'!A:A,'Medical Examinations'!H:H,"not found") -> Yes | J5: =_xlfn.XLOOKUP(A5,'Medical Examinations'!A:A,'Medical Examinations'!I:I,"not found") -> Obesity | K5: =_xlfn.XLOOKUP(A5,'Hospitalisation Details'!A:A,'Hospitalisation Details'!F:F,"Not Found") -> 33395 | L5: =_xlfn.XLOOKUP(A5,'Hospitalisation Details'!A:A,'Hospitalisation Details'!H:H,"Not Found") -> 58571.07 | M5: =_xlfn.XLOOKUP(A5,'Hospitalisation Details'!A:A,'Hospitalisation Details'!I:I,"Not Found") -> tier - 1 | N5: =_xlfn.XLOOKUP(A5,'Hospitalisation Details'!A:A,'Hospitalisation Details'!J:J,"Not Found") -> tier - 3 | O5: =_xlfn.XLOOKUP(A5,'Hospitalisation Details'!A:A,'Hospitalisation Details'!K:K,"Not Found") -> R1024 | P5: =_xlfn.XLOOKUP(A5,'Hospitalisation Details'!A:A,'Hospitalisation Details'!L:L,"Not Found") -> 32 | R5: Average BMI | S5: =AVERAGE(Table1[BMI]) -> 30.972649
A6: Id5 | B6: =_xlfn.XLOOKUP(A6,'Customer Names'!A:A,'Customer Names'!C:C,"Not Found") -> Kadala | C6: =_xlfn.XLOOKUP(A6,'Medical Examinations'!A:A,'Medical Examinations'!B:B,"not found") -> 35.53 | D6: =_xlfn.XLOOKUP(A6,'Medical Examinations'!A:A,'Medical Examinations'!C:C,"not found") -> 5.45 | E6: =_xlfn.XLOOKUP(A6,'Medical Examinations'!A:A,'Medical Examinations'!D:D,"not found") -> No | F6: =_xlfn.XLOOKUP(A6,'Medical Examinations'!A:A,'Medical Examinations'!E:E,"not found") -> No | G6: =_xlfn.XLOOKUP(A6,'Medical Examinations'!A:A,'Medical Examinations'!F:F,"not found") -> No | H6: =_xlfn.XLOOKUP(A6,'Medical Examinations'!A:A,'Medical Examinations'!G:G,"not found") -> 0 | I6: =_xlfn.XLOOKUP(A6,'Medical Examinations'!A:A,'Medical Examinations'!H:H,"not found") -> Yes | J6: =_xlfn.XLOOKUP(A6,'Medical Examinations'!A:A,'Medical Examinations'!I:I,"not found") -> Obesity | K6: =_xlfn.XLOOKUP(A6,'Hospitalisation Details'!A:A,'Hospitalisation Details'!F:F,"Not Found") -> 32678 | L6: =_xlfn.XLOOKUP(A6,'Hospitalisation Details'!A:A,'Hospitalisation Details'!H:H,"Not Found") -> 55135.4 | M6: =_xlfn.XLOOKUP(A6,'Hospitalisation Details'!A:A,'Hospitalisation Details'!I:I,"Not Found") -> tier - 1 | N6: =_xlfn.XLOOKUP(A6,'Hospitalisation Details'!A:A,'Hospitalisation Details'!J:J,"Not Found") -> tier - 3 | O6: =_xlfn.XLOOKUP(A6,'Hospitalisation Details'!A:A,'Hospitalisation Details'!K:K,"Not Found") -> R1012 | P6: =_xlfn.XLOOKUP(A6,'Hospitalisation Details'!A:A,'Hospitalisation Details'!L:L,"Not Found") -> 33 | R6: Average HBA1C | S6: =AVERAGE(Table1[HBA1C]) -> 6.5789979
A7: Id6 | B7: =_xlfn.XLOOKUP(A7,'Customer Names'!A:A,'Customer Names'!C:C,"Not Found") -> Baker | C7: =_xlfn.XLOOKUP(A7,'Medical Examinations'!A:A,'Medical Examinations'!B:B,"not found") -> 32.8 | D7: =_xlfn.XLOOKUP(A7,'Medical Examinations'!A:A,'Medical Examinations'!C:C,"not found") -> 6.59 | E7: =_xlfn.XLOOKUP(A7,'Medical Examinations'!A:A,'Medical Examinations'!D:D,"not found") -> No | F7: =_xlfn.XLOOKUP(A7,'Medical Examinations'!A:A,'Medical Examinations'!E:E,"not found") -> No | G7: =_xlfn.XLOOKUP(A7,'Medical Examinations'!A:A,'Medical Examinations'!F:F,"not found") -> No | H7: =_xlfn.XLOOKUP(A7,'Medical Examinations'!A:A,'Medical Examinations'!G:G,"not found") -> 0 | I7: =_xlfn.XLOOKUP(A7,'Medical Examinations'!A:A,'Medical Examinations'!H:H,"not found") -> Yes | J7: =_xlfn.XLOOKUP(A7,'Medical Examinations'!A:A,'Medical Examinations'!I:I,"not found") -> Obesity | K7: =_xlfn.XLOOKUP(A7,'Hospitalisation Details'!A:A,'Hospitalisation Details'!F:F,"Not Found") -> 22862 | L7: =_xlfn.XLOOKUP(A7,'Hospitalisation Details'!A:A,'Hospitalisation Details'!H:H,"Not Found") -> 52590.83 | M7: =_xlfn.XLOOKUP(A7,'Hospitalisation Details'!A:A,'Hospitalisation Details'!I:I,"Not Found") -> tier - 1 | N7: =_xlfn.XLOOKUP(A7,'Hospitalisation Details'!A:A,'Hospitalisation Details'!J:J,"Not Found") -> tier - 3 | O7: =_xlfn.XLOOKUP(A7,'Hospitalisation Details'!A:A,'Hospitalisation Details'!K:K,"Not Found") -> R1011 | P7: =_xlfn.XLOOKUP(A7,'Hospitalisation Details'!A:A,'Hospitalisation Details'!L:L,"Not Found") -> 60 | R7: Average Age | S7: =AVERAGE(Table1[Age]) -> 39.228694
A8: Id7 | B8: =_xlfn.XLOOKUP(A8,'Customer Names'!A:A,'Customer Names'!C:C,"Not Found") -> Macpherson | C8: =_xlfn.XLOOKUP(A8,'Medical Examinations'!A:A,'Medical Examinations'!B:B,"not found") -> 36.4 | D8: =_xlfn.XLOOKUP(A8,'Medical Examinations'!A:A,'Medical Examinations'!C:C,"not found") -> 6.07 | E8: =_xlfn.XLOOKUP(A8,'Medical Examinations'!A:A,'Medical Examinations'!D:D,"not found") -> No | F8: =_xlfn.XLOOKUP(A8,'Medical Examinations'!A:A,'Medical Examinations'!E:E,"not found") -> No | G8: =_xlfn.XLOOKUP(A8,'Medical Examinations'!A:A,'Medical Examinations'!F:F,"not found") -> No | H8: =_xlfn.XLOOKUP(A8,'Medical Examinations'!A:A,'Medical Examinations'!G:G,"not found") -> 0 | I8: =_xlfn.XLOOKUP(A8,'Medical Examinations'!A:A,'Medical Examinations'!H:H,"not found") -> Yes | J8: =_xlfn.XLOOKUP(A8,'Medical Examinations'!A:A,'Medical Examinations'!I:I,"not found") -> Obesity | K8: =_xlfn.XLOOKUP(A8,'Hospitalisation Details'!A:A,'Hospitalisation Details'!F:F,"Not Found") -> 34634 | L8: =_xlfn.XLOOKUP(A8,'Hospitalisation Details'!A:A,'Hospitalisation Details'!H:H,"Not Found") -> 51194.56 | M8: =_xlfn.XLOOKUP(A8,'Hospitalisation Details'!A:A,'Hospitalisation Details'!I:I,"Not Found") -> tier - 1 | N8: =_xlfn.XLOOKUP(A8,'Hospitalisation Details'!A:A,'Hospitalisation Details'!J:J,"Not Found") -> tier - 3 | O8: =_xlfn.XLOOKUP(A8,'Hospitalisation Details'!A:A,'Hospitalisation Details'!K:K,"Not Found") -> R1011 | P8: =_xlfn.XLOOKUP(A8,'Hospitalisation Details'!A:A,'Hospitalisation Details'!L:L,"Not Found") -> 28 | R8: Total hospitalisation count | S8: =COUNTA(Table1[[#Data],[#Totals],[Customer ID]]) -> 2336
A9: Id8 | B9: =_xlfn.XLOOKUP(A9,'Customer Names'!A:A,'Customer Names'!C:C,"Not Found") -> Hallman | C9: =_xlfn.XLOOKUP(A9,'Medical Examinations'!A:A,'Medical Examinations'!B:B,"not found") -> 36.96 | D9: =_xlfn.XLOOKUP(A9,'Medical Examinations'!A:A,'Medical Examinations'!C:C,"not found") -> 7.93 | E9: =_xlfn.XLOOKUP(A9,'Medical Examinations'!A:A,'Medical Examinations'!D:D,"not found") -> No | F9: =_xlfn.XLOOKUP(A9,'Medical Examinations'!A:A,'Medical Examinations'!E:E,"not found") -> No | G9: =_xlfn.XLOOKUP(A9,'Medical Examinations'!A:A,'Medical Examinations'!F:F,"not found") -> No | H9: =_xlfn.XLOOKUP(A9,'Medical Examinations'!A:A,'Medical Examinations'!G:G,"not found") -> 3 | I9: =_xlfn.XLOOKUP(A9,'Medical Examinations'!A:A,'Medical Examinations'!H:H,"not found") -> Yes | J9: =_xlfn.XLOOKUP(A9,'Medical Examinations'!A:A,'Medical Examinations'!I:I,"not found") -> Obesity | K9: =_xlfn.XLOOKUP(A9,'Hospitalisation Details'!A:A,'Hospitalisation Details'!F:F,"Not Found") -> 21363 | L9: =_xlfn.XLOOKUP(A9,'Hospitalisation Details'!A:A,'Hospitalisation Details'!H:H,"Not Found") -> 49577.66 | M9: =_xlfn.XLOOKUP(A9,'Hospitalisation Details'!A:A,'Hospitalisation Details'!I:I,"Not Found") -> tier - 1 | N9: =_xlfn.XLOOKUP(A9,'Hospitalisation Details'!A:A,'Hospitalisation Details'!J:J,"Not Found") -> tier - 3 | O9: =_xlfn.XLOOKUP(A9,'Hospitalisation Details'!A:A,'Hospitalisation Details'!K:K,"Not Found") -> R1013 | P9: =_xlfn.XLOOKUP(A9,'Hospitalisation Details'!A:A,'Hospitalisation Details'!L:L,"Not Found") -> 64
A10: Id9 | B10: =_xlfn.XLOOKUP(A10,'Customer Names'!A:A,'Customer Names'!C:C,"Not Found") -> Moran | C10: =_xlfn.XLOOKUP(A10,'Medical Examinations'!A:A,'Medical Examinations'!B:B,"not found") -> 41.14 | D10: =_xlfn.XLOOKUP(A10,'Medical Examinations'!A:A,'Medical Examinations'!C:C,"not found") -> 9.58 | E10: =_xlfn.XLOOKUP(A10,'Medical Examinations'!A:A,'Medical Examinations'!D:D,"not found") -> Yes | F10: =_xlfn.XLOOKUP(A10,'Medical Examinations'!A:A,'Medical Examinations'!E:E,"not found") -> No | G10: =_xlfn.XLOOKUP(A10,'Medical Examinations'!A:A,'Medical Examinations'!F:F,"not found") -> Yes | H10: =_xlfn.XLOOKUP(A10,'Medical Examinations'!A:A,'Medical Examinations'!G:G,"not found") -> 1 | I10: =_xlfn.XLOOKUP(A10,'Medical Examinations'!A:A,'Medical Examinations'!H:H,"not found") -> Yes | J10: =_xlfn.XLOOKUP(A10,'Medical Examinations'!A:A,'Medical Examinations'!I:I,"not found") -> Obesity | K10: =_xlfn.XLOOKUP(A10,'Hospitalisation Details'!A:A,'Hospitalisation Details'!F:F,"Not Found") -> 23258 | L10: =_xlfn.XLOOKUP(A10,'Hospitalisation Details'!A:A,'Hospitalisation Details'!H:H,"Not Found") -> 48970.25 | M10: =_xlfn.XLOOKUP(A10,'Hospitalisation Details'!A:A,'Hospitalisation Details'!I:I,"Not Found") -> tier - 1 | N10: =_xlfn.XLOOKUP(A10,'Hospitalisation Details'!A:A,'Hospitalisation Details'!J:J,"Not Found") -> tier - 3 | O10: =_xlfn.XLOOKUP(A10,'Hospitalisation Details'!A:A,'Hospitalisation Details'!K:K,"Not Found") -> R1013 | P10: =_xlfn.XLOOKUP(A10,'Hospitalisation Details'!A:A,'Hospitalisation Details'!L:L,"Not Found") -> 59
A11: Id10 | B11: =_xlfn.XLOOKUP(A11,'Customer Names'!A:A,'Customer Names'!C:C,"Not Found") -> Benner | C11: =_xlfn.XLOOKUP(A11,'Medical Examinations'!A:A,'Medical Examinations'!B:B,"not found") -> 38.06 | D11: =_xlfn.XLOOKUP(A11,'Medical Examinations'!A:A,'Medical Examinations'!C:C,"not found") -> 10.79 | E11: =_xlfn.XLOOKUP(A11,'Medical Examinations'!A:A,'Medical Examinations'!D:D,"not found") -> No | F11: =_xlfn.XLOOKUP(A11,'Medical Examinations'!A:A,'Medical Examinations'!E:E,"not found") -> No | G11: =_xlfn.XLOOKUP(A11,'Medical Examinations'!A:A,'Medical Examinations'!F:F,"not found") -> No | H11: =_xlfn.XLOOKUP(A11,'Medical Examinations'!A:A,'Medical Examinations'!G:G,"not found") -> 0 | I11: =_xlfn.XLOOKUP(A11,'Medical Examinations'!A:A,'Medical Examinations'!H:H,"not found") -> Yes | J11: =_xlfn.XLOOKUP(A11,'Medical Examinations'!A:A,'Medical Examinations'!I:I,"not found") -> Obesity | K11: =_xlfn.XLOOKUP(A11,'Hospitalisation Details'!A:A,'Hospitalisation Details'!F:F,"Not Found") -> 28853 | L11: =_xlfn.XLOOKUP(A11,'Hospitalisation Details'!A:A,'Hospitalisation Details'!H:H,"Not Found") -> 48885.14 | M11: =_xlfn.XLOOKUP(A11,'Hospitalisation Details'!A:A,'Hospitalisation Details'!I:I,"Not Found") -> tier - 1 | N11: =_xlfn.XLOOKUP(A11,'Hospitalisation Details'!A:A,'Hospitalisation Details'!J:J,"Not Found") -> tier - 3 | O11: =_xlfn.XLOOKUP(A11,'Hospitalisation Details'!A:A,'Hospitalisation Details'!K:K,"Not Found") -> R1013 | P11: =_xlfn.XLOOKUP(A11,'Hospitalisation Details'!A:A,'Hospitalisation Details'!L:L,"Not Found") -> 44
A12: Id11 | B12: =_xlfn.XLOOKUP(A12,'Customer Names'!A:A,'Customer Names'!C:C,"Not Found") -> Fierro Vargas | C12: =_xlfn.XLOOKUP(A12,'Medical Examinations'!A:A,'Medical Examinations'!B:B,"not found") -> 37.7 | D12: =_xlfn.XLOOKUP(A12,'Medical Examinations'!A:A,'Medical Examinations'!C:C,"not found") -> 5.96 | E12: =_xlfn.XLOOKUP(A12,'Medical Examinations'!A:A,'Medical Examinations'!D:D,"not found") -> Yes | F12: =_xlfn.XLOOKUP(A12,'Medical Examinations'!A:A,'Medical Examinations'!E:E,"not found") -> No | G12: =_xlfn.XLOOKUP(A12,'Medical Examinations'!A:A,'Medical Examinations'!F:F,"not found") -> No | H12: =_xlfn.XLOOKUP(A12,'Medical Examinations'!A:A,'Medical Examinations'!G:G,"not found") -> 2 | I12: =_xlfn.XLOOKUP(A12,'Medical Examinations'!A:A,'Medical Examinations'!H:H,"not found") -> Yes | J12: =_xlfn.XLOOKUP(A12,'Medical Examinations'!A:A,'Medical Examinations'!I:I,"not found") -> Obesity | K12: =_xlfn.XLOOKUP(A12,'Hospitalisation Details'!A:A,'Hospitalisation Details'!F:F,"Not Found") -> 21753 | L12: =_xlfn.XLOOKUP(A12,'Hospitalisation Details'!A:A,'Hospitalisation Details'!H:H,"Not Found") -> 48824.45 | M12: =_xlfn.XLOOKUP(A12,'Hospitalisation Details'!A:A,'Hospitalisation Details'!I:I,"Not Found") -> tier - 1 | N12: =_xlfn.XLOOKUP(A12,'Hospitalisation Details'!A:A,'Hospitalisation Details'!J:J,"Not Found") -> tier - 3 | O12: =_xlfn.XLOOKUP(A12,'Hospitalisation Details'!A:A,'Hospitalisation Details'!K:K,"Not Found") -> R1011 | P12: =_xlfn.XLOOKUP(A12,'Hospitalisation Details'!A:A,'Hospitalisation Details'!L:L,"Not Found") -> 63
A13: Id12 | B13: =_xlfn.XLOOKUP(A13,'Customer Names'!A:A,'Customer Names'!C:C,"Not Found") -> Franz | C13: =_xlfn.XLOOKUP(A13,'Medical Examinations'!A:A,'Medical Examinations'!B:B,"not found") -> 42.13 | D13: =_xlfn.XLOOKUP(A13,'Medical Examinations'!A:A,'Medical Examinations'!C:C,"not found") -> 11.9 | E13: =_xlfn.XLOOKUP(A13,'Medical Examinations'!A:A,'Medical Examinations'!D:D,"not found") -> No | F13: =_xlfn.XLOOKUP(A13,'Medical Examinations'!A:A,'Medical Examinations'!E:E,"not found") -> No | G13: =_xlfn.XLOOKUP(A13,'Medical Examinations'!A:A,'Medical Examinations'!F:F,"not found") -> No | H13: =_xlfn.XLOOKUP(A13,'Medical Examinations'!A:A,'Medical Examinations'!G:G,"not found") -> 0 | I13: =_xlfn.XLOOKUP(A13,'Medical Examinations'!A:A,'Medical Examinations'!H:H,"not found") -> Yes | J13: =_xlfn.XLOOKUP(A13,'Medical Examinations'!A:A,'Medical Examinations'!I:I,"not found") -> Obesity | K13: =_xlfn.XLOOKUP(A13,'Hospitalisation Details'!A:A,'Hospitalisation Details'!F:F,"Not Found") -> 24042 | L13: =_xlfn.XLOOKUP(A13,'Hospitalisation Details'!A:A,'Hospitalisation Details'!H:H,"Not Found") -> 48675.52 | M13: =_xlfn.XLOOKUP(A13,'Hospitalisation Details'!A:A,'Hospitalisation Details'!I:I,"Not Found") -> tier - 1 | N13: =_xlfn.XLOOKUP(A13,'Hospitalisation Details'!A:A,'Hospitalisation Details'!J:J,"Not Found") -> tier - 2 | O13: =_xlfn.XLOOKUP(A13,'Hospitalisation Details'!A:A,'Hospitalisation Details'!K:K,"Not Found") -> R1013 | P13: =_xlfn.XLOOKUP(A13,'Hospitalisation Details'!A:A,'Hospitalisation Details'!L:L,"Not Found") -> 57
A14: Id13 | B14: =_xlfn.XLOOKUP(A14,'Customer Names'!A:A,'Customer Names'!C:C,"Not Found") -> Foster | C14: =_xlfn.XLOOKUP(A14,'Medical Examinations'!A:A,'Medical Examinations'!B:B,"not found") -> 40.92 | D14: =_xlfn.XLOOKUP(A14,'Medical Examinations'!A:A,'Medical Examinations'!C:C,"not found") -> 8.41 | E14: =_xlfn.XLOOKUP(A14,'Medical Examinations'!A:A,'Medical Examinations'!D:D,"not found") -> No | F14: =_xlfn.XLOOKUP(A14,'Medical Examinations'!A:A,'Medical Examinations'!E:E,"not found") -> No | G14: =_xlfn.XLOOKUP(A14,'Medical Examinations'!A:A,'Medical Examinations'!F:F,"not found") -> No | H14: =_xlfn.XLOOKUP(A14,'Medical Examinations'!A:A,'Medical Examinations'!G:G,"not found") -> 0 | I14: =_xlfn.XLOOKUP(A14,'Medical Examinations'!A:A,'Medical Examinations'!H:H,"not found") -> Yes | J14: =_xlfn.XLOOKUP(A14,'Medical Examinations'!A:A,'Medical Examinations'!I:I,"not found") -> Obesity | K14: =_xlfn.XLOOKUP(A14,'Hospitalisation Details'!A:A,'Hospitalisation Details'!F:F,"Not Found") -> 22930 | L14: =_xlfn.XLOOKUP(A14,'Hospitalisation Details'!A:A,'Hospitalisation Details'!H:H,"Not Found") -> 48673.56 | M14: =_xlfn.XLOOKUP(A14,'Hospitalisation Details'!A:A,'Hospitalisation Details'!I:I,"Not Found") -> tier - 1 | N14: =_xlfn.XLOOKUP(A14,'Hospitalisation Details'!A:A,'Hospitalisation Details'!J:J,"Not Found") -> tier - 2 | O14: =_xlfn.XLOOKUP(A14,'Hospitalisation Details'!A:A,'Hospitalisation Details'!K:K,"Not Found") -> R1013 | P14: =_xlfn.XLOOKUP(A14,'Hospitalisation Details'!A:A,'Hospitalisation Details'!L:L,"Not Found") -> 60
A15: Id14 | B15: =_xlfn.XLOOKUP(A15,'Customer Names'!A:A,'Customer Names'!C:C,"Not Found") -> Tenorio | C15: =_xlfn.XLOOKUP(A15,'Medical Examinations'!A:A,'Medical Examinations'!B:B,"not found") -> 40.565 | D15: =_xlfn.XLOOKUP(A15,'Medical Examinations'!A:A,'Medical Examinations'!C:C,"not found") -> 7.02 | E15: =_xlfn.XLOOKUP(A15,'Medical Examinations'!A:A,'Medical Examinations'!D:D,"not found") -> No | F15: =_xlfn.XLOOKUP(A15,'Medical Examinations'!A:A,'Medical Examinations'!E:E,"not found") -> No | G15: =_xlfn.XLOOKUP(A15,'Medical Examinations'!A:A,'Medical Examinations'!F:F,"not found") -> No | H15: =_xlfn.XLOOKUP(A15,'Medical Examinations'!A:A,'Medical Examinations'!G:G,"not found") -> 0 | I15: =_xlfn.XLOOKUP(A15,'Medical Examinations'!A:A,'Medical Examinations'!H:H,"not found") -> Yes | J15: =_xlfn.XLOOKUP(A15,'Medical Examinations'!A:A,'Medical Examinations'!I:I,"not found") -> Obesity | K15: =_xlfn.XLOOKUP(A15,'Hospitalisation Details'!A:A,'Hospitalisation Details'!F:F,"Not Found") -> 25173 | L15: =_xlfn.XLOOKUP(A15,'Hospitalisation Details'!A:A,'Hospitalisation Details'!H:H,"Not Found") -> 48549.18 | M15: =_xlfn.XLOOKUP(A15,'Hospitalisation Details'!A:A,'Hospitalisation Details'!I:I,"Not Found") -> tier - 1 | N15: =_xlfn.XLOOKUP(A15,'Hospitalisation Details'!A:A,'Hospitalisation Details'!J:J,"Not Found") -> tier - 2 | O15: =_xlfn.XLOOKUP(A15,'Hospitalisation Details'!A:A,'Hospitalisation Details'!K:K,"Not Found") -> R1016 | P15: =_xlfn.XLOOKUP(A15,'Hospitalisation Details'!A:A,'Hospitalisation Details'!L:L,"Not Found") -> 54
A16: Id15 | B16: =_xlfn.XLOOKUP(A16,'Customer Names'!A:A,'Customer Names'!C:C,"Not Found") -> Rios | C16: =_xlfn.XLOOKUP(A16,'Medical Examinations'!A:A,'Medical Examinations'!B:B,"not found") -> 36.385 | D16: =_xlfn.XLOOKUP(A16,'Medical Examinations'!A:A,'Medical Examinations'!C:C,"not found") -> 7.59 | E16: =_xlfn.XLOOKUP(A16,'Medical Examinations'!A:A,'Medical Examinations'!D:D,"not found") -> Yes | F16: =_xlfn.XLOOKUP(A16,'Medical Examinations'!A:A,'Medical Examinations'!E:E,"not found") -> No | G16: =_xlfn.XLOOKUP(A16,'Medical Examinations'!A:A,'Medical Examinations'!F:F,"not found") -> No | H16: =_xlfn.XLOOKUP(A16,'Medical Examinations'!A:A,'Medical Examinations'!G:G,"not found") -> 2 | I16: =_xlfn.XLOOKUP(A16,'Medical Examinations'!A:A,'Medical Examinations'!H:H,"not found") -> Yes | J16: =_xlfn.XLOOKUP(A16,'Medical Examinations'!A:A,'Medical Examinations'!I:I,"not found") -> Obesity | K16: =_xlfn.XLOOKUP(A16,'Hospitalisation Details'!A:A,'Hospitalisation Details'!F:F,"Not Found") -> 22636 | L16: =_xlfn.XLOOKUP(A16,'Hospitalisation Details'!A:A,'Hospitalisation Details'!H:H,"Not Found") -> 48517.56 | M16: =_xlfn.XLOOKUP(A16,'Hospitalisation Details'!A:A,'Hospitalisation Details'!I:I,"Not Found") -> tier - 1 | N16: =_xlfn.XLOOKUP(A16,'Hospitalisation Details'!A:A,'Hospitalisation Details'!J:J,"Not Found") -> tier - 3 | O16: =_xlfn.XLOOKUP(A16,'Hospitalisation Details'!A:A,'Hospitalisation Details'!K:K,"Not Found") -> R1024 | P16: =_xlfn.XLOOKUP(A16,'Hospitalisation Details'!A:A,'Hospitalisation Details'!L:L,"Not Found") -> 61
A17: Id16 | B17: =_xlfn.XLOOKUP(A17,'Customer Names'!A:A,'Customer Names'!C:C,"Not Found") -> Viau-Dupuis | C17: =_xlfn.XLOOKUP(A17,'Medical Examinations'!A:A,'Medical Examinations'!B:B,"not found") -> 39.9 | D17: =_xlfn.XLOOKUP(A17,'Medical Examinations'!A:A,'Medical Examinations'!C:C,"not found") -> 11.32 | E17: =_xlfn.XLOOKUP(A17,'Medical Examinations'!A:A,'Medical Examinations'!D:D,"not found") -> No | F17: =_xlfn.XLOOKUP(A17,'Medical Examinations'!A:A,'Medical Examinations'!E:E,"not found") -> No | G17: =_xlfn.XLOOKUP(A17,'Medical Examinations'!A:A,'Medical Examinations'!F:F,"not found") -> No | H17: =_xlfn.XLOOKUP(A17,'Medical Examinations'!A:A,'Medical Examinations'!G:G,"not found") -> 0 | I17: =_xlfn.XLOOKUP(A17,'Medical Examinations'!A:A,'Medical Examinations'!H:H,"not found") -> Yes | J17: =_xlfn.XLOOKUP(A17,'Medical Examinations'!A:A,'Medical Examinations'!I:I,"not found") -> Obesity | K17: =_xlfn.XLOOKUP(A17,'Hospitalisation Details'!A:A,'Hospitalisation Details'!F:F,"Not Found") -> 22885 | L17: =_xlfn.XLOOKUP(A17,'Hospitalisation Details'!A:A,'Hospitalisation Details'!H:H,"Not Found") -> 48173.36 | M17: =_xlfn.XLOOKUP(A17,'Hospitalisation Details'!A:A,'Hospitalisation Details'!I:I,"Not Found") -> tier - 1 | N17: =_xlfn.XLOOKUP(A17,'Hospitalisation Details'!A:A,'Hospitalisation Details'!J:J,"Not Found") -> tier - 3 | O17: =_xlfn.XLOOKUP(A17,'Hospitalisation Details'!A:A,'Hospitalisation Details'!K:K,"Not Found") -> R1011 | P17: =_xlfn.XLOOKUP(A17,'Hospitalisation Details'!A:A,'Hospitalisation Details'!L:L,"Not Found") -> 60
A18: Id17 | B18: =_xlfn.XLOOKUP(A18,'Customer Names'!A:A,'Customer Names'!C:C,"Not Found") -> Cronin | C18: =_xlfn.XLOOKUP(A18,'Medical Examinations'!A:A,'Medical Examinations'!B:B,"not found") -> 33.8 | D18: =_xlfn.XLOOKUP(A18,'Medical Examinations'!A:A,'Medical Examinations'!C:C,"not found") -> 7.67 | E18: =_xlfn.XLOOKUP(A18,'Medical Examinations'!A:A,'Medical Examinations'!D:D,"not found") -> No | F18: =_xlfn.XLOOKUP(A18,'Medical Examinations'!A:A,'Medical Examinations'!E:E,"not found") -> No | G18: =_xlfn.XLOOKUP(A18,'Medical Examinations'!A:A,'Medical Examinations'!F:F,"not found") -> No | H18: =_xlfn.XLOOKUP(A18,'Medical Examinations'!A:A,'Medical Examinations'!G:G,"not found") -> 3 | I18: =_xlfn.XLOOKUP(A18,'Medical Examinations'!A:A,'Medical Examinations'!H:H,"not found") -> Yes | J18: =_xlfn.XLOOKUP(A18,'Medical Examinations'!A:A,'Medical Examinations'!I:I,"not found") -> Obesity | K18: =_xlfn.XLOOKUP(A18,'Hospitalisation Details'!A:A,'Hospitalisation Details'!F:F,"Not Found") -> 21505 | L18: =_xlfn.XLOOKUP(A18,'Hospitalisation Details'!A:A,'Hospitalisation Details'!H:H,"Not Found") -> 47928.03 | M18: =_xlfn.XLOOKUP(A18,'Hospitalisation Details'!A:A,'Hospitalisation Details'!I:I,"Not Found") -> tier - 1 | N18: =_xlfn.XLOOKUP(A18,'Hospitalisation Details'!A:A,'Hospitalisation Details'!J:J,"Not Found") -> tier - 3 | O18: =_xlfn.XLOOKUP(A18,'Hospitalisation Details'!A:A,'Hospitalisation Details'!K:K,"Not Found") -> R1011 | P18: =_xlfn.XLOOKUP(A18,'Hospitalisation Details'!A:A,'Hospitalisation Details'!L:L,"Not Found") -> 64
A19: Id18 | B19: =_xlfn.XLOOKUP(A19,'Customer Names'!A:A,'Customer Names'!C:C,"Not Found") -> Noordstar | C19: =_xlfn.XLOOKUP(A19,'Medical Examinations'!A:A,'Medical Examinations'!B:B,"not found") -> 36.765 | D19: =_xlfn.XLOOKUP(A19,'Medical Examinations'!A:A,'Medical Examinations'!C:C,"not found") -> 7.29 | E19: =_xlfn.XLOOKUP(A19,'Medical Examinations'!A:A,'Medical Examinations'!D:D,"not found") -> Yes | F19: =_xlfn.XLOOKUP(A19,'Medical Examinations'!A:A,'Medical Examinations'!E:E,"not found") -> No | G19: =_xlfn.XLOOKUP(A19,'Medical Examinations'!A:A,'Medical Examinations'!F:F,"not found") -> Yes | H19: =_xlfn.XLOOKUP(A19,'Medical Examinations'!A:A,'Medical Examinations'!G:G,"not found") -> 1 | I19: =_xlfn.XLOOKUP(A19,'Medical Examinations'!A:A,'Medical Examinations'!H:H,"not found") -> Yes | J19: =_xlfn.XLOOKUP(A19,'Medical Examinations'!A:A,'Medical Examinations'!I:I,"not found") -> Obesity | K19: =_xlfn.XLOOKUP(A19,'Hospitalisation Details'!A:A,'Hospitalisation Details'!F:F,"Not Found") -> 23228 | L19: =_xlfn.XLOOKUP(A19,'Hospitalisation Details'!A:A,'Hospitalisation Details'!H:H,"Not Found") -> 47896.79 | M19: =_xlfn.XLOOKUP(A19,'Hospitalisation Details'!A:A,'Hospitalisation Details'!I:I,"Not Found") -> tier - 1 | N19: =_xlfn.XLOOKUP(A19,'Hospitalisation Details'!A:A,'Hospitalisation Details'!J:J,"Not Found") -> tier - 3 | O19: =_xlfn.XLOOKUP(A19,'Hospitalisation Details'!A:A,'Hospitalisation Details'!K:K,"Not Found") -> R1024 | P19: =_xlfn.XLOOKUP(A19,'Hospitalisation Details'!A:A,'Hospitalisation Details'!L:L,"Not Found") -> 59
A20: Id19 | B20: =_xlfn.XLOOKUP(A20,'Customer Names'!A:A,'Customer Names'!C:C,"Not Found") -> Boudalia | C20: =_xlfn.XLOOKUP(A20,'Medical Examinations'!A:A,'Medical Examinations'!B:B,"not found") -> 36.955 | D20: =_xlfn.XLOOKUP(A20,'Medical Examinations'!A:A,'Medical Examinations'!C:C,"not found") -> 4.72 | E20: =_xlfn.XLOOKUP(A20,'Medical Examinations'!A:A,'Medical Examinations'!D:D,"not found") -> Yes | F20: =_xlfn.XLOOKUP(A20,'Medical Examinations'!A:A,'Medical Examinations'!E:E,"not found") -> No | G20: =_xlfn.XLOOKUP(A20,'Medical Examinations'!A:A,'Medical Examinations'!F:F,"not found") -> No | H20: =_xlfn.XLOOKUP(A20,'Medical Examinations'!A:A,'Medical Examinations'!G:G,"not found") -> 1 | I20: =_xlfn.XLOOKUP(A20,'Medical Examinations'!A:A,'Medical Examinations'!H:H,"not found") -> Yes | J20: =_xlfn.XLOOKUP(A20,'Medical Examinations'!A:A,'Medical Examinations'!I:I,"not found") -> Obesity | K20: =_xlfn.XLOOKUP(A20,'Hospitalisation Details'!A:A,'Hospitalisation Details'!F:F,"Not Found") -> 23688 | L20: =_xlfn.XLOOKUP(A20,'Hospitalisation Details'!A:A,'Hospitalisation Details'!H:H,"Not Found") -> 47496.49 | M20: =_xlfn.XLOOKUP(A20,'Hospitalisation Details'!A:A,'Hospitalisation Details'!I:I,"Not Found") -> tier - 1 | N20: =_xlfn.XLOOKUP(A20,'Hospitalisation Details'!A:A,'Hospitalisation Details'!J:J,"Not Found") -> tier - 3 | O20: =_xlfn.XLOOKUP(A20,'Hospitalisation Details'!A:A,'Hospitalisation Details'!K:K,"Not Found") -> R1012 | P20: =_xlfn.XLOOKUP(A20,'Hospitalisation Details'!A:A,'Hospitalisation Details'!L:L,"Not Found") -> 58
... A2336: Id2335 | B2336: =_xlfn.XLOOKUP(A2336,'Customer Names'!A:A,'Customer Names'!C:C,"Not Found") -> German | C2336: =_xlfn.XLOOKUP(A2336,'Medical Examinations'!A:A,'Medical Examinations'!B:B,"not found") -> 17.58 | D2336: =_xlfn.XLOOKUP(A2336,'Medical Examinations'!A:A,'Medical Examinations'!C:C,"not found") -> 4.51 | E2336: =_xlfn.XLOOKUP(A2336,'Medical Examinations'!A:A,'Medical Examinations'!D:D,"not found") -> No | F2336: =_xlfn.XLOOKUP(A2336,'Medical Examinations'!A:A,'Medical Examinations'!E:E,"not found") -> No | G2336: =_xlfn.XLOOKUP(A2336,'Medical Examinations'!A:A,'Medical Examinations'!F:F,"not found") -> No | H2336: =_xlfn.XLOOKUP(A2336,'Medical Examinations'!A:A,'Medical Examinations'!G:G,"not found") -> 1 | I2336: =_xlfn.XLOOKUP(A2336,'Medical Examinations'!A:A,'Medical Examinations'!H:H,"not found") -> No | J2336: =_xlfn.XLOOKUP(A2336,'Medical Examinations'!A:A,'Medical Examinations'!I:I,"not found") -> Underweight | K2336: =_xlfn.XLOOKUP(A2336,'Hospitalisation Details'!A:A,'Hospitalisation Details'!F:F,"Not Found") -> 33794 | L2336: =_xlfn.XLOOKUP(A2336,'Hospitalisation Details'!A:A,'Hospitalisation Details'!H:H,"Not Found") -> 563.84 | M2336: =_xlfn.XLOOKUP(A2336,'Hospitalisation Details'!A:A,'Hospitalisation Details'!I:I,"Not Found") -> tier - 2 | N2336: =_xlfn.XLOOKUP(A2336,'Hospitalisation Details'!A:A,'Hospitalisation Details'!J:J,"Not Found") -> tier - 2 | O2336: =_xlfn.XLOOKUP(A2336,'Hospitalisation Details'!A:A,'Hospitalisation Details'!K:K,"Not Found") -> R1013 | P2336: =_xlfn.XLOOKUP(A2336,'Hospitalisation Details'!A:A,'Hospitalisation Details'!L:L,"Not Found") -> 30
A2337: =SUBTOTAL(103,Table1[Customer ID]) -> 2335 | B2337: =SUBTOTAL(103,Table1[First Name]) -> 2335 | C2337: =SUBTOTAL(101,Table1[BMI]) -> 30.972649 | D2337: =SUBTOTAL(101,Table1[HBA1C]) -> 6.5789979 | E2337: =SUBTOTAL(103,Table1[Heart Issues]) -> 2335 | F2337: =SUBTOTAL(103,Table1[Any Transplants]) -> 2335 | G2337: =SUBTOTAL(103,Table1[Cancer history]) -> 2335 | H2337: =SUBTOTAL(103,Table1[NumberOfMajorSurgeries]) -> 2335 | I2337: =SUBTOTAL(103,Table1[smoker]) -> 2335 | J2337: =SUBTOTAL(103,Table1[Weight Status]) -> 2335 | K2337: =SUBTOTAL(103,Table1[Date of Birth]) -> 2335 | L2337: =SUBTOTAL(101,Table1[charges]) -> 13529.918 | M2337: =SUBTOTAL(103,Table1[Hospital tier]) -> 2335 | N2337: =SUBTOTAL(103,Table1[City tier]) -> 2335 | O2337: =SUBTOTAL(103,Table1[State ID]) -> 2335 | P2337: =SUBTOTAL(101,Table1[Age]) -> 39.228694

Sheet Customer Names
A1: Customer ID | B1: name | C1: First Name | D1: Title | E1: Last Name | F1: By using data/ text to column (delimited as , and . )
A2: Id1 | B2: Hawks, Ms. Kelly | C2: Hawks | D2: Ms | E2: Kelly
A3: Id2 | B3: Lehner, Mr. Matthew D | C3: Lehner | D3: Mr | E3: Matthew D
A4: Id3 | B4: Lu, Mr. Phil | C4: Lu | D4: Mr | E4: Phil
A5: Id4 | B5: Osborne, Ms. Kelsey | C5: Osborne | D5: Ms | E5: Kelsey
A6: Id5 | B6: Kadala, Ms. Kristyn | C6: Kadala | D6: Ms | E6: Kristyn
A7: Id6 | B7: Baker, Mr. Russell B. | C7: Baker | D7: Mr | E7: Russell B
A8: Id7 | B8: Macpherson, Mr. Scott | C8: Macpherson | D8: Mr | E8: Scott
A9: Id8 | B9: Hallman, Mr. Stephen | C9: Hallman | D9: Mr | E9: Stephen
A10: Id9 | B10: Moran, Mr. Patrick R. | C10: Moran | D10: Mr | E10: Patrick R
A11: Id10 | B11: Benner, Ms. Brooke N. | C11: Benner | D11: Ms | E11: Brooke N
A12: Id11 | B12: Fierro Vargas, Ms. Paola Andrea | C12: Fierro Vargas | D12: Ms | E12: Paola Andrea
A13: Id12 | B13: Franz, Mr. David | C13: Franz | D13: Mr | E13: David
... A72: Id71 | B72: Turner, Mr. Jeff | C72: Turner | D72: Mr | E72: Jeff
A73: Id72 | B73: Rangel, Mr. Elenilton V. Sr. | C73: Rangel | D73: Mr | E73: Elenilton V | F73: Sr
A74: Id73 | B74: Lacey, Ms. Maurya | C74: Lacey | D74: Ms | E74: Maurya
A75: Id74 | B75: Stiger, Ms. Samantha C | C75: Stiger | D75: Ms | E75: Samantha C
A76: Id75 | B76: Caldwell, Ms. Bethany A | C76: Caldwell | D76: Ms | E76: Bethany A
A77: Id76 | B77: Marmillod, Mr. Yves | C77: Marmillod | D77: Mr | E77: Yves
A78: Id77 | B78: Cloutier-Simons, Ms. Danielle | C78: Cloutier-Simons | D78: Ms | E78: Danielle
A79: Id78 | B79: Vegas, Ms. Julia | C79: Vegas | D79: Ms | E79: Julia
A80: Id79 | B80: Cochran, Mr. Joshua | C80: Cochran | D80: Mr | E80: Joshua
A81: Id80 | B81: Holtzapple, Ms. Jennifer | C81: Holtzapple | D81: Ms | E81: Jennifer
A82: Id81 | B82: Meyer, Ms. Gwen M. | C82: Meyer | D82: Ms | E82: Gwen M
A83: Id82 | B83: Brickley, Mr. Patrick | C83: Brickley | D83: Mr | E83: Patrick
A84: Id83 | B84: Magee, Ms. Kate | C84: Magee | D84: Ms | E84: Kate
A85: Id84 | B85: Thoma, Mr. Kevin | C85: Thoma | D85: Mr | E85: Kevin
... A188: Id187 | B188: Dublin, Mr. Andrew P | C188: Dublin | D188: Mr | E188: Andrew P
A189: Id188 | B189: Cleland, Mr. George M. V | C189: Cleland | D189: Mr | E189: George M | F189: V
A190: Id189 | B190: Evans, Ms. Sarah | C190: Evans | D190: Ms | E190: Sarah
A191: Id190 | B191: Boyd, Ms. Lara | C191: Boyd | D191: Ms | E191: Lara
A192: Id191 | B192: Roulier, Mr. Sebastien | C192: Roulier | D192: Mr | E192: Sebastien
A193: Id192 | B193: Mullins, Mr. Padraig | C193: Mullins | D193: Mr | E193: Padraig
A194: Id193 | B194: Hofmann, Ms. Heather | C194: Hofmann | D194: Ms | E194: Heather
A195: Id194 | B195: Garcia Garcia, Mr. Jorge | C195: Garcia Garcia | D195: Mr | E195: Jorge
A196: Id195 | B196: Klecker, Mr. Jack R | C196: Klecker | D196: Mr | E196: Jack R
A197: Id196 | B197: Cancre, Mr. Felix | C197: Cancre | D197: Mr | E197: Felix
A198: Id197 | B198: Denucci, Mr. Christopher C | C198: Denucci | D198: Mr | E198: Christopher C
A199: Id198 | B199: Saldana, Mr. Jesse | C199: Saldana | D199: Mr | E199: Jesse
A200: Id199 | B200: Weinberg, Ms. Jill | C200: Weinberg | D200: Ms | E200: Jill
A201: Id200 | B201: Walsh, Mr. William | C201: Walsh | D201: Mr | E201: William
... A476: Id475 | B476: Narang, Mr. Jatin | C476: Narang | D476: Mr | E476: Jatin
A477: Id476 | B477: Royston, Mr. J P. II | C477: Royston | D477: Mr | E477: J P | F477: II
A478: Id477 | B478: Tieri, Ms. Angela M. | C478: Tieri | D478: Ms | E478: Angela M
A479: Id478 | B479: Whitney, Mr. Blake K. | C479: Whitney | D479: Mr | E479: Blake K
A480: Id479 | B480: Wandzilak, Mr. Brian T. | C480: Wandzilak | D480: Mr | E480: Brian T
A481: Id480 | B481: Valenzona, Mr. Damon | C481: Valenzona | D481: Mr | E481: Damon
A482: Id481 | B482: Young, Mr. Jeffrey | C482: Young | D482: Mr | E482: Jeffrey
A483: Id482 | B483: Richards, Mr. Malcolm J. | C483: Richards | D483: Mr | E483: Malcolm J
A484: Id483 | B484: Alexson, Ms. Margaret B. | C484: Alexson | D484: Ms | E484: Margaret B
A485: Id484 | B485: Wright, Ms. Helen | C485: Wright | D485: Ms | E485: Helen
A486: Id485 | B486: McKenna, Mr. Matthew | C486: McKenna | D486: Mr | E486: Matthew
A487: Id486 | B487: Sallade, Mr. Jeff | C487: Sallade | D487: Mr | E487: Jeff
A488: Id487 | B488: Argall, Mrs. Tara R | C488: Argall | D488: Mrs | E488: Tara R
A489: Id488 | B489: Patchell, Ms. Kristin | C489: Patchell | D489: Ms | E489: Kristin
... A725: Id724 | B725: Nemec, Mrs. Lisa | C725: Nemec | D725: Mrs | E725: Lisa
A726: Id725 | B726: Appman, Mr. William D. Jr. | C726: Appman | D726: Mr | E726: William D | F726: Jr
A727: Id726 | B727: Driscoll, Mr. James | C727: Driscoll | D727: Mr | E727: James
A728: Id727 | B728: Glotzbach, Mr. John | C728: Glotzbach | D728: Mr | E728: John
A729: Id728 | B729: Tenforde, Mr. Adam S | C729: Tenforde | D729: Mr | E729: Adam S
A730: Id729 | B730: Ramirez, Mr. Armando | C730: Ramirez | D730: Mr | E730: Armando
A731: Id730 | B731: Stanley Torres, Ms. Dana | C731: Stanley Torres | D731: Ms | E731: Dana
A732: Id731 | B732: Vandongen, Ms. Jennifer L | C732: Vandongen | D732: Ms | E732: Jennifer L
A733: Id732 | B733: Liebald, Mr. Benjamin | C733: Liebald | D733: Mr | E733: Benjamin
A734: Id733 | B734: Holte, Ms. Tanya | C734: Holte | D734: Ms | E734: Tanya
A735: Id734 | B735: Johnson, Ms. Tracy | C735: Johnson | D735: Ms | E735: Tracy
A736: Id735 | B736: Bartlett, Ms. Emily S | C736: Bartlett | D736: Ms | E736: Emily S
A737: Id736 | B737: Bergman, Ms. Kelly R | C737: Bergman | D737: Ms | E737: Kelly R
A738: Id737 | B738: Aitken, Mr. Kyle | C738: Aitken | D738: Mr | E738: Kyle
... A892: Id891 | B892: Bauder, Mr. Andrew R | C892: Bauder | D892: Mr | E892: Andrew R
A893: Id892 | B893: Mendoza, Mr. Francisco J. Sr. | C893: Mendoza | D893: Mr | E893: Francisco J | F893: Sr
A894: Id893 | B894: Glass, Mrs. Rhonda | C894: Glass | D894: Mrs | E894: Rhonda
A895: Id894 | B895: Butcher, Mr. John | C895: Butcher | D895: Mr | E895: John
A896: Id895 | B896: Traiser, Mr. Miles J. | C896: Traiser | D896: Mr | E896: Miles J
A897: Id896 | B897: Mudy-Mader, Ms. Justyna I. | C897: Mudy-Mader | D897: Ms | E897: Justyna I
A898: Id897 | B898: Rogers, Ms. Lucille | C898: Rogers | D898: Ms | E898: Lucille
A899: Id898 | B899: Woo, Ms. April | C899: Woo | D899: Ms | E899: April
A900: Id899 | B900: Walsh, Mr. Robert | C900: Walsh | D900: Mr | E900: Robert
A901: Id900 | B901: White, Mrs. Alyssa | C901: White | D901: Mrs | E901: Alyssa
A902: Id901 | B902: Sheppard, Ms. Jessica E. | C902: Sheppard | D902: Ms | E902: Jessica E
A903: Id902 | B903: Doran, Mr. Patrick J. | C903: Doran | D903: Mr | E903: Patrick J
A904: Id903 | B904: Labrosse, Ms. Emilie | C904: Labrosse | D904: Ms | E904: Emilie
A905: Id904 | B905: Thomas, Ms. Caitlin B. | C905: Thomas | D905: Ms | E905: Caitlin B
... A1062: Id1061 | B1062: Dockemeyer, Mr. Kevin J | C1062: Dockemeyer | D1062: Mr | E1062: Kevin J
A1063: Id1062 | B1063: Steele, Mr. William H. III | C1063: Steele | D1063: Mr | E1063: William H | F1063: III
A1064: Id1063 | B1064: Harel, Mr. Gal | C1064: Harel | D1064: Mr | E1064: Gal
A1065: Id1064 | B1065: Aguila, Mr. Anton | C1065: Aguila | D1065: Mr | E1065: Anton
A1066: Id1065 | B1066: Vallejo Sarmiento, Ms. Yazmin | C1066: Vallejo Sarmiento | D1066: Ms | E1066: Yazmin
A1067: Id1066 | B1067: Beisheim, Mr. Florian | C1067: Beisheim | D1067: Mr | E1067: Florian
A1068: Id1067 | B1068: Lenhoff, Ms. Karen L | C1068: Lenhoff | D1068: Ms | E1068: Karen L
A1069: Id1068 | B1069: Wehrwein, Mr. Scott | C1069: Wehrwein | D1069: Mr | E1069: Scott
A1070: Id1069 | B1070: Wallace, Ms. Claire | C1070: Wallace | D1070: Ms | E1070: Claire
A1071: Id1070 | B1071: Markowitz, Ms. Lynn M. | C1071: Markowitz | D1071: Ms | E1071: Lynn M
A1072: Id1071 | B1072: Vos, Ms. Sharon | C1072: Vos | D1072: Ms | E1072: Sharon
A1073: Id1072 | B1073: McLeod, Mrs. Candice | C1073: McLeod | D1073: Mrs | E1073: Candice
A1074: Id1073 | B1074: Balcom, Ms. Jennifer D | C1074: Balcom | D1074: Ms | E1074: Jennifer D
A1075: Id1074 | B1075: Dirth, Mr. Eric | C1075: Dirth | D1075: Mr | E1075: Eric
... A1295: Id1294 | B1295: Tadich, Ms. Katarina D | C1295: Tadich | D1295: Ms | E1295: Katarina D
A1296: Id1295 | B1296: Christenson, Mr. B.j. | C1296: Christenson | D1296: Mr | E1296: B | F1296: j
A1297: Id1296 | B1297: Shell, Ms. Alison | C1297: Shell | D1297: Ms | E1297: Alison
...

Sheet Medical Examinations
A1: Customer ID | B1: BMI | C1: HBA1C | D1: Heart Issues | E1: Any Transplants | F1: Cancer history | G1: NumberOfMajorSurgeries | H1: smoker | I1: Weight Status
A2: Id1 | B2: 47.41 | C2: 7.47 | D2: No | E2: No | F2: No | G2: =IF('OG Medical Examinations'!G2="No major surgery",0,VALUE('OG Medical Examinations'!G2)) -> 0 | H2: Yes | I2: =IF(B2<18.5,"Underweight",IF(B2<25,"Normal Weight",IF(B2<30,"Overweight","Obesity"))) -> Obesity
A3: Id2 | B3: 30.36 | C3: 5.77 | D3: No | E3: No | F3: No | G3: =IF('OG Medical Examinations'!G3="No major surgery",0,VALUE('OG Medical Examinations'!G3)) -> 0 | H3: Yes | I3: =IF(B3<18.5,"Underweight",IF(B3<25,"Normal Weight",IF(B3<30,"Overweight","Obesity"))) -> Obesity
A4: Id3 | B4: 34.485 | C4: 11.87 | D4: Yes | E4: No | F4: No | G4: =IF('OG Medical Examinations'!G4="No major surgery",0,VALUE('OG Medical Examinations'!G4)) -> 2 | H4: Yes | I4: =IF(B4<18.5,"Underweight",IF(B4<25,"Normal Weight",IF(B4<30,"Overweight","Obesity"))) -> Obesity
A5: Id4 | B5: 38.095 | C5: 6.05 | D5: No | E5: No | F5: No | G5: =IF('OG Medical Examinations'!G5="No major surgery",0,VALUE('OG Medical Examinations'!G5)) -> 0 | H5: Yes | I5: =IF(B5<18.5,"Underweight",IF(B5<25,"Normal Weight",IF(B5<30,"Overweight","Obesity"))) -> Obesity
A6: Id5 | B6: 35.53 | C6: 5.45 | D6: No | E6: No | F6: No | G6: =IF('OG Medical Examinations'!G6="No major surgery",0,VALUE('OG Medical Examinations'!G6)) -> 0 | H6: Yes | I6: =IF(B6<18.5,"Underweight",IF(B6<25,"Normal Weight",IF(B6<30,"Overweight","Obesity"))) -> Obesity
A7: Id6 | B7: 32.8 | C7: 6.59 | D7: No | E7: No | F7: No | G7: =IF('OG Medical Examinations'!G7="No major surgery",0,VALUE('OG Medical Examinations'!G7)) -> 0 | H7: Yes | I7: =IF(B7<18.5,"Underweight",IF(B7<25,"Normal Weight",IF(B7<30,"Overweight","Obesity"))) -> Obesity
A8: Id7 | B8: 36.4 | C8: 6.07 | D8: No | E8: No | F8: No | G8: =IF('OG Medical Examinations'!G8="No major surgery",0,VALUE('OG Medical Examinations'!G8)) -> 0 | H8: Yes | I8: =IF(B8<18.5,"Underweight",IF(B8<25,"Normal Weight",IF(B8<30,"Overweight","Obesity"))) -> Obesity
A9: Id8 | B9: 36.96 | C9: 7.93 | D9: No | E9: No | F9: No | G9: =IF('OG Medical Examinations'!G9="No major surgery",0,VALUE('OG Medical Examinations'!G9)) -> 3 | H9: Yes | I9: =IF(B9<18.5,"Underweight",IF(B9<25,"Normal Weight",IF(B9<30,"Overweight","Obesity"))) -> Obesity
A10: Id9 | B10: 41.14 | C10: 9.58 | D10: Yes | E10: No | F10: Yes | G10: =IF('OG Medical Examinations'!G10="No major surgery",0,VALUE('OG Medical Examinations'!G10)) -> 1 | H10: Yes | I10: =IF(B10<18.5,"Underweight",IF(B10<25,"Normal Weight",IF(B10<30,"Overweight","Obesity"))) -> Obesity
A11: Id10 | B11: 38.06 | C11: 10.79 | D11: No | E11: No | F11: No | G11: =IF('OG Medical Examinations'!G11="No major surgery",0,VALUE('OG Medical Examinations'!G11)) -> 0 | H11: Yes | I11: =IF(B11<18.5,"Underweight",IF(B11<25,"Normal Weight",IF(B11<30,"Overweight","Obesity"))) -> Obesity
A12: Id11 | B12: 37.7 | C12: 5.96 | D12: Yes | E12: No | F12: No | G12: =IF('OG Medical Examinations'!G12="No major surgery",0,VALUE('OG Medical Examinations'!G12)) -> 2 | H12: Yes | I12: =IF(B12<18.5,"Underweight",IF(B12<25,"Normal Weight",IF(B12<30,"Overweight","Obesity"))) -> Obesity
A13: Id12 | B13: 42.13 | C13: 11.9 | D13: No | E13: No | F13: No | G13: =IF('OG Medical Examinations'!G13="No major surgery",0,VALUE('OG Medical Examinations'!G13)) -> 0 | H13: Yes | I13: =IF(B13<18.5,"Underweight",IF(B13<25,"Normal Weight",IF(B13<30,"Overweight","Obesity"))) -> Obesity
... A2336: Id2335 | B2336: 17.58 | C2336: 4.51 | D2336: No | E2336: No | F2336: No | G2336: =IF('OG Medical Examinations'!G2336="No major surgery",0,VALUE('OG Medical Examinations'!G2336)) -> 1 | H2336: No | I2336: =IF(B2336<18.5,"Underweight",IF(B2336<25,"Normal Weight",IF(B2336<30,"Overweight","Obesity"))) -> Underweight

Sheet Hospitalisation Details
A1: Customer ID | B1: Customer Number | C1: year | D1: month | E1: date | F1: Date of Birth | G1: children | H1: charges | I1: Hospital tier | J1: City tier | K1: State ID | L1: Age
A2: Id1 | B2: =VALUE(SUBSTITUTE(A2,"Id","")) -> 1 | C2: =IF('OG Hospitalisation Details'!B2344="?",ROUND(AVERAGE('OG Hospitalisation Details'!$B$2:$B$2344),0),'OG Hospitalisation Details'!B2344) -> 1968 | D2: =IF('OG Hospitalisation Details'!C2344="?","Sep",'OG Hospitalisation Details'!C2344) -> Oct | E2: 12 | F2: =DATE(C2,MONTH(1&D2),E2) -> 25123 | G2: 0 | H2: 63770.43 | I2: {=INDEX({"tier - 1","tier - 2","tier - 3"},MATCH(MAX(COUNTIF('OG Hospitalisation Details'!G2344:G4686,{"tier - 1","tier - 2","tier - 3"})),COUNTIF('OG Hospitalisation Details'!G2344:G4686,{"tier - 1","tier - 2","tier - 3"}),0))} -> tier - 1 | J2: {=INDEX({"tier - 1","tier - 2","tier - 3"},MATCH(MAX(COUNTIF('OG Hospitalisation Details'!H2344:H4686,{"tier - 1","tier - 2","tier - 3"})),COUNTIF('OG Hospitalisation Details'!H2344:H4686,{"tier - 1","tier - 2","tier - 3"}),0))} -> tier - 3 | K2: =IF('OG Hospitalisation Details'!I2344="?","Unknown",'OG Hospitalisation Details'!I2344) -> R1013 | L2: =DATEDIF(F2,DATE(2023,6,8),"Y") -> 54
A3: Id2 | B3: =VALUE(SUBSTITUTE(A3,"Id","")) -> 2 | C3: =IF('OG Hospitalisation Details'!B2343="?",ROUND(AVERAGE('OG Hospitalisation Details'!$B$2:$B$2344),0),'OG Hospitalisation Details'!B2343) -> 1977 | D3: =IF('OG Hospitalisation Details'!C2343="?","Sep",'OG Hospitalisation Details'!C2343) -> Jun | E3: 8 | F3: =DATE(C3,MONTH(1&D3),E3) -> 28284 | G3: 0 | H3: 62592.87 | I3: {=INDEX({"tier - 1","tier - 2","tier - 3"},MATCH(MAX(COUNTIF('OG Hospitalisation Details'!G2343:G4685,{"tier - 1","tier - 2","tier - 3"})),COUNTIF('OG Hospitalisation Details'!G2343:G4685,{"tier - 1","tier - 2","tier - 3"}),0))} -> tier - 1 | J3: {=INDEX({"tier - 1","tier - 2","tier - 3"},MATCH(MAX(COUNTIF('OG Hospitalisation Details'!H2343:H4685,{"tier - 1","tier - 2","tier - 3"})),COUNTIF('OG Hospitalisation Details'!H2343:H4685,{"tier - 1","tier - 2","tier - 3"}),0))} -> tier - 3 | K3: =IF('OG Hospitalisation Details'!I2343="?","Unknown",'OG Hospitalisation Details'!I2343) -> R1013 | L3: =DATEDIF(F3,DATE(2023,6,8),"Y") -> 46
A4: Id3 | B4: =VALUE(SUBSTITUTE(A4,"Id","")) -> 3 | C4: =IF('OG Hospitalisation Details'!B2342="?",ROUND(AVERAGE('OG Hospitalisation Details'!$B$2:$B$2344),0),'OG Hospitalisation Details'!B2342) -> 1970 | D4: =IF('OG Hospitalisation Details'!C2342="?","Sep",'OG Hospitalisation Details'!C2342) -> Sep | E4: 11 | F4: =DATE(C4,MONTH(1&D4),E4) -> 25822 | G4: 3 | H4: 60021.4 | I4: {=INDEX({"tier - 1","tier - 2","tier - 3"},MATCH(MAX(COUNTIF('OG Hospitalisation Details'!G2342:G4684,{"tier - 1","tier - 2","tier - 3"})),COUNTIF('OG Hospitalisation Details'!G2342:G4684,{"tier - 1","tier - 2","tier - 3"}),0))} -> tier - 1 | J4: {=INDEX({"tier - 1","tier - 2","tier - 3"},MATCH(MAX(COUNTIF('OG Hospitalisation Details'!H2342:H4684,{"tier - 1","tier - 2","tier - 3"})),COUNTIF('OG Hospitalisation Details'!H2342:H4684,{"tier - 1","tier - 2","tier - 3"}),0))} -> tier - 3 | K4: =IF('OG Hospitalisation Details'!I2342="?","Unknown",'OG Hospitalisation Details'!I2342) -> R1012 | L4: =DATEDIF(F4,DATE(2023,6,8),"Y") -> 52
A5: Id4 | B5: =VALUE(SUBSTITUTE(A5,"Id","")) -> 4 | C5: =IF('OG Hospitalisation Details'!B2341="?",ROUND(AVERAGE('OG Hospitalisation Details'!$B$2:$B$2344),0),'OG Hospitalisation Details'!B2341) -> 1991 | D5: =IF('OG Hospitalisation Details'!C2341="?","Sep",'OG Hospitalisation Details'!C2341) -> Jun | E5: 6 | F5: =DATE(C5,MONTH(1&D5),E5) -> 33395 | G5: 1 | H5: 58571.07 | I5: {=INDEX({"tier - 1","tier - 2","tier - 3"},MATCH(MAX(COUNTIF('OG Hospitalisation Details'!G2341:G4683,{"tier - 1","tier - 2","tier - 3"})),COUNTIF('OG Hospitalisation Details'!G2341:G4683,{"tier - 1","tier - 2","tier - 3"}),0))} -> tier - 1 | J5: {=INDEX({"tier - 1","tier - 2","tier - 3"},MATCH(MAX(COUNTIF('OG Hospitalisation Details'!H2341:H4683,{"tier - 1","tier - 2","tier - 3"})),COUNTIF('OG Hospitalisation Details'!H2341:H4683,{"tier - 1","tier - 2","tier - 3"}),0))} -> tier - 3 | K5: =IF('OG Hospitalisation Details'!I2341="?","Unknown",'OG Hospitalisation Details'!I2341) -> R1024 | L5: =DATEDIF(F5,DATE(2023,6,8),"Y") -> 32
A6: Id5 | B6: =VALUE(SUBSTITUTE(A6,"Id","")) -> 5 | C6: =IF('OG Hospitalisation Details'!B2340="?",ROUND(AVERAGE('OG Hospitalisation Details'!$B$2:$B$2344),0),'OG Hospitalisation Details'!B2340) -> 1989 | D6: =IF('OG Hospitalisation Details'!C2340="?","Sep",'OG Hospitalisation Details'!C2340) -> Jun | E6: 19 | F6: =DATE(C6,MONTH(1&D6),E6) -> 32678 | G6: 0 | H6: 55135.4 | I6: {=INDEX({"tier - 1","tier - 2","tier - 3"},MATCH(MAX(COUNTIF('OG Hospitalisation Details'!G2340:G4682,{"tier - 1","tier - 2","tier - 3"})),COUNTIF('OG Hospitalisation Details'!G2340:G4682,{"tier - 1","tier - 2","tier - 3"}),0))} -> tier - 1 | J6: {=INDEX({"tier - 1","tier - 2","tier - 3"},MATCH(MAX(COUNTIF('OG Hospitalisation Details'!H2340:H4682,{"tier - 1","tier - 2","tier - 3"})),COUNTIF('OG Hospitalisation Details'!H2340:H4682,{"tier - 1","tier - 2","tier - 3"}),0))} -> tier - 3 | K6: =IF('OG Hospitalisation Details'!I2340="?","Unknown",'OG Hospitalisation Details'!I2340) -> R1012 | L6: =DATEDIF(F6,DATE(2023,6,8),"Y") -> 33
A7: Id6 | B7: =VALUE(SUBSTITUTE(A7,"Id","")) -> 6 | C7: =IF('OG Hospitalisation Details'!B2339="?",ROUND(AVERAGE('OG Hospitalisation Details'!$B$2:$B$2344),0),'OG Hospitalisation Details'!B2339) -> 1962 | D7: =IF('OG Hospitalisation Details'!C2339="?","Sep",'OG Hospitalisation Details'!C2339) -> Aug | E7: 4 | F7: =DATE(C7,MONTH(1&D7),E7) -> 22862 | G7: 0 | H7: 52590.83 | I7: {=INDEX({"tier - 1","tier - 2","tier - 3"},MATCH(MAX(COUNTIF('OG Hospitalisation Details'!G2339:G4681,{"tier - 1","tier - 2","tier - 3"})),COUNTIF('OG Hospitalisation Details'!G2339:G4681,{"tier - 1","tier - 2","tier - 3"}),0))} -> tier - 1 | J7: {=INDEX({"tier - 1","tier - 2","tier - 3"},MATCH(MAX(COUNTIF('OG Hospitalisation Details'!H2339:H4681,{"tier - 1","tier - 2","tier - 3"})),COUNTIF('OG Hospitalisation Details'!H2339:H4681,{"tier - 1","tier - 2","tier - 3"}),0))} -> tier - 3 | K7: =IF('OG Hospitalisation Details'!I2339="?","Unknown",'OG Hospitalisation Details'!I2339) -> R1011 | L7: =DATEDIF(F7,DATE(2023,6,8),"Y") -> 60
A8: Id7 | B8: =VALUE(SUBSTITUTE(A8,"Id","")) -> 7 | C8: =IF('OG Hospitalisation Details'!B2338="?",ROUND(AVERAGE('OG Hospitalisation Details'!$B$2:$B$2344),0),'OG Hospitalisation Details'!B2338) -> 1994 | D8: =IF('OG Hospitalisation Details'!C2338="?","Sep",'OG Hospitalisation Details'!C2338) -> Oct | E8: 27 | F8: =DATE(C8,MONTH(1&D8),E8) -> 34634 | G8: 1 | H8: 51194.56 | I8: {=INDEX({"tier - 1","tier - 2","tier - 3"},MATCH(MAX(COUNTIF('OG Hospitalisation Details'!G2338:G4680,{"tier - 1","tier - 2","tier - 3"})),COUNTIF('OG Hospitalisation Details'!G2338:G4680,{"tier - 1","tier - 2","tier - 3"}),0))} -> tier - 1 | J8: {=INDEX({"tier - 1","tier - 2","tier - 3"},MATCH(MAX(COUNTIF('OG Hospitalisation Details'!H2338:H4680,{"tier - 1","tier - 2","tier - 3"})),COUNTIF('OG Hospitalisation Details'!H2338:H4680,{"tier - 1","tier - 2","tier - 3"}),0))} -> tier - 3 | K8: =IF('OG Hospitalisation Details'!I2338="?","Unknown",'OG Hospitalisation Details'!I2338) -> R1011 | L8: =DATEDIF(F8,DATE(2023,6,8),"Y") -> 28
A9: Id8 | B9: =VALUE(SUBSTITUTE(A9,"Id","")) -> 8 | C9: =IF('OG Hospitalisation Details'!B2337="?",ROUND(AVERAGE('OG Hospitalisation Details'!$B$2:$B$2344),0),'OG Hospitalisation Details'!B2337) -> 1958 | D9: =IF('OG Hospitalisation Details'!C2337="?","Sep",'OG Hospitalisation Details'!C2337) -> Jun | E9: 27 | F9: =DATE(C9,MONTH(1&D9),E9) -> 21363 | G9: 2 | H9: 49577.66 | I9: {=INDEX({"tier - 1","tier - 2","tier - 3"},MATCH(MAX(COUNTIF('OG Hospitalisation Details'!G2337:G4679,{"tier - 1","tier - 2","tier - 3"})),COUNTIF('OG Hospitalisation Details'!G2337:G4679,{"tier - 1","tier - 2","tier - 3"}),0))} -> tier - 1 | J9: {=INDEX({"tier - 1","tier - 2","tier - 3"},MATCH(MAX(COUNTIF('OG Hospitalisation Details'!H2337:H4679,{"tier - 1","tier - 2","tier - 3"})),COUNTIF('OG Hospitalisation Details'!H2337:H4679,{"tier - 1","tier - 2","tier - 3"}),0))} -> tier - 3 | K9: =IF('OG Hospitalisation Details'!I2337="?","Unknown",'OG Hospitalisation Details'!I2337) -> R1013 | L9: =DATEDIF(F9,DATE(2023,6,8),"Y") -> 64
A10: Id9 | B10: =VALUE(SUBSTITUTE(A10,"Id","")) -> 9 | C10: =IF('OG Hospitalisation Details'!B2336="?",ROUND(AVERAGE('OG Hospitalisation Details'!$B$2:$B$2344),0),'OG Hospitalisation Details'!B2336) -> 1963 | D10: =IF('OG Hospitalisation Details'!C2336="?","Sep",'OG Hospitalisation Details'!C2336) -> Sep | E10: 4 | F10: =DATE(C10,MONTH(1&D10),E10) -> 23258 | G10: 1 | H10: 48970.25 | I10: {=INDEX({"tier - 1","tier - 2","tier - 3"},MATCH(MAX(COUNTIF('OG Hospitalisation Details'!G2336:G4678,{"tier - 1","tier - 2","tier - 3"})),COUNTIF('OG Hospitalisation Details'!G2336:G4678,{"tier - 1","tier - 2","tier - 3"}),0))} -> tier - 1 | J10: {=INDEX({"tier - 1","tier - 2","tier - 3"},MATCH(MAX(COUNTIF('OG Hospitalisation Details'!H2336:H4678,{"tier - 1","tier - 2","tier - 3"})),COUNTIF('OG Hospitalisation Details'!H2336:H4678,{"tier - 1","tier - 2","tier - 3"}),0))} -> tier - 3 | K10: =IF('OG Hospitalisation Details'!I2336="?","Unknown",'OG Hospitalisation Details'!I2336) -> R1013 | L10: =DATEDIF(F10,DATE(2023,6,8),"Y") -> 59
A11: Id10 | B11: =VALUE(SUBSTITUTE(A11,"Id","")) -> 10 | C11: =IF('OG Hospitalisation Details'!B2335="?",ROUND(AVERAGE('OG Hospitalisation Details'!$B$2:$B$2344),0),'OG Hospitalisation Details'!B2335) -> 1978 | D11: =IF('OG Hospitalisation Details'!C2335="?","Sep",'OG Hospitalisation Details'!C2335) -> Dec | E11: 29 | F11: =DATE(C11,MONTH(1&D11),E11) -> 28853 | G11: 0 | H11: 48885.14 | I11: {=INDEX({"tier - 1","tier - 2","tier - 3"},MATCH(MAX(COUNTIF('OG Hospitalisation Details'!G2335:G4677,{"tier - 1","tier - 2","tier - 3"})),COUNTIF('OG Hospitalisation Details'!G2335:G4677,{"tier - 1","tier - 2","tier - 3"}),0))} -> tier - 1 | J11: {=INDEX({"tier - 1","tier - 2","tier - 3"},MATCH(MAX(COUNTIF('OG Hospitalisation Details'!H2335:H4677,{"tier - 1","tier - 2","tier - 3"})),COUNTIF('OG Hospitalisation Details'!H2335:H4677,{"tier - 1","tier - 2","tier - 3"}),0))} -> tier - 3 | K11: =IF('OG Hospitalisation Details'!I2335="?","Unknown",'OG Hospitalisation Details'!I2335) -> R1013 | L11: =DATEDIF(F11,DATE(2023,6,8),"Y") -> 44
A12: Id11 | B12: =VALUE(SUBSTITUTE(A12,"Id","")) -> 11 | C12: =IF('OG Hospitalisation Details'!B2334="?",ROUND(AVERAGE('OG Hospitalisation Details'!$B$2:$B$2344),0),'OG Hospitalisation Details'!B2334) -> 1959 | D12: =IF('OG Hospitalisation Details'!C2334="?","Sep",'OG Hospitalisation Details'!C2334) -> Jul | E12: 22 | F12: =DATE(C12,MONTH(1&D12),E12) -> 21753 | G12: 0 | H12: 48824.45 | I12: {=INDEX({"tier - 1","tier - 2","tier - 3"},MATCH(MAX(COUNTIF('OG Hospitalisation Details'!G2334:G4676,{"tier - 1","tier - 2","tier - 3"})),COUNTIF('OG Hospitalisation Details'!G2334:G4676,{"tier - 1","tier - 2","tier - 3"}),0))} -> tier - 1 | J12: {=INDEX({"tier - 1","tier - 2","tier - 3"},MATCH(MAX(COUNTIF('OG Hospitalisation Details'!H2334:H4676,{"tier - 1","tier - 2","tier - 3"})),COUNTIF('OG Hospitalisation Details'!H2334:H4676,{"tier - 1","tier - 2","tier - 3"}),0))} -> tier - 3 | K12: =IF('OG Hospitalisation Details'!I2334="?","Unknown",'OG Hospitalisation Details'!I2334) -> R1011 | L12: =DATEDIF(F12,DATE(2023,6,8),"Y") -> 63
A13: Id12 | B13: =VALUE(SUBSTITUTE(A13,"Id","")) -> 12 | C13: =IF('OG Hospitalisation Details'!B2333="?",ROUND(AVERAGE('OG Hospitalisation Details'!$B$2:$B$2344),0),'OG Hospitalisation Details'!B2333) -> 1965 | D13: =IF('OG Hospitalisation Details'!C2333="?","Sep",'OG Hospitalisation Details'!C2333) -> Oct | E13: 27 | F13: =DATE(C13,MONTH(1&D13),E13) -> 24042 | G13: 1 | H13: 48675.52 | I13: {=INDEX({"tier - 1","tier - 2","tier - 3"},MATCH(MAX(COUNTIF('OG Hospitalisation Details'!G2333:G4675,{"tier - 1","tier - 2","tier - 3"})),COUNTIF('OG Hospitalisation Details'!G2333:G4675,{"tier - 1","tier - 2","tier - 3"}),0))} -> tier - 1 | J13: {=INDEX({"tier - 1","tier - 2","tier - 3"},MATCH(MAX(COUNTIF('OG Hospitalisation Details'!H2333:H4675,{"tier - 1","tier - 2","tier - 3"})),COUNTIF('OG Hospitalisation Details'!H2333:H4675,{"tier - 1","tier - 2","tier - 3"}),0))} -> tier - 2 | K13: =IF('OG Hospitalisation Details'!I2333="?","Unknown",'OG Hospitalisation Details'!I2333) -> R1013 | L13: =DATEDIF(F13,DATE(2023,6,8),"Y") -> 57
A14: Id13 | B14: =VALUE(SUBSTITUTE(A14,"Id","")) -> 13 | C14: =IF('OG Hospitalisation Details'!B2332="?",ROUND(AVERAGE('OG Hospitalisation Details'!$B$2:$B$2344),0),'OG Hospitalisation Details'!B2332) -> 1962 | D14: =IF('OG Hospitalisation Details'!C2332="?","Sep",'OG Hospitalisation Details'!C2332) -> Oct | E14: 11 | F14: =DATE(C14,MONTH(1&D14),E14) -> 22930 | G14: 0 | H14: 48673.56 | I14: {=INDEX({"tier - 1","tier - 2","tier - 3"},MATCH(MAX(COUNTIF('OG Hospitalisation Details'!G2332:G4674,{"tier - 1","tier - 2","tier - 3"})),COUNTIF('OG Hospitalisation Details'!G2332:G4674,{"tier - 1","tier - 2","tier - 3"}),0))} -> tier - 1 | J14: {=INDEX({"tier - 1","tier - 2","tier - 3"},MATCH(MAX(COUNTIF('OG Hospitalisation Details'!H2332:H4674,{"tier - 1","tier - 2","tier - 3"})),COUNTIF('OG Hospitalisation Details'!H2332:H4674,{"tier - 1","tier - 2","tier - 3"}),0))} -> tier - 2 | K14: =IF('OG Hospitalisation Details'!I2332="?","Unknown",'OG Hospitalisation Details'!I2332) -> R1013 | L14: =DATEDIF(F14,DATE(2023,6,8),"Y") -> 60
A15: Id14 | B15: =VALUE(SUBSTITUTE(A15,"Id","")) -> 14 | C15: =IF('OG Hospitalisation Details'!B2331="?",ROUND(AVERAGE('OG Hospitalisation Details'!$B$2:$B$2344),0),'OG Hospitalisation Details'!B2331) -> 1968 | D15: =IF('OG Hospitalisation Details'!C2331="?","Sep",'OG Hospitalisation Details'!C2331) -> Dec | E15: 1 | F15: =DATE(C15,MONTH(1&D15),E15) -> 25173 | G15: 3 | H15: 48549.18 | I15: {=INDEX({"tier - 1","tier - 2","tier - 3"},MATCH(MAX(COUNTIF('OG Hospitalisation Details'!G2331:G4673,{"tier - 1","tier - 2","tier - 3"})),COUNTIF('OG Hospitalisation Details'!G2331:G4673,{"tier - 1","tier - 2","tier - 3"}),0))} -> tier - 1 | J15: {=INDEX({"tier - 1","tier - 2","tier - 3"},MATCH(MAX(COUNTIF('OG Hospitalisation Details'!H2331:H4673,{"tier - 1","tier - 2","tier - 3"})),COUNTIF('OG Hospitalisation Details'!H2331:H4673,{"tier - 1","tier - 2","tier - 3"}),0))} -> tier - 2 | K15: =IF('OG Hospitalisation Details'!I2331="?","Unknown",'OG Hospitalisation Details'!I2331) -> R1016 | L15: =DATEDIF(F15,DATE(2023,6,8),"Y") -> 54
A16: Id15 | B16: =VALUE(SUBSTITUTE(A16,"Id","")) -> 15 | C16: =IF('OG Hospitalisation Details'!B2330="?",ROUND(AVERAGE('OG Hospitalisation Details'!$B$2:$B$2344),0),'OG Hospitalisation Details'!B2330) -> 1961 | D16: =IF('OG Hospitalisation Details'!C2330="?","Sep",'OG Hospitalisation Details'!C2330) -> Dec | E16: 21 | F16: =DATE(C16,MONTH(1&D16),E16) -> 22636 | G16: 1 | H16: 48517.56 | I16: {=INDEX({"tier - 1","tier - 2","tier - 3"},MATCH(MAX(COUNTIF('OG Hospitalisation Details'!G2330:G4672,{"tier - 1","tier - 2","tier - 3"})),COUNTIF('OG Hospitalisation Details'!G2330:G4672,{"tier - 1","tier - 2","tier - 3"}),0))} -> tier - 1 | J16: {=INDEX({"tier - 1","tier - 2","tier - 3"},MATCH(MAX(COUNTIF('OG Hospitalisation Details'!H2330:H4672,{"tier - 1","tier - 2","tier - 3"})),COUNTIF('OG Hospitalisation Details'!H2330:H4672,{"tier - 1","tier - 2","tier - 3"}),0))} -> tier - 3 | K16: =IF('OG Hospitalisation Details'!I2330="?","Unknown",'OG Hospitalisation Details'!I2330) -> R1024 | L16: =DATEDIF(F16,DATE(2023,6,8),"Y") -> 61
A17: Id16 | B17: =VALUE(SUBSTITUTE(A17,"Id","")) -> 16 | C17: =IF('OG Hospitalisation Details'!B2329="?",ROUND(AVERAGE('OG Hospitalisation Details'!$B$2:$B$2344),0),'OG Hospitalisation Details'!B2329) -> 1962 | D17: =IF('OG Hospitalisation Details'!C2329="?","Sep",'OG Hospitalisation Details'!C2329) -> Aug | E17: 27 | F17: =DATE(C17,MONTH(1&D17),E17) -> 22885 | G17: 0 | H17: 48173.36 | I17: {=INDEX({"tier - 1","tier - 2","tier - 3"},MATCH(MAX(COUNTIF('OG Hospitalisation Details'!G2329:G4671,{"tier - 1","tier - 2","tier - 3"})),COUNTIF('OG Hospitalisation Details'!G2329:G4671,{"tier - 1","tier - 2","tier - 3"}),0))} -> tier - 1 | J17: {=INDEX({"tier - 1","tier - 2","tier - 3"},MATCH(MAX(COUNTIF('OG Hospitalisation Details'!H2329:H4671,{"tier - 1","tier - 2","tier - 3"})),COUNTIF('OG Hospitalisation Details'!H2329:H4671,{"tier - 1","tier - 2","tier - 3"}),0))} -> tier - 3 | K17: =IF('OG Hospitalisation Details'!I2329="?","Unknown",'OG Hospitalisation Details'!I2329) -> R1011 | L17: =DATEDIF(F17,DATE(2023,6,8),"Y") -> 60
A18: Id17 | B18: =VALUE(SUBSTITUTE(A18,"Id","")) -> 17 | C18: =IF('OG Hospitalisation Details'!B2328="?",ROUND(AVERAGE('OG Hospitalisation Details'!$B$2:$B$2344),0),'OG Hospitalisation Details'!B2328) -> 1958 | D18: =IF('OG Hospitalisation Details'!C2328="?","Sep",'OG Hospitalisation Details'!C2328) -> Nov | E18: 16 | F18: =DATE(C18,MONTH(1&D18),E18) -> 21505 | G18: 1 | H18: 47928.03 | I18: {=INDEX({"tier - 1","tier - 2","tier - 3"},MATCH(MAX(COUNTIF('OG Hospitalisation Details'!G2328:G4670,{"tier - 1","tier - 2","tier - 3"})),COUNTIF('OG Hospitalisation Details'!G2328:G4670,{"tier - 1","tier - 2","tier - 3"}),0))} -> tier - 1 | J18: {=INDEX({"tier - 1","tier - 2","tier - 3"},MATCH(MAX(COUNTIF('OG Hospitalisation Details'!H2328:H4670,{"tier - 1","tier - 2","tier - 3"})),COUNTIF('OG Hospitalisation Details'!H2328:H4670,{"tier - 1","tier - 2","tier - 3"}),0))} -> tier - 3 | K18: =IF('OG Hospitalisation Details'!I2328="?","Unknown",'OG Hospitalisation Details'!I2328) -> R1011 | L18: =DATEDIF(F18,DATE(2023,6,8),"Y") -> 64
A19: Id18 | B19: =VALUE(SUBSTITUTE(A19,"Id","")) -> 18 | C19: =IF('OG Hospitalisation Details'!B2327="?",ROUND(AVERAGE('OG Hospitalisation Details'!$B$2:$B$2344),0),'OG Hospitalisation Details'!B2327) -> 1963 | D19: =IF('OG Hospitalisation Details'!C2327="?","Sep",'OG Hospitalisation Details'!C2327) -> Aug | E19: 5 | F19: =DATE(C19,MONTH(1&D19),E19) -> 23228 | G19: 1 | H19: 47896.79 | I19: {=INDEX({"tier - 1","tier - 2","tier - 3"},MATCH(MAX(COUNTIF('OG Hospitalisation Details'!G2327:G4669,{"tier - 1","tier - 2","tier - 3"})),COUNTIF('OG Hospitalisation Details'!G2327:G4669,{"tier - 1","tier - 2","tier - 3"}),0))} -> tier - 1 | J19: {=INDEX({"tier - 1","tier - 2","tier - 3"},MATCH(MAX(COUNTIF('OG Hospitalisation Details'!H2327:H4669,{"tier - 1","tier - 2","tier - 3"})),COUNTIF('OG Hospitalisation Details'!H2327:H4669,{"tier - 1","tier - 2","tier - 3"}),0))} -> tier - 3 | K19: =IF('OG Hospitalisation Details'!I2327="?","Unknown",'OG Hospitalisation Details'!I2327) -> R1024 | L19: =DATEDIF(F19,DATE(2023,6,8),"Y") -> 59
A20: Id19 | B20: =VALUE(SUBSTITUTE(A20,"Id","")) -> 19 | C20: =IF('OG Hospitalisation Details'!B2326="?",ROUND(AVERAGE('OG Hospitalisation Details'!$B$2:$B$2344),0),'OG Hospitalisation Details'!B2326) -> 1964 | D20: =IF('OG Hospitalisation Details'!C2326="?","Sep",'OG Hospitalisation Details'!C2326) -> Nov | E20: 7 | F20: =DATE(C20,MONTH(1&D20),E20) -> 23688 | G20: 2 | H20: 47496.49 | I20: {=INDEX({"tier - 1","tier - 2","tier - 3"},MATCH(MAX(COUNTIF('OG Hospitalisation Details'!G2326:G4668,{"tier - 1","tier - 2","tier - 3"})),COUNTIF('OG Hospitalisation Details'!G2326:G4668,{"tier - 1","tier - 2","tier - 3"}),0))} -> tier - 1 | J20: {=INDEX({"tier - 1","tier - 2","tier - 3"},MATCH(MAX(COUNTIF('OG Hospitalisation Details'!H2326:H4668,{"tier - 1","tier - 2","tier - 3"})),COUNTIF('OG Hospitalisation Details'!H2326:H4668,{"tier - 1","tier - 2","tier - 3"}),0))} -> tier - 3 | K20: =IF('OG Hospitalisation Details'!I2326="?","Unknown",'OG Hospitalisation Details'!I2326) -> R1012 | L20: =DATEDIF(F20,DATE(2023,6,8),"Y") -> 58
A21: Id20 | B21: =VALUE(SUBSTITUTE(A21,"Id","")) -> 20 | C21: =IF('OG Hospitalisation Details'!B2325="?",ROUND(AVERAGE('OG Hospitalisation Details'!$B$2:$B$2344),0),'OG Hospitalisation Details'!B2325) -> 1971 | D21: =IF('OG Hospitalisation Details'!C2325="?","Sep",'OG Hospitalisation Details'!C2325) -> Sep | E21: 27 | F21: =DATE(C21,MONTH(1&D21),E21) -> 26203 | G21: 2 | H21: 47462.89 | I21: {=INDEX({"tier - 1","tier - 2","tier - 3"},MATCH(MAX(COUNTIF('OG Hospitalisation Details'!G2325:G4667,{"tier - 1","tier - 2","tier - 3"})),COUNTIF('OG Hospitalisation Details'!G2325:G4667,{"tier - 1","tier - 2","tier - 3"}),0))} -> tier - 1 | J21: {=INDEX({"tier - 1","tier - 2","tier - 3"},MATCH(MAX(COUNTIF('OG Hospitalisation Details'!H2325:H4667,{"tier - 1","tier - 2","tier - 3"})),COUNTIF('OG Hospitalisation Details'!H2325:H4667,{"tier - 1","tier - 2","tier - 3"}),0))} -> tier - 3 | K21: =IF('OG Hospitalisation Details'!I2325="?","Unknown",'OG Hospitalisation Details'!I2325) -> R1013 | L21: =DATEDIF(F21,DATE(2023,6,8),"Y") -> 51
A22: Id21 | B22: =VALUE(SUBSTITUTE(A22,"Id","")) -> 21 | C22: =IF('OG Hospitalisation Details'!B2324="?",ROUND(AVERAGE('OG Hospitalisation Details'!$B$2:$B$2344),0),'OG Hospitalisation Details'!B2324) -> 1961 | D22: =IF('OG Hospitalisation Details'!C2324="?","Sep",'OG Hospitalisation Details'!C2324) -> Jun | E22: 13 | F22: =DATE(C22,MONTH(1&D22),E22) -> 22445 | G22: 1 | H22: 47403.88 | I22: {=INDEX({"tier - 1","tier - 2","tier - 3"},MATCH(MAX(COUNTIF('OG Hospitalisation Details'!G2324:G4666,{"tier - 1","tier - 2","tier - 3"})),COUNTIF('OG Hospitalisation Details'!G2324:G4666,{"tier - 1","tier - 2","tier - 3"}),0))} -> tier - 1 | J22: {=INDEX({"tier - 1","tier - 2","tier - 3"},MATCH(MAX(COUNTIF('OG Hospitalisation Details'!H2324:H4666,{"tier - 1","tier - 2","tier - 3"})),COUNTIF('OG Hospitalisation Details'!H2324:H4666,{"tier - 1","tier - 2","tier - 3"}),0))} -> tier - 3 | K22: =IF('OG Hospitalisation Details'!I2324="?","Unknown",'OG Hospitalisation Details'!I2324) -> R1011 | L22: =DATEDIF(F22,DATE(2023,6,8),"Y") -> 61
A23: Id22 | B23: =VALUE(SUBSTITUTE(A23,"Id","")) -> 22 | C23: =IF('OG Hospitalisation Details'!B2323="?",ROUND(AVERAGE('OG Hospitalisation Details'!$B$2:$B$2344),0),'OG Hospitalisation Details'!B2323) -> 1959 | D23: =IF('OG Hospitalisation Details'!C2323="?","Sep",'OG Hospitalisation Details'!C2323) -> Oct | E23: 4 | F23: =DATE(C23,MONTH(1&D23),E23) -> 21827 | G23: 2 | H23: 47305.31 | I23: {=INDEX({"tier - 1","tier - 2","tier - 3"},MATCH(MAX(COUNTIF('OG Hospitalisation Details'!G2323:G4665,{"tier - 1","tier - 2","tier - 3"})),COUNTIF('OG Hospitalisation Details'!G2323:G4665,{"tier - 1","tier - 2","tier - 3"}),0))} -> tier - 1 | J23: {=INDEX({"tier - 1","tier - 2","tier - 3"},MATCH(MAX(COUNTIF('OG Hospitalisation Details'!H2323:H4665,{"tier - 1","tier - 2","tier - 3"})),COUNTIF('OG Hospitalisation Details'!H2323:H4665,{"tier - 1","tier - 2","tier - 3"}),0))} -> tier - 3 | K23: =IF('OG Hospitalisation Details'!I2323="?","Unknown",'OG Hospitalisation Details'!I2323) -> R1011 | L23: =DATEDIF(F23,DATE(2023,6,8),"Y") -> 63
A24: Id23 | B24: =VALUE(SUBSTITUTE(A24,"Id","")) -> 23 | C24: =IF('OG Hospitalisation Details'!B2322="?",ROUND(AVERAGE('OG Hospitalisation Details'!$B$2:$B$2344),0),'OG Hospitalisation Details'!B2322) -> 1958 | D24: =IF('OG Hospitalisation Details'!C2322="?","Sep",'OG Hospitalisation Details'!C2322) -> Sep | E24: 3 | F24: =DATE(C24,MONTH(1&D24),E24) -> 21431 | G24: 2 | H24: 47291.06 | I24: {=INDEX({"tier - 1","tier - 2","tier - 3"},MATCH(MAX(COUNTIF('OG Hospitalisation Details'!G2322:G4664,{"tier - 1","tier - 2","tier - 3"})),COUNTIF('OG Hospitalisation Details'!G2322:G4664,{"tier - 1","tier - 2","tier - 3"}),0))} -> tier - 1 | J24: {=INDEX({"tier - 1","tier - 2","tier - 3"},MATCH(MAX(COUNTIF('OG Hospitalisation Details'!H2322:H4664,{"tier - 1","tier - 2","tier - 3"})),COUNTIF('OG Hospitalisation Details'!H2322:H4664,{"tier - 1","tier - 2","tier - 3"}),0))} -> tier - 3 | K24: =IF('OG Hospitalisation Details'!I2322="?","Unknown",'OG Hospitalisation Details'!I2322) -> R1011 | L24: =DATEDIF(F24,DATE(2023,6,8),"Y") -> 64
A25: Id24 | B25: =VALUE(SUBSTITUTE(A25,"Id","")) -> 24 | C25: =IF('OG Hospitalisation Details'!B2321="?",ROUND(AVERAGE('OG Hospitalisation Details'!$B$2:$B$2344),0),'OG Hospitalisation Details'!B2321) -> 1970 | D25: =IF('OG Hospitalisation Details'!C2321="?","Sep",'OG Hospitalisation Details'!C2321) -> Dec | E25: 28 | F25: =DATE(C25,MONTH(1&D25),E25) -> 25930 | G25: 2 | H25: 47269.85 | I25: {=INDEX({"tier - 1","tier - 2","tier - 3"},MATCH(MAX(COUNTIF('OG Hospitalisation Details'!G2321:G4663,{"tier - 1","tier - 2","tier - 3"})),COUNTIF('OG Hospitalisation Details'!G2321:G4663,{"tier - 1","tier - 2","tier - 3"}),0))} -> tier - 1 | J25: {=INDEX({"tier - 1","tier - 2","tier - 3"},MATCH(MAX(COUNTIF('OG Hospitalisation Details'!H2321:H4663,{"tier - 1","tier - 2","tier - 3"})),COUNTIF('OG Hospitalisation Details'!H2321:H4663,{"tier - 1","tier - 2","tier - 3"}),0))} -> tier - 3 | K25: =IF('OG Hospitalisation Details'!I2321="?","Unknown",'OG Hospitalisation Details'!I2321) -> R1013 | L25: =DATEDIF(F25,DATE(2023,6,8),"Y") -> 52
A26: Id25 | B26: =VALUE(SUBSTITUTE(A26,"Id","")) -> 25 | C26: =IF('OG Hospitalisation Details'!B2320="?",ROUND(AVERAGE('OG Hospitalisation Details'!$B$2:$B$2344),0),'OG Hospitalisation Details'!B2320) -> 1959 | D26: =IF('OG Hospitalisation Details'!C2320="?","Sep",'OG Hospitalisation Details'!C2320) -> Jul | E26: 14 | F26: =DATE(C26,MONTH(1&D26),E26) -> 21745 | G26: 0 | H26: 47055.53 | I26: {=INDEX({"tier - 1","tier - 2","tier - 3"},MATCH(MAX(COUNTIF('OG Hospitalisation Details'!G2320:G4662,{"tier - 1","tier - 2","tier - 3"})),COUNTIF('OG Hospitalisation Details'!G2320:G4662,{"tier - 1","tier - 2","tier - 3"}),0))} -> tier - 1 | J26: {=INDEX({"tier - 1","tier - 2","tier - 3"},MATCH(MAX(COUNTIF('OG Hospitalisation Details'!H2320:H4662,{"tier - 1","tier - 2","tier - 3"})),COUNTIF('OG Hospitalisation Details'!H2320:H4662,{"tier - 1","tier - 2","tier - 3"}),0))} -> tier - 3 | K26: =IF('OG Hospitalisation Details'!I2320="?","Unknown",'OG Hospitalisation Details'!I2320) -> R1013 | L26: =DATEDIF(F26,DATE(2023,6,8),"Y") -> 63
A27: Id26 | B27: =VALUE(SUBSTITUTE(A27,"Id","")) -> 26 | C27: =IF('OG Hospitalisation Details'!B2319="?",ROUND(AVERAGE('OG Hospitalisation Details'!$B$2:$B$2344),0),'OG Hospitalisation Details'!B2319) -> 1958 | D27: =IF('OG Hospitalisation Details'!C2319="?","Sep",'OG Hospitalisation Details'!C2319) -> Sep | E27: 15 | F27: =DATE(C27,MONTH(1&D27),E27) -> 21443 | G27: 0 | H27: 46889.26 | I27: {=INDEX({"tier - 1","tier - 2","tier - 3"},MATCH(MAX(COUNTIF('OG Hospitalisation Details'!G2319:G4661,{"tier - 1","tier - 2","tier - 3"})),COUNTIF('OG Hospitalisation Details'!G2319:G4661,{"tier - 1","tier - 2","tier - 3"}),0))} -> tier - 1 | J27: {=INDEX({"tier - 1","tier - 2","tier - 3"},MATCH(MAX(COUNTIF('OG Hospitalisation Details'!H2319:H4661,{"tier - 1","tier - 2","tier - 3"})),COUNTIF('OG Hospitalisation Details'!H2319:H4661,{"tier - 1","tier - 2","tier - 3"}),0))} -> tier - 3 | K27: =IF('OG Hospitalisation Details'!I2319="?","Unknown",'OG Hospitalisation Details'!I2319) -> R1013 | L27: =DATEDIF(F27,DATE(2023,6,8),"Y") -> 64
A28: Id27 | B28: =VALUE(SUBSTITUTE(A28,"Id","")) -> 27 | C28: =IF('OG Hospitalisation Details'!B2318="?",ROUND(AVERAGE('OG Hospitalisation Details'!$B$2:$B$2344),0),'OG Hospitalisation Details'!B2318) -> 1960 | D28: =IF('OG Hospitalisation Details'!C2318="?","Sep",'OG Hospitalisation Details'!C2318) -> Nov | E28: 17 | F28: =DATE(C28,MONTH(1&D28),E28) -> 22237 | G28: 3 | H28: 46718.16 | I28: {=INDEX({"tier - 1","tier - 2","tier - 3"},MATCH(MAX(COUNTIF('OG Hospitalisation Details'!G2318:G4660,{"tier - 1","tier - 2","tier - 3"})),COUNTIF('OG Hospitalisation Details'!G2318:G4660,{"tier - 1","tier - 2","tier - 3"}),0))} -> tier - 1 | J28: {=INDEX({"tier - 1","tier - 2","tier - 3"},MATCH(MAX(COUNTIF('OG Hospitalisation Details'!H2318:H4660,{"tier - 1","tier - 2","tier - 3"})),COUNTIF('OG Hospitalisation Details'!H2318:H4660,{"tier - 1","tier - 2","tier - 3"}),0))} -> tier - 3 | K28: =IF('OG Hospitalisation Details'!I2318="?","Unknown",'OG Hospitalisation Details'!I2318) -> R1012 | L28: =DATEDIF(F28,DATE(2023,6,8),"Y") -> 62
A29: Id28 | B29: =VALUE(SUBSTITUTE(A29,"Id","")) -> 28 | C29: =IF('OG Hospitalisation Details'!B2317="?",ROUND(AVERAGE('OG Hospitalisation Details'!$B$2:$B$2344),0),'OG Hospitalisation Details'!B2317) -> 1969 | D29: =IF('OG Hospitalisation Details'!C2317="?","Sep",'OG Hospitalisation Details'!C2317) -> Jun | E29: 23 | F29: =DATE(C29,MONTH(1&D29),E29) -> 25377 | G29: 3 | H29: 46661.44 | I29: {=INDEX({"tier - 1","tier - 2","tier - 3"},MATCH(MAX(COUNTIF('OG Hospitalisation Details'!G2317:G4659,{"tier - 1","tier - 2","tier - 3"})),COUNTIF('OG Hospitalisation Details'!G2317:G4659,{"tier - 1","tier - 2","tier - 3"}),0))} -> tier - 1 | J29: {=INDEX({"tier - 1","tier - 2","tier - 3"},MATCH(MAX(COUNTIF('OG Hospitalisation Details'!H2317:H4659,{"tier - 1","tier - 2","tier - 3"})),COUNTIF('OG Hospitalisation Details'!H2317:H4659,{"tier - 1","tier - 2","tier - 3"}),0))} -> tier - 3 | K29: =IF('OG Hospitalisation Details'!I2317="?","Unknown",'OG Hospitalisation Details'!I2317) -> R1012 | L29: =DATEDIF(F29,DATE(2023,6,8),"Y") -> 53
A30: Id29 | B30: =VALUE(SUBSTITUTE(A30,"Id","")) -> 29 | C30: =IF('OG Hospitalisation Details'!B2316="?",ROUND(AVERAGE('OG Hospitalisation Details'!$B$2:$B$2344),0),'OG Hospitalisation Details'!B2316) -> 1961 | D30: =IF('OG Hospitalisation Details'!C2316="?","Sep",'OG Hospitalisation Details'!C2316) -> Aug | E30: 8 | F30: =DATE(C30,MONTH(1&D30),E30) -> 22501 | G30: 0 | H30: 46599.11 | I30: {=INDEX({"tier - 1","tier - 2","tier - 3"},MATCH(MAX(COUNTIF('OG Hospitalisation Details'!G2316:G4658,{"tier - 1","tier - 2","tier - 3"})),COUNTIF('OG Hospitalisation Details'!G2316:G4658,{"tier - 1","tier - 2","tier - 3"}),0))} -> tier - 1 | J30: {=INDEX({"tier - 1","tier - 2","tier - 3"},MATCH(MAX(COUNTIF('OG Hospitalisation Details'!H2316:H4658,{"tier - 1","tier - 2","tier - 3"})),COUNTIF('OG Hospitalisation Details'!H2316:H4658,{"tier - 1","tier - 2","tier - 3"}),0))} -> tier - 3 | K30: =IF('OG Hospitalisation Details'!I2316="?","Unknown",'OG Hospitalisation Details'!I2316) -> R1013 | L30: =DATEDIF(F30,DATE(2023,6,8),"Y") -> 61
A31: Id30 | B31: =VALUE(SUBSTITUTE(A31,"Id","")) -> 30 | C31: =IF('OG Hospitalisation Details'!B2315="?",ROUND(AVERAGE('OG Hospitalisation Details'!$B$2:$B$2344),0),'OG Hospitalisation Details'!B2315) -> 1971 | D31: =IF('OG Hospitalisation Details'!C2315="?","Sep",'OG Hospitalisation Details'!C2315) -> Dec | E31: 6 | F31: =DATE(C31,MONTH(1&D31),E31) -> 26273 | G31: 3 | H31: 46255.11 | I31: {=INDEX({"tier - 1","tier - 2","tier - 3"},MATCH(MAX(COUNTIF('OG Hospitalisation Details'!G2315:G4657,{"tier - 1","tier - 2","tier - 3"})),COUNTIF('OG Hospitalisation Details'!G2315:G4657,{"tier - 1","tier - 2","tier - 3"}),0))} -> tier - 1 | J31: {=INDEX({"tier - 1","tier - 2","tier - 3"},MATCH(MAX(COUNTIF('OG Hospitalisation Details'!H2315:H4657,{"tier - 1","tier - 2","tier - 3"})),COUNTIF('OG Hospitalisation Details'!H2315:H4657,{"tier - 1","tier - 2","tier - 3"}),0))} -> tier - 3 | K31: =IF('OG Hospitalisation Details'!I2315="?","Unknown",'OG Hospitalisation Details'!I2315) -> R1024 | L31: =DATEDIF(F31,DATE(2023,6,8),"Y") -> 51
A32: Id31 | B32: =VALUE(SUBSTITUTE(A32,"Id","")) -> 31 | C32: =IF('OG Hospitalisation Details'!B2314="?",ROUND(AVERAGE('OG Hospitalisation Details'!$B$2:$B$2344),0),'OG Hospitalisation Details'!B2314) -> 1978 | D32: =IF('OG Hospitalisation Details'!C2314="?","Sep",'OG Hospitalisation Details'!C2314) -> Aug | E32: 17 | F32: =DATE(C32,MONTH(1&D32),E32) -> 28719 | G32: 2 | H32: 46200.99 | I32: {=INDEX({"tier - 1","tier - 2","tier - 3"},MATCH(MAX(COUNTIF('OG Hospitalisation Details'!G2314:G4656,{"tier - 1","tier - 2","tier - 3"})),COUNTIF('OG Hospitalisation Details'!G2314:G4656,{"tier - 1","tier - 2","tier - 3"}),0))} -> tier - 1 | J32: {=INDEX({"tier - 1","tier - 2","tier - 3"},MATCH(MAX(COUNTIF('OG Hospitalisation Details'!H2314:H4656,{"tier - 1","tier - 2","tier - 3"})),COUNTIF('OG Hospitalisation Details'!H2314:H4656,{"tier - 1","tier - 2","tier - 3"}),0))} -> tier - 3 | K32: =IF('OG Hospitalisation Details'!I2314="?","Unknown",'OG Hospitalisation Details'!I2314) -> R1013 | L32: =DATEDIF(F32,DATE(2023,6,8),"Y") -> 44
A33: Id32 | B33: =VALUE(SUBSTITUTE(A33,"Id","")) -> 32 | C33: =IF('OG Hospitalisation Details'!B2313="?",ROUND(AVERAGE('OG Hospitalisation Details'!$B$2:$B$2344),0),'OG Hospitalisation Details'!B2313) -> 1976 | D33: =IF('OG Hospitalisation Details'!C2313="?","Sep",'OG Hospitalisation Details'!C2313) -> Dec | E33: 2 | F33: =DATE(C33,MONTH(1&D33),E33) -> 28096 | G33: 3 | H33: 46151.12 | I33: {=INDEX({"tier - 1","tier - 2","tier - 3"},MATCH(MAX(COUNTIF('OG Hospitalisation Details'!G2313:G4655,{"tier - 1","tier - 2","tier - 3"})),COUNTIF('OG Hospitalisation Details'!G2313:G4655,{"tier - 1","tier - 2","tier - 3"}),0))} -> tier - 1 | J33: {=INDEX({"tier - 1","tier - 2","tier - 3"},MATCH(MAX(COUNTIF('OG Hospitalisation Details'!H2313:H4655,{"tier - 1","tier - 2","tier - 3"})),COUNTIF('OG Hospitalisation Details'!H2313:H4655,{"tier - 1","tier - 2","tier - 3"}),0))} -> tier - 3 | K33: =IF('OG Hospitalisation Details'!I2313="?","Unknown",'OG Hospitalisation Details'!I2313) -> R1013 | L33: =DATEDIF(F33,DATE(2023,6,8),"Y") -> 46
A34: Id33 | B34: =VALUE(SUBSTITUTE(A34,"Id","")) -> 33 | C34: =IF('OG Hospitalisation Details'!B2312="?",ROUND(AVERAGE('OG Hospitalisation Details'!$B$2:$B$2344),0),'OG Hospitalisation Details'!B2312) -> 1962 | D34: =IF('OG Hospitalisation Details'!C2312="?","Sep",'OG Hospitalisation Details'!C2312) -> Dec | E34: 4 | F34: =DATE(C34,MONTH(1&D34),E34) -> 22984 | G34: 3 | H34: 46130.53 | I34: {=INDEX({"tier - 1","tier - 2","tier - 3"},MATCH(MAX(COUNTIF('OG Hospitalisation Details'!G2312:G4654,{"tier - 1","tier - 2","tier - 3"})),COUNTIF('OG Hospitalisation Details'!G2312:G4654,{"tier - 1","tier - 2","tier - 3"}),0))} -> tier - 1 | J34: {=INDEX({"tier - 1","tier - 2","tier - 3"},MATCH(MAX(COUNTIF('OG Hospitalisation Details'!H2312:H4654,{"tier - 1","tier - 2","tier - 3"})),COUNTIF('OG Hospitalisation Details'!H2312:H4654,{"tier - 1","tier - 2","tier - 3"}),0))} -> tier - 3 | K34: =IF('OG Hospitalisation Details'!I2312="?","Unknown",'OG Hospitalisation Details'!I2312) -> R1012 | L34: =DATEDIF(F34,DATE(2023,6,8),"Y") -> 60
A35: Id34 | B35: =VALUE(SUBSTITUTE(A35,"Id","")) -> 34 | C35: =IF('OG Hospitalisation Details'!B2311="?",ROUND(AVERAGE('OG Hospitalisation Details'!$B$2:$B$2344),0),'OG Hospitalisation Details'!B2311) -> 1985 | D35: =IF('OG Hospitalisation Details'!C2311="?","Sep",'OG Hospitalisation Details'!C2311) -> Sep | E35: 30 | F35: =DATE(C35,MONTH(1&D35),E35) -> 31320 | G35: 2 | H35: 46113.51 | I35: {=INDEX({"tier - 1","tier - 2","tier - 3"},MATCH(MAX(COUNTIF('OG Hospitalisation Details'!G2311:G4653,{"tier - 1","tier - 2","tier - 3"})),COUNTIF('OG Hospitalisation Details'!G2311:G4653,{"tier - 1","tier - 2","tier - 3"}),0))} -> tier - 1 | J35: {=INDEX({"tier - 1","tier - 2","tier - 3"},MATCH(MAX(COUNTIF('OG Hospitalisation Details'!H2311:H4653,{"tier - 1","tier - 2","tier - 3"})),COUNTIF('OG Hospitalisation Details'!H2311:H4653,{"tier - 1","tier - 2","tier - 3"}),0))} -> tier - 3 | K35: =IF('OG Hospitalisation Details'!I2311="?","Unknown",'OG Hospitalisation Details'!I2311) -> R1011 | L35: =DATEDIF(F35,DATE(2023,6,8),"Y") -> 37
A36: Id35 | B36: =VALUE(SUBSTITUTE(A36,"Id","")) -> 35 | C36: =IF('OG Hospitalisation Details'!B2310="?",ROUND(AVERAGE('OG Hospitalisation Details'!$B$2:$B$2344),0),'OG Hospitalisation Details'!B2310) -> 1979 | D36: =IF('OG Hospitalisation Details'!C2310="?","Sep",'OG Hospitalisation Details'!C2310) -> Aug | E36: 12 | F36: =DATE(C36,MONTH(1&D36),E36) -> 29079 | G36: 0 | H36: 45863.21 | I36: {=INDEX({"tier - 1","tier - 2","tier - 3"},MATCH(MAX(COUNTIF('OG Hospitalisation Details'!G2310:G4652,{"tier - 1","tier - 2","tier - 3"})),COUNTIF('OG Hospitalisation Details'!G2310:G4652,{"tier - 1","tier - 2","tier - 3"}),0))} -> tier - 1 | J36: {=INDEX({"tier - 1","tier - 2","tier - 3"},MATCH(MAX(COUNTIF('OG Hospitalisation Details'!H2310:H4652,{"tier - 1","tier - 2","tier - 3"})),COUNTIF('OG Hospitalisation Details'!H2310:H4652,{"tier - 1","tier - 2","tier - 3"}),0))} -> tier - 3 | K36: =IF('OG Hospitalisation Details'!I2310="?","Unknown",'OG Hospitalisation Details'!I2310) -> R1013 | L36: =DATEDIF(F36,DATE(2023,6,8),"Y") -> 43
A37: Id36 | B37: =VALUE(SUBSTITUTE(A37,"Id","")) -> 36 | C37: =IF('OG Hospitalisation Details'!B2309="?",ROUND(AVERAGE('OG Hospitalisation Details'!$B$2:$B$2344),0),'OG Hospitalisation Details'!B2309) -> 1960 | D37: =IF('OG Hospitalisation Details'!C2309="?","Sep",'OG Hospitalisation Details'!C2309) -> Dec | E37: 21 | F37: =DATE(C37,MONTH(1&D37),E37) -> 22271 | G37: 0 | H37: 45710.21 | I37: {=INDEX({"tier - 1","tier - 2","tier - 3"},MATCH(MAX(COUNTIF('OG Hospitalisation Details'!G2309:G4651,{"tier - 1","tier - 2","tier - 3"})),COUNTIF('OG Hospitalisation Details'!G2309:G4651,{"tier - 1","tier - 2","tier - 3"}),0))} -> tier - 1 | J37: {=INDEX({"tier - 1","tier - 2","tier - 3"},MATCH(MAX(COUNTIF('OG Hospitalisation Details'!H2309:H4651,{"tier - 1","tier - 2","tier - 3"})),COUNTIF('OG Hospitalisation Details'!H2309:H4651,{"tier - 1","tier - 2","tier - 3"}),0))} -> tier - 3 | K37: =IF('OG Hospitalisation Details'!I2309="?","Unknown",'OG Hospitalisation Details'!I2309) -> R1016 | L37: =DATEDIF(F37,DATE(2023,6,8),"Y") -> 62
A38: Id37 | B38: =VALUE(SUBSTITUTE(A38,"Id","")) -> 37 | C38: =IF('OG Hospitalisation Details'!B2308="?",ROUND(AVERAGE('OG Hospitalisation Details'!$B$2:$B$2344),0),'OG Hospitalisation Details'!B2308) -> 1974 | D38: =IF('OG Hospitalisation Details'!C2308="?","Sep",'OG Hospitalisation Details'!C2308) -> Aug | E38: 9 | F38: =DATE(C38,MONTH(1&D38),E38) -> 27250 | G38: 2 | H38: 45702.02 | I38: {=INDEX({"tier - 1","tier - 2","tier - 3"},MATCH(MAX(COUNTIF('OG Hospitalisation Details'!G2308:G4650,{"tier - 1","tier - 2","tier - 3"})),COUNTIF('OG Hospitalisation Details'!G2308:G4650,{"tier - 1","tier - 2","tier - 3"}),0))} -> tier - 1 | J38: {=INDEX({"tier - 1","tier - 2","tier - 3"},MATCH(MAX(COUNTIF('OG Hospitalisation Details'!H2308:H4650,{"tier - 1","tier - 2","tier - 3"})),COUNTIF('OG Hospitalisation Details'!H2308:H4650,{"tier - 1","tier - 2","tier - 3"}),0))} -> tier - 3 | K38: =IF('OG Hospitalisation Details'!I2308="?","Unknown",'OG Hospitalisation Details'!I2308) -> R1012 | L38: =DATEDIF(F38,DATE(2023,6,8),"Y") -> 48
A39: Id38 | B39: =VALUE(SUBSTITUTE(A39,"Id","")) -> 38 | C39: =IF('OG Hospitalisation Details'!B2307="?",ROUND(AVERAGE('OG Hospitalisation Details'!$B$2:$B$2344),0),'OG Hospitalisation Details'!B2307) -> 1962 | D39: =IF('OG Hospitalisation Details'!C2307="?","Sep",'OG Hospitalisation Details'!C2307) -> Dec | E39: 17 | F39: =DATE(C39,MONTH(1&D39),E39) -> 22997 | G39: 0 | H39: 45008.96 | I39: {=INDEX({"tier - 1","tier - 2","tier - 3"},MATCH(MAX(COUNTIF('OG Hospitalisation Details'!G2307:G4649,{"tier - 1","tier - 2","tier - 3"})),COUNTIF('OG Hospitalisation Details'!G2307:G4649,{"tier - 1","tier - 2","tier - 3"}),0))} -> tier - 1 | J39: {=INDEX({"tier - 1","tier - 2","tier - 3"},MATCH(MAX(COUNTIF('OG Hospitalisation Details'!H2307:H4649,{"tier - 1","tier - 2","tier - 3"})),COUNTIF('OG Hospitalisation Details'!H2307:H4649,{"tier - 1","tier - 2","tier - 3"}),0))} -> tier - 3 | K39: =IF('OG Hospitalisation Details'!I2307="?","Unknown",'OG Hospitalisation Details'!I2307) -> R1013 | L39: =DATEDIF(F39,DATE(2023,6,8),"Y") -> 60
A40: Id39 | B40: =VALUE(SUBSTITUTE(A40,"Id","")) -> 39 | C40: =IF('OG Hospitalisation Details'!B2306="?",ROUND(AVERAGE('OG Hospitalisation Details'!$B$2:$B$2344),0),'OG Hospitalisation Details'!B2306) -> 1971 | D40: =IF('OG Hospitalisation Details'!C2306="?","Sep",'OG Hospitalisation Details'!C2306) -> Aug | E40: 13 | F40: =DATE(C40,MONTH(1&D40),E40) -> 26158 | G40: 2 | H40: 44641.2 | I40: {=INDEX({"tier - 1","tier - 2","tier - 3"},MATCH(MAX(COUNTIF('OG Hospitalisation Details'!G2306:G4648,{"tier - 1","tier - 2","tier - 3"})),COUNTIF('OG Hospitalisation Details'!G2306:G4648,{"tier - 1","tier - 2","tier - 3"}),0))} -> tier - 1 | J40: {=INDEX({"tier - 1","tier - 2","tier - 3"},MATCH(MAX(COUNTIF('OG Hospitalisation Details'!H2306:H4648,{"tier - 1","tier - 2","tier - 3"})),COUNTIF('OG Hospitalisation Details'!H2306:H4648,{"tier - 1","tier - 2","tier - 3"}),0))} -> tier - 3 | K40: =IF('OG Hospitalisation Details'!I2306="?","Unknown",'OG Hospitalisation Details'!I2306) -> R1024 | L40: =DATEDIF(F40,DATE(2023,6,8),"Y") -> 51
A41: Id40 | B41: =VALUE(SUBSTITUTE(A41,"Id","")) -> 40 | C41: =IF('OG Hospitalisation Details'!B2305="?",ROUND(AVERAGE('OG Hospitalisation Details'!$B$2:$B$2344),0),'OG Hospitalisation Details'!B2305) -> 1993 | D41: =IF('OG Hospitalisation Details'!C2305="?","Sep",'OG Hospitalisation Details'!C2305) -> Oct | E41: 11 | F41: =DATE(C41,MONTH(1&D41),E41) -> 34253 | G41: 2 | H41: 44585.46 | I41: {=INDEX({"tier - 1","tier - 2","tier - 3"},MATCH(MAX(COUNTIF('OG Hospitalisation Details'!G2305:G4647,{"tier - 1","tier - 2","tier - 3"})),COUNTIF('OG Hospitalisation Details'!G2305:G4647,{"tier - 1","tier - 2","tier - 3"}),0))} -> tier - 1 | J41: {=INDEX({"tier - 1","tier - 2","tier - 3"},MATCH(MAX(COUNTIF('OG Hospitalisation Details'!H2305:H4647,{"tier - 1","tier - 2","tier - 3"})),COUNTIF('OG Hospitalisation Details'!H2305:H4647,{"tier - 1","tier - 2","tier - 3"}),0))} -> tier - 3 | K41: =IF('OG Hospitalisation Details'!I2305="?","Unknown",'OG Hospitalisation Details'!I2305) -> R1011 | L41: =DATEDIF(F41,DATE(2023,6,8),"Y") -> 29
A42: Id41 | B42: =VALUE(SUBSTITUTE(A42,"Id","")) -> 41 | C42: =IF('OG Hospitalisation Details'!B2304="?",ROUND(AVERAGE('OG Hospitalisation Details'!$B$2:$B$2344),0),'OG Hospitalisation Details'!B2304) -> 2000 | D42: =IF('OG Hospitalisation Details'!C2304="?","Sep",'OG Hospitalisation Details'!C2304) -> Aug | E42: 2 | F42: =DATE(C42,MONTH(1&D42),E42) -> 36740 | G42: 1 | H42: 44501.4 | I42: {=INDEX({"tier - 1","tier - 2","tier - 3"},MATCH(MAX(COUNTIF('OG Hospitalisation Details'!G2304:G4646,{"tier - 1","tier - 2","tier - 3"})),COUNTIF('OG Hospitalisation Details'!G2304:G4646,{"tier - 1","tier - 2","tier - 3"}),0))} -> tier - 1 | J42: {=INDEX({"tier - 1","tier - 2","tier - 3"},MATCH(MAX(COUNTIF('OG Hospitalisation Details'!H2304:H4646,{"tier - 1","tier - 2","tier - 3"})),COUNTIF('OG Hospitalisation Details'!H2304:H4646,{"tier - 1","tier - 2","tier - 3"}),0))} -> tier - 3 | K42: =IF('OG Hospitalisation Details'!I2304="?","Unknown",'OG Hospitalisation Details'!I2304) -> R1013 | L42: =DATEDIF(F42,DATE(2023,6,8),"Y") -> 22
A43: Id42 | B43: =VALUE(SUBSTITUTE(A43,"Id","")) -> 42 | C43: =IF('OG Hospitalisation Details'!B2303="?",ROUND(AVERAGE('OG Hospitalisation Details'!$B$2:$B$2344),0),'OG Hospitalisation Details'!B2303) -> 1967 | D43: =IF('OG Hospitalisation Details'!C2303="?","Sep",'OG Hospitalisation Details'!C2303) -> Sep | E43: 14 | F43: =DATE(C43,MONTH(1&D43),E43) -> 24729 | G43: 0 | H43: 44423.8 | I43: {=INDEX({"tier - 1","tier - 2","tier - 3"},MATCH(MAX(COUNTIF('OG Hospitalisation Details'!G2303:G4645,{"tier - 1","tier - 2","tier - 3"})),COUNTIF('OG Hospitalisation Details'!G2303:G4645,{"tier - 1","tier - 2","tier - 3"}),0))} -> tier - 1 | J43: {=INDEX({"tier - 1","tier - 2","tier - 3"},MATCH(MAX(COUNTIF('OG Hospitalisation Details'!H2303:H4645,{"tier - 1","tier - 2","tier - 3"})),COUNTIF('OG Hospitalisation Details'!H2303:H4645,{"tier - 1","tier - 2","tier - 3"}),0))} -> tier - 3 | K43: =IF('OG Hospitalisation Details'!I2303="?","Unknown",'OG Hospitalisation Details'!I2303) -> R1013 | L43: =DATEDIF(F43,DATE(2023,6,8),"Y") -> 55
A44: Id43 | B44: =VALUE(SUBSTITUTE(A44,"Id","")) -> 43 | C44: =IF('OG Hospitalisation Details'!B2302="?",ROUND(AVERAGE('OG Hospitalisation Details'!$B$2:$B$2344),0),'OG Hospitalisation Details'!B2302) -> 1971 | D44: =IF('OG Hospitalisation Details'!C2302="?","Sep",'OG Hospitalisation Details'!C2302) -> Oct | E44: 29 | F44: =DATE(C44,MONTH(1&D44),E44) -> 26235 | G44: 0 | H44: 44400.41 | I44: {=INDEX({"tier - 1","tier - 2","tier - 3"},MATCH(MAX(COUNTIF('OG Hospitalisation Details'!G2302:G4644,{"tier - 1","tier - 2","tier - 3"})),COUNTIF('OG Hospitalisation Details'!G2302:G4644,{"tier - 1","tier - 2","tier - 3"}),0))} -> tier - 1 | J44: {=INDEX({"tier - 1","tier - 2","tier - 3"},MATCH(MAX(COUNTIF('OG Hospitalisation Details'!H2302:H4644,{"tier - 1","tier - 2","tier - 3"})),COUNTIF('OG Hospitalisation Details'!H2302:H4644,{"tier - 1","tier - 2","tier - 3"}),0))} -> tier - 3 | K44: =IF('OG Hospitalisation Details'!I2302="?","Unknown",'OG Hospitalisation Details'!I2302) -> R1013 | L44: =DATEDIF(F44,DATE(2023,6,8),"Y") -> 51
A45: Id44 | B45: =VALUE(SUBSTITUTE(A45,"Id","")) -> 44 | C45: =IF('OG Hospitalisation Details'!B2301="?",ROUND(AVERAGE('OG Hospitalisation Details'!$B$2:$B$2344),0),'OG Hospitalisation Details'!B2301) -> 1968 | D45: =IF('OG Hospitalisation Details'!C2301="?","Sep",'OG Hospitalisation Details'!C2301) -> Nov | E45: 24 | F45: =DATE(C45,MONTH(1&D45),E45) -> 25166 | G45: 2 | H45: 44260.75 | I45: {=INDEX({"tier - 1","tier - 2","tier - 3"},MATCH(MAX(COUNTIF('OG Hospitalisation Details'!G2301:G4643,{"tier - 1","tier - 2","tier - 3"})),COUNTIF('OG Hospitalisation Details'!G2301:G4643,{"tier - 1","tier - 2","tier - 3"}),0))} -> tier - 1 | J45: {=INDEX({"tier - 1","tier - 2","tier - 3"},MATCH(MAX(COUNTIF('OG Hospitalisation Details'!H2301:H4643,{"tier - 1","tier - 2","tier - 3"})),COUNTIF('OG Hospitalisation Details'!H2301:H4643,{"tier - 1","tier - 2","tier - 3"}),0))} -> tier - 3 | K45: =IF('OG Hospitalisation Details'!I2301="?","Unknown",'OG Hospitalisation Details'!I2301) -> R1013 | L45: =DATEDIF(F45,DATE(2023,6,8),"Y") -> 54
A46: Id45 | B46: =VALUE(SUBSTITUTE(A46,"Id","")) -> 45 | C46: =IF('OG Hospitalisation Details'!B2300="?",ROUND(AVERAGE('OG Hospitalisation Details'!$B$2:$B$2344),0),'OG Hospitalisation Details'!B2300) -> 1975 | D46: =IF('OG Hospitalisation Details'!C2300="?","Sep",'OG Hospitalisation Details'!C2300) -> Jun | E46: 1 | F46: =DATE(C46,MONTH(1&D46),E46) -> 27546 | G46: 2 | H46: 44202.65 | I46: {=INDEX({"tier - 1","tier - 2","tier - 3"},MATCH(MAX(COUNTIF('OG Hospitalisation Details'!G2300:G4642,{"tier - 1","tier - 2","tier - 3"})),COUNTIF('OG Hospitalisation Details'!G2300:G4642,{"tier - 1","tier - 2","tier - 3"}),0))} -> tier - 1 | J46: {=INDEX({"tier - 1","tier - 2","tier - 3"},MATCH(MAX(COUNTIF('OG Hospitalisation Details'!H2300:H4642,{"tier - 1","tier - 2","tier - 3"})),COUNTIF('OG Hospitalisation Details'!H2300:H4642,{"tier - 1","tier - 2","tier - 3"}),0))} -> tier - 3 | K46: =IF('OG Hospitalisation Details'!I2300="?","Unknown",'OG Hospitalisation Details'!I2300) -> R1013 | L46: =DATEDIF(F46,DATE(2023,6,8),"Y") -> 48
A47: ? | C47: =IF('OG Hospitalisation Details'!B47="?",ROUND(AVERAGE('OG Hospitalisation Details'!$B$2:$B$2344),0),'OG Hospitalisation Details'!B47) -> 2004 | D47: =IF('OG Hospitalisation Details'!C47="?","Sep",'OG Hospitalisation Details'!C47) -> Nov | E47: 6 | F47: =DATE(C47,MONTH(1&D47),E47) -> 38297 | G47: 0 | H47: 1137.01 | I47: {=INDEX({"tier - 1","tier - 2","tier - 3"},MATCH(MAX(COUNTIF('OG Hospitalisation Details'!G47:G2389,{"tier - 1","tier - 2","tier - 3"})),COUNTIF('OG Hospitalisation Details'!G47:G2389,{"tier - 1","tier - 2","tier - 3"}),0))} -> tier - 2 | J47: {=INDEX({"tier - 1","tier - 2","tier - 3"},MATCH(MAX(COUNTIF('OG Hospitalisation Details'!H47:H2389,{"tier - 1","tier - 2","tier - 3"})),COUNTIF('OG Hospitalisation Details'!H47:H2389,{"tier - 1","tier - 2","tier - 3"}),0))} -> tier - 2 | K47: =IF('OG Hospitalisation Details'!I47="?","Unknown",'OG Hospitalisation Details'!I47) -> R1013 | L47: =DATEDIF(F47,DATE(2023,6,8),"Y") -> 18
A48: Id46 | B48: =VALUE(SUBSTITUTE(A48,"Id","")) -> 46 | C48: =IF('OG Hospitalisation Details'!B2299="?",ROUND(AVERAGE('OG Hospitalisation Details'!$B$2:$B$2344),0),'OG Hospitalisation Details'!B2299) -> 1988 | D48: =IF('OG Hospitalisation Details'!C2299="?","Sep",'OG Hospitalisation Details'!C2299) -> Jul | E48: 16 | F48: =DATE(C48,MONTH(1&D48),E48) -> 32340 | G48: 1 | H48: 43943.88 | I48: {=INDEX({"tier - 1","tier - 2","tier - 3"},MATCH(MAX(COUNTIF('OG Hospitalisation Details'!G2299:G4641,{"tier - 1","tier - 2","tier - 3"})),COUNTIF('OG Hospitalisation Details'!G2299:G4641,{"tier - 1","tier - 2","tier - 3"}),0))} -> tier - 1 | J48: {=INDEX({"tier - 1","tier - 2","tier - 3"},MATCH(MAX(COUNTIF('OG Hospitalisation Details'!H2299:H4641,{"tier - 1","tier - 2","tier - 3"})),COUNTIF('OG Hospitalisation Details'!H2299:H4641,{"tier - 1","tier - 2","tier - 3"}),0))} -> tier - 3 | K48: =IF('OG Hospitalisation Details'!I2299="?","Unknown",'OG Hospitalisation Details'!I2299) -> R1012 | L48: =DATEDIF(F48,DATE(2023,6,8),"Y") -> 34
A49: Id47 | B49: =VALUE(SUBSTITUTE(A49,"Id","")) -> 47 | C49: =IF('OG Hospitalisation Details'!B2298="?",ROUND(AVERAGE('OG Hospitalisation Details'!$B$2:$B$2344),0),'OG Hospitalisation Details'!B2298) -> 1966 | D49: =IF('OG Hospitalisation Details'!C2298="?","Sep",'OG Hospitalisation Details'!C2298) -> Oct | E49: 5 | F49: =DATE(C49,MONTH(1&D49),E49) -> 24385 | G49: 0 | H49: 43921.18 | I49: {=INDEX({"tier - 1","tier - 2","tier - 3"},MATCH(MAX(COUNTIF('OG Hospitalisation Details'!G2298:G4640,{"tier - 1","tier - 2","tier - 3"})),COUNTIF('OG Hospitalisation Details'!G2298:G4640,{"tier - 1","tier - 2","tier - 3"}),0))} -> tier - 1 | J49: {=INDEX({"tier - 1","tier - 2","tier - 3"},MATCH(MAX(COUNTIF('OG Hospitalisation Details'!H2298:H4640,{"tier - 1","tier - 2","tier - 3"})),COUNTIF('OG Hospitalisation Details'!H2298:H4640,{"tier - 1","tier - 2","tier - 3"}),0))} -> tier - 3 | K49: =IF('OG Hospitalisation Details'!I2298="?","Unknown",'OG Hospitalisation Details'!I2298) -> R1012 | L49: =DATEDIF(F49,DATE(2023,6,8),"Y") -> 56
A50: Id48 | B50: =VALUE(SUBSTITUTE(A50,"Id","")) -> 48 | C50: =IF('OG Hospitalisation Details'!B2297="?",ROUND(AVERAGE('OG Hospitalisation Details'!$B$2:$B$2344),0),'OG Hospitalisation Details'!B2297) -> 1980 | D50: =IF('OG Hospitalisation Details'!C2297="?","Sep",'OG Hospitalisation Details'!C2297) -> Nov | E50: 10 | F50: =DATE(C50,MONTH(1&D50),E50) -> 29535 | G50: 2 | H50: 43896.38 | I50: {=INDEX({"tier - 1","tier - 2","tier - 3"},MATCH(MAX(COUNTIF('OG Hospitalisation Details'!G2297:G4639,{"tier - 1","tier - 2","tier - 3"})),COUNTIF('OG Hospitalisation Details'!G2297:G4639,{"tier - 1","tier - 2","tier - 3"}),0))} -> tier - 1 | J50: {=INDEX({"tier - 1","tier - 2","tier - 3"},MATCH(MAX(COUNTIF('OG Hospitalisation Details'!H2297:H4639,{"tier - 1","tier - 2","tier - 3"})),COUNTIF('OG Hospitalisation Details'!H2297:H4639,{"tier - 1","tier - 2","tier - 3"}),0))} -> tier - 3 | K50: =IF('OG Hospitalisation Details'!I2297="?","Unknown",'OG Hospitalisation Details'!I2297) -> R1013 | L50: =DATEDIF(F50,DATE(2023,6,8),"Y") -> 42
A51: Id49 | B51: =VALUE(SUBSTITUTE(A51,"Id","")) -> 49 | C51: =IF('OG Hospitalisation Details'!B2296="?",ROUND(AVERAGE('OG Hospitalisation Details'!$B$2:$B$2344),0),'OG Hospitalisation Details'!B2296) -> 1966 | D51: =IF('OG Hospitalisation Details'!C2296="?","Sep",'OG Hospitalisation Details'!C2296) -> Jul | E51: 2 | F51: =DATE(C51,MONTH(1&D51),E51) -> 24290 | G51: 0 | H51: 43817.45 | I51: {=INDEX({"tier - 1","tier - 2","tier - 3"},MATCH(MAX(COUNTIF('OG Hospitalisation Details'!G2296:G4638,{"tier - 1","tier - 2","tier - 3"})),COUNTIF('OG Hospitalisation Details'!G2296:G4638,{"tier - 1","tier - 2","tier - 3"}),0))} -> tier - 1 | J51: {=INDEX({"tier - 1","tier - 2","tier - 3"},MATCH(MAX(COUNTIF('OG Hospitalisation Details'!H2296:H4638,{"tier - 1","tier - 2","tier - 3"})),COUNTIF('OG Hospitalisation Details'!H2296:H4638,{"tier - 1","tier - 2","tier - 3"}),0))} -> tier - 3 | K51: =IF('OG Hospitalisation Details'!I2296="?","Unknown",'OG Hospitalisation Details'!I2296) -> R1012 | L51: =DATEDIF(F51,DATE(2023,6,8),"Y") -> 56
A52: Id50 | B52: =VALUE(SUBSTITUTE(A52,"Id","")) -> 50 | C52: =IF('OG Hospitalisation Details'!B2295="?",ROUND(AVERAGE('OG Hospitalisation Details'!$B$2:$B$2344),0),'OG Hospitalisation Details'!B2295) -> 1966 | D52: =IF('OG Hospitalisation Details'!C2295="?","Sep",'OG Hospitalisation Details'!C2295) -> Oct | E52: 25 | F52: =DATE(C52,MONTH(1&D52),E52) -> 24405 | G52: 2 | H52: 43813.87 | I52: {=INDEX({"tier - 1","tier - 2","tier - 3"},MATCH(MAX(COUNTIF('OG Hospitalisation Details'!G2295:G4637,{"tier - 1","tier - 2","tier - 3"})),COUNTIF('OG Hospitalisation Details'!G2295:G4637,{"tier - 1","tier - 2","tier - 3"}),0))} -> tier - 1 | J52: {=INDEX({"tier - 1","tier - 2","tier - 3"},MATCH(MAX(COUNTIF('OG Hospitalisation Details'!H2295:H4637,{"tier - 1","tier - 2","tier - 3"})),COUNTIF('OG Hospitalisation Details'!H2295:H4637,{"tier - 1","tier - 2","tier - 3"}),0))} -> tier - 3 | K52: =IF('OG Hospitalisation Details'!I2295="?","Unknown",'OG Hospitalisation Details'!I2295) -> R1013 | L52: =DATEDIF(F52,DATE(2023,6,8),"Y") -> 56
A53: Id51 | B53: =VALUE(SUBSTITUTE(A53,"Id","")) -> 51 | C53: =IF('OG Hospitalisation Details'!B2294="?",ROUND(AVERAGE('OG Hospitalisation Details'!$B$2:$B$2344),0),'OG Hospitalisation Details'!B2294) -> 1986 | D53: =IF('OG Hospitalisation Details'!C2294="?","Sep",'OG Hospitalisation Details'!C2294) -> Dec | E53: 29 | F53: =DATE(C53,MONTH(1&D53),E53) -> 31775 | G53: 3 | H53: 43753.34 | I53: {=INDEX({"tier - 1","tier - 2","tier - 3"},MATCH(MAX(COUNTIF('OG Hospitalisation Details'!G2294:G4636,{"tier - 1","tier - 2","tier - 3"})),COUNTIF('OG Hospitalisation Details'!G2294:G4636,{"tier - 1","tier - 2","tier - 3"}),0))} -> tier - 2 | J53: {=INDEX({"tier - 1","tier - 2","tier - 3"},MATCH(MAX(COUNTIF('OG Hospitalisation Details'!H2294:H4636,{"tier - 1","tier - 2","tier - 3"})),COUNTIF('OG Hospitalisation Details'!H2294:H4636,{"tier - 1","tier - 2","tier - 3"}),0))} -> tier - 3 | K53: =IF('OG Hospitalisation Details'!I2294="?","Unknown",'OG Hospitalisation Details'!I2294) -> R1015 | L53: =DATEDIF(F53,DATE(2023,6,8),"Y") -> 36
A54: Id52 | B54: =VALUE(SUBSTITUTE(A54,"Id","")) -> 52 | C54: =IF('OG Hospitalisation Details'!B2293="?",ROUND(AVERAGE('OG Hospitalisation Details'!$B$2:$B$2344),0),'OG Hospitalisation Details'!B2293) -> 1965 | D54: =IF('OG Hospitalisation Details'!C2293="?","Sep",'OG Hospitalisation Details'!C2293) -> Aug | E54: 22 | F54: =DATE(C54,MONTH(1&D54),E54) -> 23976 | G54: 0 | H54: 43578.94 | I54: {=INDEX({"tier - 1","tier - 2","tier - 3"},MATCH(MAX(COUNTIF('OG Hospitalisation Details'!G2293:G4635,{"tier - 1","tier - 2","tier - 3"})),COUNTIF('OG Hospitalisation Details'!G2293:G4635,{"tier - 1","tier - 2","tier - 3"}),0))} -> tier - 2 | J54: {=INDEX({"tier - 1","tier - 2","tier - 3"},MATCH(MAX(COUNTIF('OG Hospitalisation Details'!H2293:H4635,{"tier - 1","tier - 2","tier - 3"})),COUNTIF('OG Hospitalisation Details'!H2293:H4635,{"tier - 1","tier - 2","tier - 3"}),0))} -> tier - 3 | K54: =IF('OG Hospitalisation Details'!I2293="?","Unknown",'OG Hospitalisation Details'!I2293) -> R1012 | L54: =DATEDIF(F54,DATE(2023,6,8),"Y") -> 57
A55: Id53 | B55: =VALUE(SUBSTITUTE(A55,"Id","")) -> 53 | C55: =IF('OG Hospitalisation Details'!B2292="?",ROUND(AVERAGE('OG Hospitalisation Details'!$B$2:$B$2344),0),'OG Hospitalisation Details'!B2292) -> 1969 | D55: =IF('OG Hospitalisation Details'!C2292="?","Sep",'OG Hospitalisation Details'!C2292) -> Dec | E55: 3 | F55: =DATE(C55,MONTH(1&D55),E55) -> 25540 | G55: 0 | H55: 43254.42 | I55: {=INDEX({"tier - 1","tier - 2","tier - 3"},MATCH(MAX(COUNTIF('OG Hospitalisation Details'!G2292:G4634,{"tier - 1","tier - 2","tier - 3"})),COUNTIF('OG Hospitalisation Details'!G2292:G4634,{"tier - 1","tier - 2","tier - 3"}),0))} -> tier - 2 | J55: {=INDEX({"tier - 1","tier - 2","tier - 3"},MATCH(MAX(COUNTIF('OG Hospitalisation Details'!H2292:H4634,{"tier - 1","tier - 2","tier - 3"})),COUNTIF('OG Hospitalisation Details'!H2292:H4634,{"tier - 1","tier - 2","tier - 3"}),0))} -> tier - 3 | K55: =IF('OG Hospitalisation Details'!I2292="?","Unknown",'OG Hospitalisation Details'!I2292) -> R1016 | L55: =DATEDIF(F55,DATE(2023,6,8),"Y") -> 53
A56: Id54 | B56: =VALUE(SUBSTITUTE(A56,"Id","")) -> 54 | C56: =IF('OG Hospitalisation Details'!B2291="?",ROUND(AVERAGE('OG Hospitalisation Details'!$B$2:$B$2344),0),'OG Hospitalisation Details'!B2291) -> 1965 | D56: =IF('OG Hospitalisation Details'!C2291="?","Sep",'OG Hospitalisation Details'!C2291) -> Nov | E56: 29 | F56: =DATE(C56,MONTH(1&D56),E56) -> 24075 | G56: 0 | H56: 43073.76 | I56: {=INDEX({"tier - 1","tier - 2","tier - 3"},MATCH(MAX(COUNTIF('OG Hospitalisation Details'!G2291:G4633,{"tier - 1","tier - 2","tier - 3"})),COUNTIF('OG Hospitalisation Details'!G2291:G4633,{"tier - 1","tier - 2","tier - 3"}),0))} -> tier - 2 | J56: {=INDEX({"tier - 1","tier - 2","tier - 3"},MATCH(MAX(COUNTIF('OG Hospitalisation Details'!H2291:H4633,{"tier - 1","tier - 2","tier - 3"})),COUNTIF('OG Hospitalisation Details'!H2291:H4633,{"tier - 1","tier - 2","tier - 3"}),0))} -> tier - 3 | K56: =IF('OG Hospitalisation Details'!I2291="?","Unknown",'OG Hospitalisation Details'!I2291) -> R1011 | L56: =DATEDIF(F56,DATE(2023,6,8),"Y") -> 57
A57: Id55 | B57: =VALUE(SUBSTITUTE(A57,"Id","")) -> 55 | C57: =IF('OG Hospitalisation Details'!B2290="?",ROUND(AVERAGE('OG Hospitalisation Details'!$B$2:$B$2344),0),'OG Hospitalisation Details'!B2290) -> 1978 | D57: =IF('OG Hospitalisation Details'!C2290="?","Sep",'OG Hospitalisation Details'!C2290) -> Nov | E57: 4 | F57: =DATE(C57,MONTH(1&D57),E57) -> 28798 | G57: 0 | H57: 42983.46 | I57: {=INDEX({"tier - 1","tier - 2","tier - 3"},MATCH(MAX(COUNTIF('OG Hospitalisation Details'!G2290:G4632,{"tier - 1","tier - 2","tier - 3"})),COUNTIF('OG Hospitalisation Details'!G2290:G4632,{"tier - 1","tier - 2","tier - 3"}),0))} -> tier - 2 | J57: {=INDEX({"tier - 1","tier - 2","tier - 3"},MATCH(MAX(COUNTIF('OG Hospitalisation Details'!H2290:H4632,{"tier - 1","tier - 2","tier - 3"})),COUNTIF('OG Hospitalisation Details'!H2290:H4632,{"tier - 1","tier - 2","tier - 3"}),0))} -> tier - 3 | K57: =IF('OG Hospitalisation Details'!I2290="?","Unknown",'OG Hospitalisation Details'!I2290) -> R1012 | L57: =DATEDIF(F57,DATE(2023,6,8),"Y") -> 44
A58: Id56 | B58: =VALUE(SUBSTITUTE(A58,"Id","")) -> 56 | C58: =IF('OG Hospitalisation Details'!B2289="?",ROUND(AVERAGE('OG Hospitalisation Details'!$B$2:$B$2344),0),'OG Hospitalisation Details'!B2289) -> 1975 | D58: =IF('OG Hospitalisation Details'!C2289="?","Sep",'OG Hospitalisation Details'!C2289) -> Oct | E58: 23 | F58: =DATE(C58,MONTH(1&D58),E58) -> 27690 | G58: 1 | H58: 42969.85 | I58: {=INDEX({"tier - 1","tier - 2","tier - 3"},MATCH(MAX(COUNTIF('OG Hospitalisation Details'!G2289:G4631,{"tier - 1","tier - 2","tier - 3"})),COUNTIF('OG Hospitalisation Details'!G2289:G4631,{"tier - 1","tier - 2","tier - 3"}),0))} -> tier - 2 | J58: {=INDEX({"tier - 1","tier - 2","tier - 3"},MATCH(MAX(COUNTIF('OG Hospitalisation Details'!H2289:H4631,{"tier - 1","tier - 2","tier - 3"})),COUNTIF('OG Hospitalisation Details'!H2289:H4631,{"tier - 1","tier - 2","tier - 3"}),0))} -> tier - 3 | K58: =IF('OG Hospitalisation Details'!I2289="?","Unknown",'OG Hospitalisation Details'!I2289) -> R1013 | L58: =DATEDIF(F58,DATE(2023,6,8),"Y") -> 47
A59: Id57 | B59: =VALUE(SUBSTITUTE(A59,"Id","")) -> 57 | C59: =IF('OG Hospitalisation Details'!B2288="?",ROUND(AVERAGE('OG Hospitalisation Details'!$B$2:$B$2344),0),'OG Hospitalisation Details'!B2288) -> 1972 | D59: =IF('OG Hospitalisation Details'!C2288="?","Sep",'OG Hospitalisation Details'!C2288) -> Sep | E59: 10 | F59: =DATE(C59,MONTH(1&D59),E59) -> 26552 | G59: 2 | H59: 42856.84 | I59: {=INDEX({"tier - 1","tier - 2","tier - 3"},MATCH(MAX(COUNTIF('OG Hospitalisation Details'!G2288:G4630,{"tier - 1","tier - 2","tier - 3"})),COUNTIF('OG Hospitalisation Details'!G2288:G4630,{"tier - 1","tier - 2","tier - 3"}),0))} -> tier - 2 | J59: {=INDEX({"tier - 1","tier - 2","tier - 3"},MATCH(MAX(COUNTIF('OG Hospitalisation Details'!H2288:H4630,{"tier - 1","tier - 2","tier - 3"})),COUNTIF('OG Hospitalisation Details'!H2288:H4630,{"tier - 1","tier - 2","tier - 3"}),0))} -> tier - 3 | K59: =IF('OG Hospitalisation Details'!I2288="?","Unknown",'OG Hospitalisation Details'!I2288) -> R1011 | L59: =DATEDIF(F59,DATE(2023,6,8),"Y") -> 50
A60: Id58 | B60: =VALUE(SUBSTITUTE(A60,"Id","")) -> 58 | C60: =IF('OG Hospitalisation Details'!B2287="?",ROUND(AVERAGE('OG Hospitalisation Details'!$B$2:$B$2344),0),'OG Hospitalisation Details'!B2287) -> 1965 | D60: =IF('OG Hospitalisation Details'!C2287="?","Sep",'OG Hospitalisation Details'!C2287) -> Oct | E60: 29 | F60: =DATE(C60,MONTH(1&D60),E60) -> 24044 | G60: 0 | H60: 42764.12 | I60: {=INDEX({"tier - 1","tier - 2","tier - 3"},MATCH(MAX(COUNTIF('OG Hospitalisation Details'!G2287:G4629,{"tier - 1","tier - 2","tier - 3"})),COUNTIF('OG Hospitalisation Details'!G2287:G4629,{"tier - 1","tier - 2","tier - 3"}),0))} -> tier - 1 | J60: {=INDEX({"tier - 1","tier - 2","tier - 3"},MATCH(MAX(COUNTIF('OG Hospitalisation Details'!H2287:H4629,{"tier - 1","tier - 2","tier - 3"})),COUNTIF('OG Hospitalisation Details'!H2287:H4629,{"tier - 1","tier - 2","tier - 3"}),0))} -> tier - 3 | K60: =IF('OG Hospitalisation Details'!I2287="?","Unknown",'OG Hospitalisation Details'!I2287) -> R1011 | L60: =DATEDIF(F60,DATE(2023,6,8),"Y") -> 57
A61: Id59 | B61: =VALUE(SUBSTITUTE(A61,"Id","")) -> 59 | C61: =IF('OG Hospitalisation Details'!B2286="?",ROUND(AVERAGE('OG Hospitalisation Details'!$B$2:$B$2344),0),'OG Hospitalisation Details'!B2286) -> 1977 | D61: =IF('OG Hospitalisation Details'!C2286="?","Sep",'OG Hospitalisation Details'!C2286) -> Oct | E61: 21 | F61: =DATE(C61,MONTH(1&D61),E61) -> 28419 | G61: 2 | H61: 42760.5 | I61: {=INDEX({"tier - 1","tier - 2","tier - 3"},MATCH(MAX(COUNTIF('OG Hospitalisation Details'!G2286:G4628,{"tier - 1","tier - 2","tier - 3"})),COUNTIF('OG Hospitalisation Details'!G2286:G4628,{"tier - 1","tier - 2","tier - 3"}),0))} -> tier - 1 | J61: {=INDEX({"tier - 1","tier - 2","tier - 3"},MATCH(MAX(COUNTIF('OG Hospitalisation Details'!H2286:H4628,{"tier - 1","tier - 2","tier - 3"})),COUNTIF('OG Hospitalisation Details'!H2286:H4628,{"tier - 1","tier - 2","tier - 3"}),0))} -> tier - 2 | K61: =IF('OG Hospitalisation Details'!I2286="?","Unknown",'OG Hospitalisation Details'!I2286) -> R1012 | L61: =DATEDIF(F61,DATE(2023,6,8),"Y") -> 45
A62: Id60 | B62: =VALUE(SUBSTITUTE(A62,"Id","")) -> 60 | C62: =IF('OG Hospitalisation Details'!B2285="?",ROUND(AVERAGE('OG Hospitalisation Details'!$B$2:$B$2344),0),'OG Hospitalisation Details'!B2285) -> 1971 | D62: =IF('OG Hospitalisation Details'!C2285="?","Sep",'OG Hospitalisation Details'!C2285) -> Nov | E62: 3 | F62: =DATE(C62,MONTH(1&D62),E62) -> 26240 | G62: 0 | H62: 42644.2 | I62: {=INDEX({"tier - 1","tier - 2","tier - 3"},MATCH(MAX(COUNTIF('OG Hospitalisation Details'!G2285:G4627,{"tier - 1","tier - 2","tier - 3"})),COUNTIF('OG Hospitalisation Details'!G2285:G4627,{"tier - 1","tier - 2","tier - 3"}),0))} -> tier - 1 | J62: {=INDEX({"tier - 1","tier - 2","tier - 3"},MATCH(MAX(COUNTIF('OG Hospitalisation Details'!H2285:H4627,{"tier - 1","tier - 2","tier - 3"})),COUNTIF('OG Hospitalisation Details'!H2285:H4627,{"tier - 1","tier - 2","tier - 3"}),0))} -> tier - 3 | K62: =IF('OG Hospitalisation Details'!I2285="?","Unknown",'OG Hospitalisation Details'!I2285) -> R1011 | L62: =DATEDIF(F62,DATE(2023,6,8),"Y") -> 51
A63: Id61 | B63: =VALUE(SUBSTITUTE(A63,"Id","")) -> 61 | C63: =IF('OG Hospitalisation Details'!B2284="?",ROUND(AVERAGE('OG Hospitalisation Details'!$B$2:$B$2344),0),'OG Hospitalisation Details'!B2284) -> 1979 | D63: =IF('OG Hospitalisation Details'!C2284="?","Sep",'OG Hospitalisation Details'!C2284) -> Dec | E63: 27 | F63: =DATE(C63,MONTH(1&D63),E63) -> 29216 | G63: 2 | H63: 42560.43 | I63: {=INDEX({"tier - 1","tier - 2","tier - 3"},MATCH(MAX(COUNTIF('OG Hospitalisation Details'!G2284:G4626,{"tier - 1","tier - 2","tier - 3"})),COUNTIF('OG Hospitalisation Details'!G2284:G4626,{"tier - 1","tier - 2","tier - 3"}),0))} -> tier - 1 | J63: {=INDEX({"tier - 1","tier - 2","tier - 3"},MATCH(MAX(COUNTIF('OG Hospitalisation Details'!H2284:H4626,{"tier - 1","tier - 2","tier - 3"})),COUNTIF('OG Hospitalisation Details'!H2284:H4626,{"tier - 1","tier - 2","tier - 3"}),0))} -> tier - 3 | K63: =IF('OG Hospitalisation Details'!I2284="?","Unknown",'OG Hospitalisation Details'!I2284) -> R1013 | L63: =DATEDIF(F63,DATE(2023,6,8),"Y") -> 43
A64: Id62 | B64: =VALUE(SUBSTITUTE(A64,"Id","")) -> 62 | C64: =IF('OG Hospitalisation Details'!B2283="?",ROUND(AVERAGE('OG Hospitalisation Details'!$B$2:$B$2344),0),'OG Hospitalisation Details'!B2283) -> 1967 | D64: =IF('OG Hospitalisation Details'!C2283="?","Sep",'OG Hospitalisation Details'!C2283) -> Jun | E64: 27 | F64: =DATE(C64,MONTH(1&D64),E64) -> 24650 | G64: 0 | H64: 42538.72 | I64: {=INDEX({"tier - 1","tier - 2","tier - 3"},MATCH(MAX(COUNTIF('OG Hospitalisation Details'!G2283:G4625,{"tier - 1","tier - 2","tier - 3"})),COUNTIF('OG Hospitalisation Details'!G2283:G4625,{"tier - 1","tier - 2","tier - 3"}),0))} -> tier - 1 | J64: {=INDEX({"tier - 1","tier - 2","tier - 3"},MATCH(MAX(COUNTIF('OG Hospitalisation Details'!H2283:H4625,{"tier - 1","tier - 2","tier - 3"})),COUNTIF('OG Hospitalisation Details'!H2283:H4625,{"tier - 1","tier - 2","tier - 3"}),0))} -> tier - 3 | K64: =IF('OG Hospitalisation Details'!I2283="?","Unknown",'OG Hospitalisation Details'!I2283) -> R1011 | L64: =DATEDIF(F64,DATE(2023,6,8),"Y") -> 55
A65: Id63 | B65: =VALUE(SUBSTITUTE(A65,"Id","")) -> 63 | C65: =IF('OG Hospitalisation Details'!B2282="?",ROUND(AVERAGE('OG Hospitalisation Details'!$B$2:$B$2344),0),'OG Hospitalisation Details'!B2282) -> 1968 | D65: =IF('OG Hospitalisation Details'!C2282="?","Sep",'OG Hospitalisation Details'!C2282) -> Aug | E65: 3 | F65: =DATE(C65,MONTH(1&D65),E65) -> 25053 | G65: 0 | H65: 42478.6 | I65: {=INDEX({"tier - 1","tier - 2","tier - 3"},MATCH(MAX(COUNTIF('OG Hospitalisation Details'!G2282:G4624,{"tier - 1","tier - 2","tier - 3"})),COUNTIF('OG Hospitalisation Details'!G2282:G4624,{"tier - 1","tier - 2","tier - 3"}),0))} -> tier - 1 | J65: {=INDEX({"tier - 1","tier - 2","tier - 3"},MATCH(MAX(COUNTIF('OG Hospitalisation Details'!H2282:H4624,{"tier - 1","tier - 2","tier - 3"})),COUNTIF('OG Hospitalisation Details'!H2282:H4624,{"tier - 1","tier - 2","tier - 3"}),0))} -> tier - 3 | K65: =IF('OG Hospitalisation Details'!I2282="?","Unknown",'OG Hospitalisation Details'!I2282) -> R1011 | L65: =DATEDIF(F65,DATE(2023,6,8),"Y") -> 54
A66: Id64 | B66: =VALUE(SUBSTITUTE(A66,"Id","")) -> 64 | C66: =IF('OG Hospitalisation Details'!B2281="?",ROUND(AVERAGE('OG Hospitalisation Details'!$B$2:$B$2344),0),'OG Hospitalisation Details'!B2281) -> 1967 | D66: =IF('OG Hospitalisation Details'!C2281="?","Sep",'OG Hospitalisation Details'!C2281) -> Jun | E66: 28 | F66: =DATE(C66,MONTH(1&D66),E66) -> 24651 | G66: 0 | H66: 42303.69 | I66: {=INDEX({"tier - 1","tier - 2","tier - 3"},MATCH(MAX(COUNTIF('OG Hospitalisation Details'!G2281:G4623,{"tier - 1","tier - 2","tier - 3"})),COUNTIF('OG Hospitalisation Details'!G2281:G4623,{"tier - 1","tier - 2","tier - 3"}),0))} -> tier - 1 | J66: {=INDEX({"tier - 1","tier - 2","tier - 3"},MATCH(MAX(COUNTIF('OG Hospitalisation Details'!H2281:H4623,{"tier - 1","tier - 2","tier - 3"})),COUNTIF('OG Hospitalisation Details'!H2281:H4623,{"tier - 1","tier - 2","tier - 3"}),0))} -> tier - 3 | K66: =IF('OG Hospitalisation Details'!I2281="?","Unknown",'OG Hospitalisation Details'!I2281) -> R1016 | L66: =DATEDIF(F66,DATE(2023,6,8),"Y") -> 55
A67: Id65 | B67: =VALUE(SUBSTITUTE(A67,"Id","")) -> 65 | C67: =IF('OG Hospitalisation Details'!B2280="?",ROUND(AVERAGE('OG Hospitalisation Details'!$B$2:$B$2344),0),'OG Hospitalisation Details'!B2280) -> 1975 | D67: =IF('OG Hospitalisation Details'!C2280="?","Sep",'OG Hospitalisation Details'!C2280) -> Aug | E67: 15 | F67: =DATE(C67,MONTH(1&D67),E67) -> 27621 | G67: 1 | H67: 42211.14 | I67: {=INDEX({"tier - 1","tier - 2","tier - 3"},MATCH(MAX(COUNTIF('OG Hospitalisation Details'!G2280:G4622,{"tier - 1","tier - 2","tier - 3"})),COUNTIF('OG Hospitalisation Details'!G2280:G4622,{"tier - 1","tier - 2","tier - 3"}),0))} -> tier - 1 | J67: {=INDEX({"tier - 1","tier - 2","tier - 3"},MATCH(MAX(COUNTIF('OG Hospitalisation Details'!H2280:H4622,{"tier - 1","tier - 2","tier - 3"})),COUNTIF('OG Hospitalisation Details'!H2280:H4622,{"tier - 1","tier - 2","tier - 3"}),0))} -> tier - 3 | K67: =IF('OG Hospitalisation Details'!I2280="?","Unknown",'OG Hospitalisation Details'!I2280) -> R1013 | L67: =DATEDIF(F67,DATE(2023,6,8),"Y") -> 47
A68: Id66 | B68: =VALUE(SUBSTITUTE(A68,"Id","")) -> 66 | C68: =IF('OG Hospitalisation Details'!B2279="?",ROUND(AVERAGE('OG Hospitalisation Details'!$B$2:$B$2344),0),'OG Hospitalisation Details'!B2279) -> 1973 | D68: =IF('OG Hospitalisation Details'!C2279="?","Sep",'OG Hospitalisation Details'!C2279) -> Sep | E68: 18 | F68: =DATE(C68,MONTH(1&D68),E68) -> 26925 | G68: 0 | H68: 42188.15 | I68: {=INDEX({"tier - 1","tier - 2","tier - 3"},MATCH(MAX(COUNTIF('OG Hospitalisation Details'!G2279:G4621,{"tier - 1","tier - 2","tier - 3"})),COUNTIF('OG Hospitalisation Details'!G2279:G4621,{"tier - 1","tier - 2","tier - 3"}),0))} -> tier - 1 | J68: {=INDEX({"tier - 1","tier - 2","tier - 3"},MATCH(MAX(COUNTIF('OG Hospitalisation Details'!H2279:H4621,{"tier - 1","tier - 2","tier - 3"})),COUNTIF('OG Hospitalisation Details'!H2279:H4621,{"tier - 1","tier - 2","tier - 3"}),0))} -> tier - 3 | K68: =IF('OG Hospitalisation Details'!I2279="?","Unknown",'OG Hospitalisation Details'!I2279) -> R1011 | L68: =DATEDIF(F68,DATE(2023,6,8),"Y") -> 49
A69: Id67 | B69: =VALUE(SUBSTITUTE(A69,"Id","")) -> 67 | C69: =IF('OG Hospitalisation Details'!B2278="?",ROUND(AVERAGE('OG Hospitalisation Details'!$B$2:$B$2344),0),'OG Hospitalisation Details'!B2278) -> 1979 | D69: =IF('OG Hospitalisation Details'!C2278="?","Sep",'OG Hospitalisation Details'!C2278) -> Jul | E69: 3 | F69: =DATE(C69,MONTH(1&D69),E69) -> 29039 | G69: 3 | H69: 42124.52 | I69: {=INDEX({"tier - 1","tier - 2","tier - 3"},MATCH(MAX(COUNTIF('OG Hospitalisation Details'!G2278:G4620,{"tier - 1","tier - 2","tier - 3"})),COUNTIF('OG Hospitalisation Details'!G2278:G4620,{"tier - 1","tier - 2","tier - 3"}),0))} -> tier - 1 | J69: {=INDEX({"tier - 1","tier - 2","tier - 3"},MATCH(MAX(COUNTIF('OG Hospitalisation Details'!H2278:H4620,{"tier - 1","tier - 2","tier - 3"})),COUNTIF('OG Hospitalisation Details'!H2278:H4620,{"tier - 1","tier - 2","tier - 3"}),0))} -> tier - 3 | K69: =IF('OG Hospitalisation Details'!I2278="?","Unknown",'OG Hospitalisation Details'!I2278) -> R1013 | L69: =DATEDIF(F69,DATE(2023,6,8),"Y") -> 43
A70: Id68 | B70: =VALUE(SUBSTITUTE(A70,"Id","")) -> 68 | C70: =IF('OG Hospitalisation Details'!B2277="?",ROUND(AVERAGE('OG Hospitalisation Details'!$B$2:$B$2344),0),'OG Hospitalisation Details'!B2277) -> 1997 | D70: =IF('OG Hospitalisation Details'!C2277="?","Sep",'OG Hospitalisation Details'!C2277) -> Dec | E70: 9 | F70: =DATE(C70,MONTH(1&D70),E70) -> 35773 | G70: 2 | H70: 42112.24 | I70: {=INDEX({"tier - 1","tier - 2","tier - 3"},MATCH(MAX(COUNTIF('OG Hospitalisation Details'!G2277:G4619,{"tier - 1","tier - 2","tier - 3"})),COUNTIF('OG Hospitalisation Details'!G2277:G4619,{"tier - 1","tier - 2","tier - 3"}),0))} -> tier - 1 | J70: {=INDEX({"tier - 1","tier - 2","tier - 3"},MATCH(MAX(COUNTIF('OG Hospitalisation Details'!H2277:H4619,{"tier - 1","tier - 2","tier - 3"})),COUNTIF('OG Hospitalisation Details'!H2277:H4619,{"tier - 1","tier - 2","tier - 3"}),0))} -> tier - 3 | K70: =IF('OG Hospitalisation Details'!I2277="?","Unknown",'OG Hospitalisation Details'!I2277) -> R1013 | L70: =DATEDIF(F70,DATE(2023,6,8),"Y") -> 25
A71: Id69 | B71: =VALUE(SUBSTITUTE(A71,"Id","")) -> 69 | C71: =IF('OG Hospitalisation Details'!B2276="?",ROUND(AVERAGE('OG Hospitalisation Details'!$B$2:$B$2344),0),'OG Hospitalisation Details'!B2276) -> 1976 | D71: =IF('OG Hospitalisation Details'!C2276="?","Sep",'OG Hospitalisation Details'!C2276) -> Nov | E71: 28 | F71: =DATE(C71,MONTH(1&D71),E71) -> 28092 | G71: 0 | H71: 42111.66 | I71: {=INDEX({"tier - 1","tier - 2","tier - 3"},MATCH(MAX(COUNTIF('OG Hospitalisation Details'!G2276:G4618,{"tier - 1","tier - 2","tier - 3"})),COUNTIF('OG Hospitalisation Details'!G2276:G4618,{"tier - 1","tier - 2","tier - 3"}),0))} -> tier - 1 | J71: {=INDEX({"tier - 1","tier - 2","tier - 3"},MATCH(MAX(COUNTIF('OG Hospitalisation Details'!H2276:H4618,{"tier - 1","tier - 2","tier - 3"})),COUNTIF('OG Hospitalisation Details'!H2276:H4618,{"tier - 1","tier - 2","tier - 3"}),0))} -> tier - 3 | K71: =IF('OG Hospitalisation Details'!I2276="?","Unknown",'OG Hospitalisation Details'!I2276) -> R1024 | L71: =DATEDIF(F71,DATE(2023,6,8),"Y") -> 46
A72: Id70 | B72: =VALUE(SUBSTITUTE(A72,"Id","")) -> 70 | C72: =IF('OG Hospitalisation Details'!B2275="?",ROUND(AVERAGE('OG Hospitalisation Details'!$B$2:$B$2344),0),'OG Hospitalisation Details'!B2275) -> 1968 | D72: =IF('OG Hospitalisation Details'!C2275="?","Sep",'OG Hospitalisation Details'!C2275) -> Dec | E72: 19 | F72: =DATE(C72,MONTH(1&D72),E72) -> 25191 | G72: 1 | H72: 41999.52 | I72: {=INDEX({"tier - 1","tier - 2","tier - 3"},MATCH(MAX(COUNTIF('OG Hospitalisation Details'!G2275:G4617,{"tier - 1","tier - 2","tier - 3"})),COUNTIF('OG Hospitalisation Details'!G2275:G4617,{"tier - 1","tier - 2","tier - 3"}),0))} -> tier - 1 | J72: {=INDEX({"tier - 1","tier - 2","tier - 3"},MATCH(MAX(COUNTIF('OG Hospitalisation Details'!H2275:H4617,{"tier - 1","tier - 2","tier - 3"})),COUNTIF('OG Hospitalisation Details'!H2275:H4617,{"tier - 1","tier - 2","tier - 3"}),0))} -> tier - 3 | K72: =IF('OG Hospitalisation Details'!I2275="?","Unknown",'OG Hospitalisation Details'!I2275) -> R1013 | L72: =DATEDIF(F72,DATE(2023,6,8),"Y") -> 54
A73: Id71 | B73: =VALUE(SUBSTITUTE(A73,"Id","")) -> 71 | C73: =IF('OG Hospitalisation Details'!B2274="?",ROUND(AVERAGE('OG Hospitalisation Details'!$B$2:$B$2344),0),'OG Hospitalisation Details'!B2274) -> 1984 | D73: =IF('OG Hospitalisation Details'!C2274="?","Sep",'OG Hospitalisation Details'!C2274) -> Nov | E73: 10 | F73: =DATE(C73,MONTH(1&D73),E73) -> 30996 | G73: 3 | H73: 41949.24 | I73: {=INDEX({"tier - 1","tier - 2","tier - 3"},MATCH(MAX(COUNTIF('OG Hospitalisation Details'!G2274:G4616,{"tier - 1","tier - 2","tier - 3"})),COUNTIF('OG Hospitalisation Details'!G2274:G4616,{"tier - 1","tier - 2","tier - 3"}),0))} -> tier - 1 | J73: {=INDEX({"tier - 1","tier - 2","tier - 3"},MATCH(MAX(COUNTIF('OG Hospitalisation Details'!H2274:H4616,{"tier - 1","tier - 2","tier - 3"})),COUNTIF('OG Hospitalisation Details'!H2274:H4616,{"tier - 1","tier - 2","tier - 3"}),0))} -> tier - 3 | K73: =IF('OG Hospitalisation Details'!I2274="?","Unknown",'OG Hospitalisation Details'!I2274) -> R1013 | L73: =DATEDIF(F73,DATE(2023,6,8),"Y") -> 38
A74: Id72 | B74: =VALUE(SUBSTITUTE(A74,"Id","")) -> 72 | C74: =IF('OG Hospitalisation Details'!B2273="?",ROUND(AVERAGE('OG Hospitalisation Details'!$B$2:$B$2344),0),'OG Hospitalisation Details'!B2273) -> 1972 | D74: =IF('OG Hospitalisation Details'!C2273="?","Sep",'OG Hospitalisation Details'!C2273) -> Jun | E74: 8 | F74: =DATE(C74,MONTH(1&D74),E74) -> 26458 | G74: 1 | H74: 41919.1 | I74: {=INDEX({"tier - 1","tier - 2","tier - 3"},MATCH(MAX(COUNTIF('OG Hospitalisation Details'!G2273:G4615,{"tier - 1","tier - 2","tier - 3"})),COUNTIF('OG Hospitalisation Details'!G2273:G4615,{"tier - 1","tier - 2","tier - 3"}),0))} -> tier - 1 | J74: {=INDEX({"tier - 1","tier - 2","tier - 3"},MATCH(MAX(COUNTIF('OG Hospitalisation Details'!H2273:H4615,{"tier - 1","tier - 2","tier - 3"})),COUNTIF('OG Hospitalisation Details'!H2273:H4615,{"tier - 1","tier - 2","tier - 3"}),0))} -> tier - 3 | K74: =IF('OG Hospitalisation Details'!I2273="?","Unknown",'OG Hospitalisation Details'!I2273) -> R1016 | L74: =DATEDIF(F74,DATE(2023,6,8),"Y") -> 51
A75: Id73 | B75: =VALUE(SUBSTITUTE(A75,"Id","")) -> 73 | C75: =IF('OG Hospitalisation Details'!B2272="?",ROUND(AVERAGE('OG Hospitalisation Details'!$B$2:$B$2344),0),'OG Hospitalisation Details'!B2272) -> 1966 | D75: =IF('OG Hospitalisation Details'!C2272="?","Sep",'OG Hospitalisation Details'!C2272) -> Sep | E75: 21 | F75: =DATE(C75,MONTH(1&D75),E75) -> 24371 | G75: 0 | H75: 41886.54 | I75: {=INDEX({"tier - 1","tier - 2","tier - 3"},MATCH(MAX(COUNTIF('OG Hospitalisation Details'!G2272:G4614,{"tier - 1","tier - 2","tier - 3"})),COUNTIF('OG Hospitalisation Details'!G2272:G4614,{"tier - 1","tier - 2","tier - 3"}),0))} -> tier - 1 | J75: {=INDEX({"tier - 1","tier - 2","tier - 3"},MATCH(MAX(COUNTIF('OG Hospitalisation Details'!H2272:H4614,{"tier - 1","tier - 2","tier - 3"})),COUNTIF('OG Hospitalisation Details'!H2272:H4614,{"tier - 1","tier - 2","tier - 3"}),0))} -> tier - 3 | K75: =IF('OG Hospitalisation Details'!I2272="?","Unknown",'OG Hospitalisation Details'!I2272) -> R1011 | L75: =DATEDIF(F75,DATE(2023,6,8),"Y") -> 56
A76: Id74 | B76: =VALUE(SUBSTITUTE(A76,"Id","")) -> 74 | C76: =IF('OG Hospitalisation Details'!B2271="?",ROUND(AVERAGE('OG Hospitalisation Details'!$B$2:$B$2344),0),'OG Hospitalisation Details'!B2271) -> 1962 | D76: =IF('OG Hospitalisation Details'!C2271="?","Sep",'OG Hospitalisation Details'!C2271) -> Sep | E76: 22 | F76: =DATE(C76,MONTH(1&D76),E76) -> 22911 | G76: 0 | H76: 41794.63 | I76: {=INDEX({"tier - 1","tier - 2","tier - 3"},MATCH(MAX(COUNTIF('OG Hospitalisation Details'!G2271:G4613,{"tier - 1","tier - 2","tier - 3"})),COUNTIF('OG Hospitalisation Details'!G2271:G4613,{"tier - 1","tier - 2","tier - 3"}),0))} -> tier - 1 | J76: {=INDEX({"tier - 1","tier - 2","tier - 3"},MATCH(MAX(COUNTIF('OG Hospitalisation Details'!H2271:H4613,{"tier - 1","tier - 2","tier - 3"})),COUNTIF('OG Hospitalisation Details'!H2271:H4613,{"tier - 1","tier - 2","tier - 3"}),0))} -> tier - 3 | K76: =IF('OG Hospitalisation Details'!I2271="?","Unknown",'OG Hospitalisation Details'!I2271) -> R1011 | L76: =DATEDIF(F76,DATE(2023,6,8),"Y") -> 60
A77: Id75 | B77: =VALUE(SUBSTITUTE(A77,"Id","")) -> 75 | C77: =IF('OG Hospitalisation Details'!B2270="?",ROUND(AVERAGE('OG Hospitalisation Details'!$B$2:$B$2344),0),'OG Hospitalisation Details'!B2270) -> 1975 | D77: =IF('OG Hospitalisation Details'!C2270="?","Sep",'OG Hospitalisation Details'!C2270) -> Sep | E77: 29 | F77: =DATE(C77,MONTH(1&D77),E77) -> 27666 | G77: 1 | H77: 41681.86 | I77: {=INDEX({"tier - 1","tier - 2","tier - 3"},MATCH(MAX(COUNTIF('OG Hospitalisation Details'!G2270:G4612,{"tier - 1","tier - 2","tier - 3"})),COUNTIF('OG Hospitalisation Details'!G2270:G4612,{"tier - 1","tier - 2","tier - 3"}),0))} -> tier - 1 | J77: {=INDEX({"tier - 1","tier - 2","tier - 3"},MATCH(MAX(COUNTIF('OG Hospitalisation Details'!H2270:H4612,{"tier - 1","tier - 2","tier - 3"})),COUNTIF('OG Hospitalisation Details'!H2270:H4612,{"tier - 1","tier - 2","tier - 3"}),0))} -> tier - 3 | K77: =IF('OG Hospitalisation Details'!I2270="?","Unknown",'OG Hospitalisation Details'!I2270) -> R1011 | L77: =DATEDIF(F77,DATE(2023,6,8),"Y") -> 47
A78: Id76 | B78: =VALUE(SUBSTITUTE(A78,"Id","")) -> 76 | C78: =IF('OG Hospitalisation Details'!B2269="?",ROUND(AVERAGE('OG Hospitalisation Details'!$B$2:$B$2344),0),'OG Hospitalisation Details'!B2269) -> 1975 | D78: =IF('OG Hospitalisation Details'!C2269="?","Sep",'OG Hospitalisation Details'!C2269) -> Nov | E78: 14 | F78: =DATE(C78,MONTH(1&D78),E78) -> 27712 | G78: 0 | H78: 41676.08 | I78: {=INDEX({"tier - 1","tier - 2","tier - 3"},MATCH(MAX(COUNTIF('OG Hospitalisation Details'!G2269:G4611,{"tier - 1","tier - 2","tier - 3"})),COUNTIF('OG Hospitalisation Details'!G2269:G4611,{"tier - 1","tier - 2","tier - 3"}),0))} -> tier - 1 | J78: {=INDEX({"tier - 1","tier - 2","tier - 3"},MATCH(MAX(COUNTIF('OG Hospitalisation Details'!H2269:H4611,{"tier - 1","tier - 2","tier - 3"})),COUNTIF('OG Hospitalisation Details'!H2269:H4611,{"tier - 1","tier - 2","tier - 3"}),0))} -> tier - 3 | K78: =IF('OG Hospitalisation Details'!I2269="?","Unknown",'OG Hospitalisation Details'!I2269) -> R1013 | L78: =DATEDIF(F78,DATE(2023,6,8),"Y") -> 47
A79: Id77 | B79: =VALUE(SUBSTITUTE(A79,"Id","")) -> 77 | C79: =IF('OG Hospitalisation Details'!B2268="?",ROUND(AVERAGE('OG Hospitalisation Details'!$B$2:$B$2344),0),'OG Hospitalisation Details'!B2268) -> 1976 | D79: =IF('OG Hospitalisation Details'!C2268="?","Sep",'OG Hospitalisation Details'!C2268) -> Oct | E79: 29 | F79: =DATE(C79,MONTH(1&D79),E79) -> 28062 | G79: 1 | H79: 41661.6 | I79: {=INDEX({"tier - 1","tier - 2","tier - 3"},MATCH(MAX(COUNTIF('OG Hospitalisation Details'!G2268:G4610,{"tier - 1","tier - 2","tier - 3"})),COUNTIF('OG Hospitalisation Details'!G2268:G4610,{"tier - 1","tier - 2","tier - 3"}),0))} -> tier - 1 | J79: {=INDEX({"tier - 1","tier - 2","tier - 3"},MATCH(MAX(COUNTIF('OG Hospitalisation Details'!H2268:H4610,{"tier - 1","tier - 2","tier - 3"})),COUNTIF('OG Hospitalisation Details'!H2268:H4610,{"tier - 1","tier - 2","tier - 3"}),0))} -> tier - 3 | K79: =IF('OG Hospitalisation Details'!I2268="?","Unknown",'OG Hospitalisation Details'!I2268) -> R1011 | L79: =DATEDIF(F79,DATE(2023,6,8),"Y") -> 46
A80: Id78 | B80: =VALUE(SUBSTITUTE(A80,"Id","")) -> 78 | C80: =IF('OG Hospitalisation Details'!B2267="?",ROUND(AVERAGE('OG Hospitalisation Details'!$B$2:$B$2344),0),'OG Hospitalisation Details'!B2267) -> 1974 | D80: =IF('OG Hospitalisation Details'!C2267="?","Sep",'OG Hospitalisation Details'!C2267) -> Nov | E80: 24 | F80: =DATE(C80,MONTH(1&D80),E80) -> 27357 | G80: 0 | H80: 41636.2 | I80: {=INDEX({"tier - 1","tier - 2","tier - 3"},MATCH(MAX(COUNTIF('OG Hospitalisation Details'!G2267:G4609,{"tier - 1","tier - 2","tier - 3"})),COUNTIF('OG Hospitalisation Details'!G2267:G4609,{"tier - 1","tier - 2","tier - 3"}),0))} -> tier - 1 | J80: {=INDEX({"tier - 1","tier - 2","tier - 3"},MATCH(MAX(COUNTIF('OG Hospitalisation Details'!H2267:H4609,{"tier - 1","tier - 2","tier - 3"})),COUNTIF('OG Hospitalisation Details'!H2267:H4609,{"tier - 1","tier - 2","tier - 3"}),0))} -> tier - 3 | K80: =IF('OG Hospitalisation Details'!I2267="?","Unknown",'OG Hospitalisation Details'!I2267) -> R1011 | L80: =DATEDIF(F80,DATE(2023,6,8),"Y") -> 48
A81: Id79 | B81: =VALUE(SUBSTITUTE(A81,"Id","")) -> 79 | C81: =IF('OG Hospitalisation Details'!B2266="?",ROUND(AVERAGE('OG Hospitalisation Details'!$B$2:$B$2344),0),'OG Hospitalisation Details'!B2266) -> 1967 | D81: =IF('OG Hospitalisation Details'!C2266="?","Sep",'OG Hospitalisation Details'!C2266) -> Dec | E81: 22 | F81: =DATE(C81,MONTH(1&D81),E81) -> 24828 | G81: 0 | H81: 41505.15 | I81: {=INDEX({"tier - 1","tier - 2","tier - 3"},MATCH(MAX(COUNTIF('OG Hospitalisation Details'!G2266:G4608,{"tier - 1","tier - 2","tier - 3"})),COUNTIF('OG Hospitalisation Details'!G2266:G4608,{"tier - 1","tier - 2","tier - 3"}),0))} -> tier - 1 | J81: {=INDEX({"tier - 1","tier - 2","tier - 3"},MATCH(MAX(COUNTIF('OG Hospitalisation Details'!H2266:H4608,{"tier - 1","tier - 2","tier - 3"})),COUNTIF('OG Hospitalisation Details'!H2266:H4608,{"tier - 1","tier - 2","tier - 3"}),0))} -> tier - 3 | K81: =IF('OG Hospitalisation Details'!I2266="?","Unknown",'OG Hospitalisation Details'!I2266) -> R1011 | L81: =DATEDIF(F81,DATE(2023,6,8),"Y") -> 55
A82: Id80 | B82: =VALUE(SUBSTITUTE(A82,"Id","")) -> 80 | C82: =IF('OG Hospitalisation Details'!B2265="?",ROUND(AVERAGE('OG Hospitalisation Details'!$B$2:$B$2344),0),'OG Hospitalisation Details'!B2265) -> 1971 | D82: =IF('OG Hospitalisation Details'!C2265="?","Sep",'OG Hospitalisation Details'!C2265) -> Oct | E82: 16 | F82: =DATE(C82,MONTH(1&D82),E82) -> 26222 | G82: 0 | H82: 41351.88 | I82: {=INDEX({"tier - 1","tier - 2","tier - 3"},MATCH(MAX(COUNTIF('OG Hospitalisation Details'!G2265:G4607,{"tier - 1","tier - 2","tier - 3"})),COUNTIF('OG Hospitalisation Details'!G2265:G4607,{"tier - 1","tier - 2","tier - 3"}),0))} -> tier - 1 | J82: {=INDEX({"tier - 1","tier - 2","tier - 3"},MATCH(MAX(COUNTIF('OG Hospitalisation Details'!H2265:H4607,{"tier - 1","tier - 2","tier - 3"})),COUNTIF('OG Hospitalisation Details'!H2265:H4607,{"tier - 1","tier - 2","tier - 3"}),0))} -> tier - 3 | K82: =IF('OG Hospitalisation Details'!I2265="?","Unknown",'OG Hospitalisation Details'!I2265) -> R1011 | L82: =DATEDIF(F82,DATE(2023,6,8),"Y") -> 51
A83: Id81 | B83: =VALUE(SUBSTITUTE(A83,"Id","")) -> 81 | C83: =IF('OG Hospitalisation Details'!B2264="?",ROUND(AVERAGE('OG Hospitalisation Details'!$B$2:$B$2344),0),'OG Hospitalisation Details'!B2264) -> 1964 | D83: =IF('OG Hospitalisation Details'!C2264="?","Sep",'OG Hospitalisation Details'!C2264) -> Oct | E83: 7 | F83: =DATE(C83,MONTH(1&D83),E83) -> 23657 | G83: 0 | H83: 41331.79 | I83: {=INDEX({"tier - 1","tier - 2","tier - 3"},MATCH(MAX(COUNTIF('OG Hospitalisation Details'!G2264:G4606,{"tier - 1","tier - 2","tier - 3"})),COUNTIF('OG Hospitalisation Details'!G2264:G4606,{"tier - 1","tier - 2","tier - 3"}),0))} -> tier - 1 | J83: {=INDEX({"tier - 1","tier - 2","tier - 3"},MATCH(MAX(COUNTIF('OG Hospitalisation Details'!H2264:H4606,{"tier - 1","tier - 2","tier - 3"})),COUNTIF('OG Hospitalisation Details'!H2264:H4606,{"tier - 1","tier - 2","tier - 3"}),0))} -> tier - 3 | K83: =IF('OG Hospitalisation Details'!I2264="?","Unknown",'OG Hospitalisation Details'!I2264) -> R1011 | L83: =DATEDIF(F83,DATE(2023,6,8),"Y") -> 58
A84: Id82 | B84: =VALUE(SUBSTITUTE(A84,"Id","")) -> 82 | C84: =IF('OG Hospitalisation Details'!B2263="?",ROUND(AVERAGE('OG Hospitalisation Details'!$B$2:$B$2344),0),'OG Hospitalisation Details'!B2263) -> 1977 | D84: =IF('OG Hospitalisation Details'!C2263="?","Sep",'OG Hospitalisation Details'!C2263) -> Aug | E84: 27 | F84: =DATE(C84,MONTH(1&D84),E84) -> 28364 | G84: 2 | H84: 41271.5 | I84: {=INDEX({"tier - 1","tier - 2","tier - 3"},MATCH(MAX(COUNTIF('OG Hospitalisation Details'!G2263:G4605,{"tier - 1","tier - 2","tier - 3"})),COUNTIF('OG Hospitalisation Details'!G2263:G4605,{"tier - 1","tier - 2","tier - 3"}),0))} -> tier - 1 | J84: {=INDEX({"tier - 1","tier - 2","tier - 3"},MATCH(MAX(COUNTIF('OG Hospitalisation Details'!H2263:H4605,{"tier - 1","tier - 2","tier - 3"})),COUNTIF('OG Hospitalisation Details'!H2263:H4605,{"tier - 1","tier - 2","tier - 3"}),0))} -> tier - 3 | K84: =IF('OG Hospitalisation Details'!I2263="?","Unknown",'OG Hospitalisation Details'!I2263) -> R1011 | L84: =DATEDIF(F84,DATE(2023,6,8),"Y") -> 45
A85: Id83 | B85: =VALUE(SUBSTITUTE(A85,"Id","")) -> 83 | C85: =IF('OG Hospitalisation Details'!B2262="?",ROUND(AVERAGE('OG Hospitalisation Details'!$B$2:$B$2344),0),'OG Hospitalisation Details'!B2262) -> 1964 | D85: =IF('OG Hospitalisation Details'!C2262="?","Sep",'OG Hospitalisation Details'!C2262) -> Jun | E85: 6 | F85: =DATE(C85,MONTH(1&D85),E85) -> 23534 | G85: 0 | H85: 41250.39 | I85: {=INDEX({"tier - 1","tier - 2","tier - 3"},MATCH(MAX(COUNTIF('OG Hospitalisation Details'!G2262:G4604,{"tier - 1","tier - 2","tier - 3"})),COUNTIF('OG Hospitalisation Details'!G2262:G4604,{"tier - 1","tier - 2","tier - 3"}),0))} -> tier - 1 | J85: {=INDEX({"tier - 1","tier - 2","tier - 3"},MATCH(MAX(COUNTIF('OG Hospitalisation Details'!H2262:H4604,{"tier - 1","tier - 2","tier - 3"})),COUNTIF('OG Hospitalisation Details'!H2262:H4604,{"tier - 1","tier - 2","tier - 3"}),0))} -> tier - 3 | K85: =IF('OG Hospitalisation Details'!I2262="?","Unknown",'OG Hospitalisation Details'!I2262) -> R1011 | L85: =DATEDIF(F85,DATE(2023,6,8),"Y") -> 59
A86: Id84 | B86: =VALUE(SUBSTITUTE(A86,"Id","")) -> 84 | C86: =IF('OG Hospitalisation Details'!B2261="?",ROUND(AVERAGE('OG Hospitalisation Details'!$B$2:$B$2344),0),'OG Hospitalisation Details'!B2261) -> 1969 | D86: =IF('OG Hospitalisation Details'!C2261="?","Sep",'OG Hospitalisation Details'!C2261) -> Aug | E86: 8 | F86: =DATE(C86,MONTH(1&D86),E86) -> 25423 | G86: 0 | H86: 41191.57 | I86: {=INDEX({"tier - 1","tier - 2","tier - 3"},MATCH(MAX(COUNTIF('OG Hospitalisation Details'!G2261:G4603,{"tier - 1","tier - 2","tier - 3"})),COUNTIF('OG Hospitalisation Details'!G2261:G4603,{"tier - 1","tier - 2","tier - 3"}),0))} -> tier - 1 | J86: {=INDEX({"tier - 1","tier - 2","tier - 3"},MATCH(MAX(COUNTIF('OG Hospitalisation Details'!H2261:H4603,{"tier - 1","tier - 2","tier - 3"})),COUNTIF('OG Hospitalisation Details'!H2261:H4603,{"tier - 1","tier - 2","tier - 3"}),0))} -> tier - 3 | K86: =IF('OG Hospitalisation Details'!I2261="?","Unknown",'OG Hospitalisation Details'!I2261) -> R1011 | L86: =DATEDIF(F86,DATE(2023,6,8),"Y") -> 53
A87: Id85 | B87: =VALUE(SUBSTITUTE(A87,"Id","")) -> 85 | C87: =IF('OG Hospitalisation Details'!B2260="?",ROUND(AVERAGE('OG Hospitalisation Details'!$B$2:$B$2344),0),'OG Hospitalisation Details'!B2260) -> 1972 | D87: =IF('OG Hospitalisation Details'!C2260="?","Sep",'OG Hospitalisation Details'!C2260) -> Sep | E87: 6 | F87: =DATE(C87,MONTH(1&D87),E87) -> 26548 | G87: 0 | H87: 41097.16 | I87: {=INDEX({"tier - 1","tier - 2","tier - 3"},MATCH(MAX(COUNTIF('OG Hospitalisation Details'!G2260:G4602,{"tier - 1","tier - 2","tier - 3"})),COUNTIF('OG Hospitalisation Details'!G2260:G4602,{"tier - 1","tier - 2","tier - 3"}),0))} -> tier - 1 | J87: {=INDEX({"tier - 1","tier - 2","tier - 3"},MATCH(MAX(COUNTIF('OG Hospitalisation Details'!H2260:H4602,{"tier - 1","tier - 2","tier - 3"})),COUNTIF('OG Hospitalisation Details'!H2260:H4602,{"tier - 1","tier - 2","tier - 3"}),0))} -> tier - 3 | K87: =IF('OG Hospitalisation Details'!I2260="?","Unknown",'OG Hospitalisation Details'!I2260) -> R1016 | L87: =DATEDIF(F87,DATE(2023,6,8),"Y") -> 50
A88: Id86 | B88: =VALUE(SUBSTITUTE(A88,"Id","")) -> 86 | C88: =IF('OG Hospitalisation Details'!B2259="?",ROUND(AVERAGE('OG Hospitalisation Details'!$B$2:$B$2344),0),'OG Hospitalisation Details'!B2259) -> 1972 | D88: =IF('OG Hospitalisation Details'!C2259="?","Sep",'OG Hospitalisation Details'!C2259) -> Aug | E88: 12 | F88: =DATE(C88,MONTH(1&D88),E88) -> 26523 | G88: 0 | H88: 41055.29 | I88: {=INDEX({"tier - 1","tier - 2","tier - 3"},MATCH(MAX(COUNTIF('OG Hospitalisation Details'!G2259:G4601,{"tier - 1","tier - 2","tier - 3"})),COUNTIF('OG Hospitalisation Details'!G2259:G4601,{"tier - 1","tier - 2","tier - 3"}),0))} -> tier - 1 | J88: {=INDEX({"tier - 1","tier - 2","tier - 3"},MATCH(MAX(COUNTIF('OG Hospitalisation Details'!H2259:H4601,{"tier - 1","tier - 2","tier - 3"})),COUNTIF('OG Hospitalisation Details'!H2259:H4601,{"tier - 1","tier - 2","tier - 3"}),0))} -> tier - 3 | K88: =IF('OG Hospitalisation Details'!I2259="?","Unknown",'OG Hospitalisation Details'!I2259) -> R1011 | L88: =DATEDIF(F88,DATE(2023,6,8),"Y") -> 50
A89: Id87 | B89: =VALUE(SUBSTITUTE(A89,"Id","")) -> 87 | C89: =IF('OG Hospitalisation Details'!B2258="?",ROUND(AVERAGE('OG Hospitalisation Details'!$B$2:$B$2344),0),'OG Hospitalisation Details'!B2258) -> 1979 | D89: =IF('OG Hospitalisation Details'!C2258="?","Sep",'OG Hospitalisation Details'!C2258) -> Oct | E89: 11 | F89: =DATE(C89,MONTH(1&D89),E89) -> 29139 | G89: 1 | H89: 41034.22 | I89: {=INDEX({"tier - 1","tier - 2","tier - 3"},MATCH(MAX(COUNTIF('OG Hospitalisation Details'!G2258:G4600,{"tier - 1","tier - 2","tier - 3"})),COUNTIF('OG Hospitalisation Details'!G2258:G4600,{"tier - 1","tier - 2","tier - 3"}),0))} -> tier - 1 | J89: {=INDEX({"tier - 1","tier - 2","tier - 3"},MATCH(MAX(COUNTIF('OG Hospitalisation Details'!H2258:H4600,{"tier - 1","tier - 2","tier - 3"})),COUNTIF('OG Hospitalisation Details'!H2258:H4600,{"tier - 1","tier - 2","tier - 3"}),0))} -> tier - 3 | K89: =IF('OG Hospitalisation Details'!I2258="?","Unknown",'OG Hospitalisation Details'!I2258) -> R1017 | L89: =DATEDIF(F89,DATE(2023,6,8),"Y") -> 43
A90: Id88 | B90: =VALUE(SUBSTITUTE(A90,"Id","")) -> 88 | C90: =IF('OG Hospitalisation Details'!B2257="?",ROUND(AVERAGE('OG Hospitalisation Details'!$B$2:$B$2344),0),'OG Hospitalisation Details'!B2257) -> 1974 | D90: =IF('OG Hospitalisation Details'!C2257="?","Sep",'OG Hospitalisation Details'!C2257) -> Jun | E90: 5 | F90: =DATE(C90,MONTH(1&D90),E90) -> 27185 | G90: 0 | H90: 40974.16 | I90: {=INDEX({"tier - 1","tier - 2","tier - 3"},MATCH(MAX(COUNTIF('OG Hospitalisation Details'!G2257:G4599,{"tier - 1","tier - 2","tier - 3"})),COUNTIF('OG Hospitalisation Details'!G2257:G4599,{"tier - 1","tier - 2","tier - 3"}),0))} -> tier - 1 | J90: {=INDEX({"tier - 1","tier - 2","tier - 3"},MATCH(MAX(COUNTIF('OG Hospitalisation Details'!H2257:H4599,{"tier - 1","tier - 2","tier - 3"})),COUNTIF('OG Hospitalisation Details'!H2257:H4599,{"tier - 1","tier - 2","tier - 3"}),0))} -> tier - 3 | K90: =IF('OG Hospitalisation Details'!I2257="?","Unknown",'OG Hospitalisation Details'!I2257) -> R1013 | L90: =DATEDIF(F90,DATE(2023,6,8),"Y") -> 49
A91: Id89 | B91: =VALUE(SUBSTITUTE(A91,"Id","")) -> 89 | C91: =IF('OG Hospitalisation Details'!B2256="?",ROUND(AVERAGE('OG Hospitalisation Details'!$B$2:$B$2344),0),'OG Hospitalisation Details'!B2256) -> 1983 | D91: =IF('OG Hospitalisation Details'!C2256="?","Sep",'OG Hospitalisation Details'!C2256) -> Sep | E91: 8 | F91: =DATE(C91,MONTH(1&D91),E91) -> 30567 | G91: 3 | H91: 40961.29 | I91: {=INDEX({"tier - 1","tier - 2","tier - 3"},MATCH(MAX(COUNTIF('OG Hospitalisation Details'!G2256:G4598,{"tier - 1","tier - 2","tier - 3"})),COUNTIF('OG Hospitalisation Details'!G2256:G4598,{"tier - 1","tier - 2","tier - 3"}),0))} -> tier - 1 | J91: {=INDEX({"tier - 1","tier - 2","tier - 3"},MATCH(MAX(COUNTIF('OG Hospitalisation Details'!H2256:H4598,{"tier - 1","tier - 2","tier - 3"})),COUNTIF('OG Hospitalisation Details'!H2256:H4598,{"tier - 1","tier - 2","tier - 3"}),0))} -> tier - 3 | K91: =IF('OG Hospitalisation Details'!I2256="?","Unknown",'OG Hospitalisation Details'!I2256) -> R1011 | L91: =DATEDIF(F91,DATE(2023,6,8),"Y") -> 39
A92: Id90 | B92: =VALUE(SUBSTITUTE(A92,"Id","")) -> 90 | C92: =IF('OG Hospitalisation Details'!B2255="?",ROUND(AVERAGE('OG Hospitalisation Details'!$B$2:$B$2344),0),'OG Hospitalisation Details'!B2255) -> 1979 | D92: =IF('OG Hospitalisation Details'!C2255="?","Sep",'OG Hospitalisation Details'!C2255) -> Sep | E92: 16 | F92: =DATE(C92,MONTH(1&D92),E92) -> 29114 | G92: 3 | H92: 40941.29 | I92: {=INDEX({"tier - 1","tier - 2","tier - 3"},MATCH(MAX(COUNTIF('OG Hospitalisation Details'!G2255:G4597,{"tier - 1","tier - 2","tier - 3"})),COUNTIF('OG Hospitalisation Details'!G2255:G4597,{"tier - 1","tier - 2","tier - 3"}),0))} -> tier - 1 | J92: {=INDEX({"tier - 1","tier - 2","tier - 3"},MATCH(MAX(COUNTIF('OG Hospitalisation Details'!H2255:H4597,{"tier - 1","tier - 2","tier - 3"})),COUNTIF('OG Hospitalisation Details'!H2255:H4597,{"tier - 1","tier - 2","tier - 3"}),0))} -> tier - 2 | K92: =IF('OG Hospitalisation Details'!I2255="?","Unknown",'OG Hospitalisation Details'!I2255) -> R1013 | L92: =DATEDIF(F92,DATE(2023,6,8),"Y") -> 43
A93: Id91 | B93: =VALUE(SUBSTITUTE(A93,"Id","")) -> 91 | C93: =IF('OG Hospitalisation Details'!B2254="?",ROUND(AVERAGE('OG Hospitalisation Details'!$B$2:$B$2344),0),'OG Hospitalisation Details'!B2254) -> 1992 | D93: =IF('OG Hospitalisation Details'!C2254="?","Sep",'OG Hospitalisation Details'!C2254) -> Aug | E93: 4 | F93: =DATE(C93,MONTH(1&D93),E93) -> 33820 | G93: 3 | H93: 40932.43 | I93: {=INDEX({"tier - 1","tier - 2","tier - 3"},MATCH(MAX(COUNTIF('OG Hospitalisation Details'!G2254:G4596,{"tier - 1","tier - 2","tier - 3"})),COUNTIF('OG Hospitalisation Details'!G2254:G4596,{"tier - 1","tier - 2","tier - 3"}),0))} -> tier - 1 | J93: {=INDEX({"tier - 1","tier - 2","tier - 3"},MATCH(MAX(COUNTIF('OG Hospitalisation Details'!H2254:H4596,{"tier - 1","tier - 2","tier - 3"})),COUNTIF('OG Hospitalisation Details'!H2254:H4596,{"tier - 1","tier - 2","tier - 3"}),0))} -> tier - 2 | K93: =IF('OG Hospitalisation Details'!I2254="?","Unknown",'OG Hospitalisation Details'!I2254) -> R1013 | L93: =DATEDIF(F93,DATE(2023,6,8),"Y") -> 30
A94: Id92 | B94: =VALUE(SUBSTITUTE(A94,"Id","")) -> 92 | C94: =IF('OG Hospitalisation Details'!B2253="?",ROUND(AVERAGE('OG Hospitalisation Details'!$B$2:$B$2344),0),'OG Hospitalisation Details'!B2253) -> 1999 | D94: =IF('OG Hospitalisation Details'!C2253="?","Sep",'OG Hospitalisation Details'!C2253) -> Jul | E94: 2 | F94: =DATE(C94,MONTH(1&D94),E94) -> 36343 | G94: 1 | H94: 40904.2 | I94: {=INDEX({"tier - 1","tier - 2","tier - 3"},MATCH(MAX(COUNTIF('OG Hospitalisation Details'!G2253:G4595,{"tier - 1","tier - 2","tier - 3"})),COUNTIF('OG Hospitalisation Details'!G2253:G4595,{"tier - 1","tier - 2","tier - 3"}),0))} -> tier - 1 | J94: {=INDEX({"tier - 1","tier - 2","tier - 3"},MATCH(MAX(COUNTIF('OG Hospitalisation Details'!H2253:H4595,{"tier - 1","tier - 2","tier - 3"})),COUNTIF('OG Hospitalisation Details'!H2253:H4595,{"tier - 1","tier - 2","tier - 3"}),0))} -> tier - 2 | K94: =IF('OG Hospitalisation Details'!I2253="?","Unknown",'OG Hospitalisation Details'!I2253) -> R1024 | L94: =DATEDIF(F94,DATE(2023,6,8),"Y") -> 23
A95: Id93 | B95: =VALUE(SUBSTITUTE(A95,"Id","")) -> 93 | C95: =IF('OG Hospitalisation Details'!B2252="?",ROUND(AVERAGE('OG Hospitalisation Details'!$B$2:$B$2344),0),'OG Hospitalisation Details'!B2252) -> 1972 | D95: =IF('OG Hospitalisation Details'!C2252="?","Sep",'OG Hospitalisation Details'!C2252) -> Jun | E95: 10 | F95: =DATE(C95,MONTH(1&D95),E95) -> 26460 | G95: 0 | H95: 40817.85 | I95: {=INDEX({"tier - 1","tier - 2","tier - 3"},MATCH(MAX(COUNTIF('OG Hospitalisation Details'!G2252:G4594,{"tier - 1","tier - 2","tier - 3"})),COUNTIF('OG Hospitalisation Details'!G2252:G4594,{"tier - 1","tier - 2","tier - 3"}),0))} -> tier - 1 | J95: {=INDEX({"tier - 1","tier - 2","tier - 3"},MATCH(MAX(COUNTIF('OG Hospitalisation Details'!H2252:H4594,{"tier - 1","tier - 2","tier - 3"})),COUNTIF('OG Hospitalisation Details'!H2252:H4594,{"tier - 1","tier - 2","tier - 3"}),0))} -> tier - 2 | K95: =IF('OG Hospitalisation Details'!I2252="?","Unknown",'OG Hospitalisation Details'!I2252) -> R1011 | L95: =DATEDIF(F95,DATE(2023,6,8),"Y") -> 50
A96: Id94 | B96: =VALUE(SUBSTITUTE(A96,"Id","")) -> 94 | C96: =IF('OG Hospitalisation Details'!B2251="?",ROUND(AVERAGE('OG Hospitalisation Details'!$B$2:$B$2344),0),'OG Hospitalisation Details'!B2251) -> 1976 | D96: =IF('OG Hospitalisation Details'!C2251="?","Sep",'OG Hospitalisation Details'!C2251) -> Dec | E96: 26 | F96: =DATE(C96,MONTH(1&D96),E96) -> 28120 | G96: 3 | H96: 40720.55 | I96: {=INDEX({"tier - 1","tier - 2","tier - 3"},MATCH(MAX(COUNTIF('OG Hospitalisation Details'!G2251:G4593,{"tier - 1","tier - 2","tier - 3"})),COUNTIF('OG Hospitalisation Details'!G2251:G4593,{"tier - 1","tier - 2","tier - 3"}),0))} -> tier - 1 | J96: {=INDEX({"tier - 1","tier - 2","tier - 3"},MATCH(MAX(COUNTIF('OG Hospitalisation Details'!H2251:H4593,{"tier - 1","tier - 2","tier - 3"})),COUNTIF('OG Hospitalisation Details'!H2251:H4593,{"tier - 1","tier - 2","tier - 3"}),0))} -> tier - 3 | K96: =IF('OG Hospitalisation Details'!I2251="?","Unknown",'OG Hospitalisation Details'!I2251) -> R1012 | L96: =DATEDIF(F96,DATE(2023,6,8),"Y") -> 46
A97: Id95 | B97: =VALUE(SUBSTITUTE(A97,"Id","")) -> 95 | C97: =IF('OG Hospitalisation Details'!B2250="?",ROUND(AVERAGE('OG Hospitalisation Details'!$B$2:$B$2344),0),'OG Hospitalisation Details'!B2250) -> 1970 | D97: =IF('OG Hospitalisation Details'!C2250="?","Sep",'OG Hospitalisation Details'!C2250) -> Sep | E97: 25 | F97: =DATE(C97,MONTH(1&D97),E97) -> 25836 | G97: 0 | H97: 40692.91 | I97: {=INDEX({"tier - 1","tier - 2","tier - 3"},MATCH(MAX(COUNTIF('OG Hospitalisation Details'!G2250:G4592,{"tier - 1","tier - 2","tier - 3"})),COUNTIF('OG Hospitalisation Details'!G2250:G4592,{"tier - 1","tier - 2","tier - 3"}),0))} -> tier - 1 | J97: {=INDEX({"tier - 1","tier - 2","tier - 3"},MATCH(MAX(COUNTIF('OG Hospitalisation Details'!H2250:H4592,{"tier - 1","tier - 2","tier - 3"})),COUNTIF('OG Hospitalisation Details'!H2250:H4592,{"tier - 1","tier - 2","tier - 3"}),0))} -> tier - 3 | K97: =IF('OG Hospitalisation Details'!I2250="?","Unknown",'OG Hospitalisation Details'!I2250) -> R1011 | L97: =DATEDIF(F97,DATE(2023,6,8),"Y") -> 52
A98: Id96 | B98: =VALUE(SUBSTITUTE(A98,"Id","")) -> 96 | C98: =IF('OG Hospitalisation Details'!B2249="?",ROUND(AVERAGE('OG Hospitalisation Details'!$B$2:$B$2344),0),'OG Hospitalisation Details'!B2249) -> 1975 | D98: =IF('OG Hospitalisation Details'!C2249="?","Sep",'OG Hospitalisation Details'!C2249) -> Jul | E98: 10 | F98: =DATE(C98,MONTH(1&D98),E98) -> 27585 | G98: 1 | H98: 40590.55 | I98: {=INDEX({"tier - 1","tier - 2","tier - 3"},MATCH(MAX(COUNTIF('OG Hospitalisation Details'!G2249:G4591,{"tier - 1","tier - 2","tier - 3"})),COUNTIF('OG Hospitalisation Details'!G2249:G4591,{"tier - 1","tier - 2","tier - 3"}),0))} -> tier - 1 | J98: {=INDEX({"tier - 1","tier - 2","tier - 3"},MATCH(MAX(COUNTIF('OG Hospitalisation Details'!H2249:H4591,{"tier - 1","tier - 2","tier - 3"})),COUNTIF('OG Hospitalisation Details'!H2249:H4591,{"tier - 1","tier - 2","tier - 3"}),0))} -> tier - 3 | K98: =IF('OG Hospitalisation Details'!I2249="?","Unknown",'OG Hospitalisation Details'!I2249) -> R1012 | L98: =DATEDIF(F98,DATE(2023,6,8),"Y") -> 47
A99: Id97 | B99: =VALUE(SUBSTITUTE(A99,"Id","")) -> 97 | C99: =IF('OG Hospitalisation Details'!B2248="?",ROUND(AVERAGE('OG Hospitalisation Details'!$B$2:$B$2344),0),'OG Hospitalisation Details'!B2248) -> 1985 | D99: =IF('OG Hospitalisation Details'!C2248="?","Sep",'OG Hospitalisation Details'!C2248) -> Nov | E99: 3 | F99: =DATE(C99,MONTH(1&D99),E99) -> 31354 | G99: 0 | H99: 40419.02 | I99: {=INDEX({"tier - 1","tier - 2","tier - 3"},MATCH(MAX(COUNTIF('OG Hospitalisation Details'!G2248:G4590,{"tier - 1","tier - 2","tier - 3"})),COUNTIF('OG Hospitalisation Details'!G2248:G4590,{"tier - 1","tier - 2","tier - 3"}),0))} -> tier - 1 | J99: {=INDEX({"tier - 1","tier - 2","tier - 3"},MATCH(MAX(COUNTIF('OG Hospitalisation Details'!H2248:H4590,{"tier - 1","tier - 2","tier - 3"})),COUNTIF('OG Hospitalisation Details'!H2248:H4590,{"tier - 1","tier - 2","tier - 3"}),0))} -> tier - 3 | K99: =IF('OG Hospitalisation Details'!I2248="?","Unknown",'OG Hospitalisation Details'!I2248) -> R1013 | L99: =DATEDIF(F99,DATE(2023,6,8),"Y") -> 37
A100: Id98 | B100: =VALUE(SUBSTITUTE(A100,"Id","")) -> 98 | C100: =IF('OG Hospitalisation Details'!B2247="?",ROUND(AVERAGE('OG Hospitalisation Details'!$B$2:$B$2344),0),'OG Hospitalisation Details'!B2247) -> 1966 | D100: =IF('OG Hospitalisation Details'!C2247="?","Sep",'OG Hospitalisation Details'!C2247) -> Aug | E100: 12 | F100: =DATE(C100,MONTH(1&D100),E100) -> 24331 | G100: 0 | H100: 40373.74 | I100: {=INDEX({"tier - 1","tier - 2","tier - 3"},MATCH(MAX(COUNTIF('OG Hospitalisation Details'!G2247:G4589,{"tier - 1","tier - 2","tier - 3"})),COUNTIF('OG Hospitalisation Details'!G2247:G4589,{"tier - 1","tier - 2","tier - 3"}),0))} -> tier - 1 | J100: {=INDEX({"tier - 1","tier - 2","tier - 3"},MATCH(MAX(COUNTIF('OG Hospitalisation Details'!H2247:H4589,{"tier - 1","tier - 2","tier - 3"})),COUNTIF('OG Hospitalisation Details'!H2247:H4589,{"tier - 1","tier - 2","tier - 3"}),0))} -> tier - 3 | K100: =IF('OG Hospitalisation Details'!I2247="?","Unknown",'OG Hospitalisation Details'!I2247) -> R1011 | L100: =DATEDIF(F100,DATE(2023,6,8),"Y") -> 56
...

Sheet Working Sheet
B1: Customer ID | C1: BMI | D1: HBA1C | E1: Heart Issues | F1: Any Transplants | G1: Cancer history | H1: NumberOfMajorSurgeries | I1: smoker
A2: Medical Examinations | B2: =COUNTIF('OG Medical Examinations'!A:A,"?") -> 0 | C2: =COUNTIF('OG Medical Examinations'!B:B,"?") -> 0 | D2: =COUNTIF('OG Medical Examinations'!C:C,"?") -> 0 | E2: =COUNTIF('OG Medical Examinations'!D:D,"?") -> 0 | F2: =COUNTIF('OG Medical Examinations'!E:E,"?") -> 0 | G2: =COUNTIF('OG Medical Examinations'!F:F,"?") -> 0 | H2: =COUNTIF('OG Medical Examinations'!G:G,"?") -> 0 | I2: =COUNTIF('OG Medical Examinations'!H:H,"?") -> 2
B3: =COUNTBLANK('OG Medical Examinations'!A2:A2336) -> 0 | C3: =COUNTBLANK('OG Medical Examinations'!B2:B2336) -> 0 | D3: =COUNTBLANK('OG Medical Examinations'!C2:C2336) -> 0 | E3: =COUNTBLANK('OG Medical Examinations'!D2:D2336) -> 0 | F3: =COUNTBLANK('OG Medical Examinations'!E2:E2336) -> 0 | G3: =COUNTBLANK('OG Medical Examinations'!F2:F2336) -> 0 | H3: =COUNTBLANK('OG Medical Examinations'!G2:G2336) -> 0 | I3: =COUNTBLANK('OG Medical Examinations'!H2:H2336) -> 0
B4: Customer ID | C4: year | D4: month | E4: date | F4: children | G4: charges | H4: Hospital tier | I4: City tier | J4: State ID
A5: Hospitalisation Details | B5: =COUNTIF('OG Hospitalisation Details'!B:B,"?") -> 2 | C5: =COUNTIF('OG Hospitalisation Details'!C:C,"?") -> 3 | D5: =COUNTIF('OG Hospitalisation Details'!D:D,"?") -> 0 | E5: =COUNTIF('OG Hospitalisation Details'!E:E,"?") -> 0 | F5: =COUNTIF('OG Hospitalisation Details'!F:F,"?") -> 0 | G5: =COUNTIF('OG Hospitalisation Details'!G:G,"?") -> 1 | H5: =COUNTIF('OG Hospitalisation Details'!H:H,"?") -> 1 | I5: =COUNTIF('OG Hospitalisation Details'!I:I,"?") -> 2 | J5: =COUNTIF('OG Hospitalisation Details'!J:J,"?") -> 0
B6: =COUNTBLANK('OG Hospitalisation Details'!A2:A2344) -> 0 | C6: =COUNTBLANK('OG Hospitalisation Details'!B2:B2344) -> 0 | D6: =COUNTBLANK('OG Hospitalisation Details'!C2:C2344) -> 0 | E6: =COUNTBLANK('OG Hospitalisation Details'!D2:D2344) -> 0 | F6: =COUNTBLANK('OG Hospitalisation Details'!E2:E2344) -> 0 | G6: =COUNTBLANK('OG Hospitalisation Details'!F2:F2344) -> 0 | H6: =COUNTBLANK('OG Hospitalisation Details'!G2:G2344) -> 0 | I6: =COUNTBLANK('OG Hospitalisation Details'!H2:H2344) -> 0 | J6: =COUNTBLANK('OG Hospitalisation Details'!I2:I2344) -> 0
A9: Most Frequent Tier | B9: Tier 1 | C9: Tier 2 | D9: Tire 3
B10: =COUNTIF('OG Hospitalisation Details'!G2:G2344,"Tier - 1") -> 309 | C10: =COUNTIF('OG Hospitalisation Details'!G2:G2344,"Tier - 2") -> 1339 | D10: =COUNTIF('OG Hospitalisation Details'!G2:G2344,"Tier - 3") -> 694
B11: =COUNTIF('OG Hospitalisation Details'!H3:H2345,"Tier - 1") -> 734 | C11: =COUNTIF('OG Hospitalisation Details'!H3:H2345,"Tier - 2") -> 812 | D11: =COUNTIF('OG Hospitalisation Details'!H3:H2345,"Tier - 3") -> 795
A13: Medical Examinations 2 | B13: Yes | C13: No
B14: 1949 replacements | C14: 9724 replacements
A17: Customer ID | B17: First Name | C17: BMI | D17: HBA1C | E17: Heart Issues | F17: Any Transplants | G17: Cancer History | H17: Number of Major Surgeries | I17: Smoker | J17: Weight | K17: Status | L17: Diabetes Status | M17: Date of Birth | N17: Charges | O17: Hospital Tier | P17: City Tier | Q17: State ID | R17: and Age.
